Workbook

Sheet 1 · BBDD 2025 (insumo)
A1: País | B1: Caso | C1: Año | D1: Descripción breve | E1: Organización a cargo | F1: Tipo de Organización (2025) | G1: Tipo de Proceso | H1: Etapa de Participación | I1: Continuidad (2025) | J1: Tipo de Desarrollador | K1: Origen Desarrollador | L1: Tipos de IA (2025) | M1: Convocante 7-cat (recodificación 2026, BORRADOR) | N1: Nivel 0-3 (recodificación 2026, override aplicado) | O1: Nota recodificación | P1: norm proceso | Q1: norm etapa | R1: norm desarrollador | S1: norm origen | T1: norm sistemas IA | U1: norm convocante | V1: TP: Participación Digital (0/1) | W1: TP: Gobernanza Colaborativa (0/1) | X1: TP: Mini públicos (0/1) | Y1: TP: Referendos e Inic. Populares (0/1) | Z1: TP: Presupuestos Participativos (0/1) | AA1: ET: Planificación (0/1) | AB1: ET: Implementación (0/1) | AC1: ET: Análisis (0/1) | AD1: ET: Traducción Política (0/1) | AE1: ORG: Público (0/1) | AF1: ORG: Privado (0/1) | AG1: ORG: Mixto (0/1) | AH1: CONT: Uso único (0/1) | AI1: CONT: Plataforma (0/1) | AJ1: DEV: Industria (0/1) | AK1: DEV: Academia (0/1) | AL1: DEV: Gobierno (0/1) | AM1: DEV: Sociedad Civil (0/1) | AN1: ORIGEN: Nacional (0/1) | AO1: ORIGEN: Internacional (0/1) | AP1: CONV: gobierno local (0/1) | AQ1: CONV: gobierno nacional (0/1) | AR1: CONV: otra institución pública (0/1) | AS1: CONV: empresa (0/1) | AT1: CONV: universidad (0/1) | AU1: CONV: sociedad civil (0/1) | AV1: CONV: organización internacional (0/1) | AW1: Nivel efectivo | AX1: Clave combinación convocantes | AY1: Combinación 1ª aparición (país)
A2: BO | B2: Bolivia Conversa | C2: 2021 | D2: Plataforma de diálogo digital que emplea IA para procesar y agrupar aportaciones ciudadanas en tiempo real, retornando feedback inmediato y garantizando anonimato, con vistas a fomentar el reencuentro y la cohesión social en el país. | E2: Vicepresidencia del Estado Plurinacional de Bolivia y Sistema de Naciones Unidas en Bolivia | F2: Público | G2: Governanza Colaborativa | H2: Implementación, Análisis | I2: Uso único | J2: Gobierno | K2: Internacional | L2: NLP - Tópicos | M2: gobierno nacional; organización internacional | N2: 2 | P2: =";"&LOWER(SUBSTITUTE(SUBSTITUTE(SUBSTITUTE(G2,"; ",";"),", ",";"),",",";"))&";" -> ;governanza colaborativa; | Q2: =";"&LOWER(SUBSTITUTE(SUBSTITUTE(SUBSTITUTE(H2,"; ",";"),", ",";"),",",";"))&";" -> ;implementación;análisis; | R2: =";"&LOWER(SUBSTITUTE(SUBSTITUTE(SUBSTITUTE(J2,"; ",";"),", ",";"),",",";"))&";" -> ;gobierno; | S2: =";"&LOWER(SUBSTITUTE(SUBSTITUTE(SUBSTITUTE(K2,"; ",";"),", ",";"),",",";"))&";" -> ;internacional; | T2: =";"&LOWER(SUBSTITUTE(SUBSTITUTE(SUBSTITUTE(L2,"; ",";"),", ",";"),",",";"))&";" -> ;nlp - tópicos; | U2: =";"&LOWER(SUBSTITUTE(SUBSTITUTE(SUBSTITUTE(M2,"; ",";"),", ",";"),",",";"))&";" -> ;gobierno nacional;organización internacional; | V2: =IF(ISNUMBER(SEARCH(";participación digital;",P2)),1,0) -> 0 | W2: =IF(OR(ISNUMBER(SEARCH(";governanza colaborativa;",P2)),ISNUMBER(SEARCH(";gobernanza colaborativa;",P2))),1,0) -> 1 | X2: =IF(ISNUMBER(SEARCH(";mini públicos;",P2)),1,0) -> 0 | Y2: =IF(ISNUMBER(SEARCH(";referendos e iniciativas populares;",P2)),1,0) -> 0 | Z2: =IF(ISNUMBER(SEARCH(";presupuestos participativos;",P2)),1,0) -> 0 | AA2: =IF(ISNUMBER(SEARCH("planif",Q2)),1,0) -> 0 | AB2: =IF(ISNUMBER(SEARCH("implement",Q2)),1,0) -> 1 | AC2: =IF(ISNUMBER(SEARCH("análisis",Q2)),1,0) -> 1 | AD2: =IF(ISNUMBER(SEARCH("traducción",Q2)),1,0) -> 0 | AE2: =IF(ISNUMBER(SEARCH("público",F2)),1,0) -> 1 | AF2: =IF(ISNUMBER(SEARCH("privado",F2)),1,0) -> 0 | AG2: =IF(ISNUMBER(SEARCH("mixto",F2)),1,0) -> 0 | AH2: =IF(ISNUMBER(SEARCH("único",I2)),1,0) -> 1 | AI2: =IF(ISNUMBER(SEARCH("plataforma",I2)),1,0) -> 0 | AJ2: =IF(ISNUMBER(SEARCH(";industria;",R2)),1,0) -> 0 | AK2: =IF(ISNUMBER(SEARCH(";academia;",R2)),1,0) -> 0 | AL2: =IF(ISNUMBER(SEARCH(";gobierno;",R2)),1,0) -> 1 | AM2: =IF(ISNUMBER(SEARCH(";sociedad civil;",R2)),1,0) -> 0 | AN2: =IF(ISNUMBER(SEARCH(";nacional;",S2)),1,0) -> 0 | AO2: =IF(ISNUMBER(SEARCH(";internacional;",S2)),1,0) -> 1 | AP2: =IF(ISNUMBER(SEARCH(";gobierno local;",U2)),1,0) -> 0 | AQ2: =IF(ISNUMBER(SEARCH(";gobierno nacional;",U2)),1,0) -> 1 | AR2: =IF(ISNUMBER(SEARCH(";otra institución pública;",U2)),1,0) -> 0 | AS2: =IF(ISNUMBER(SEARCH(";empresa;",U2)),1,0) -> 0 | AT2: =IF(ISNUMBER(SEARCH(";universidad;",U2)),1,0) -> 0 | AU2: =IF(ISNUMBER(SEARCH(";sociedad civil;",U2)),1,0) -> 0 | AV2: =IF(ISNUMBER(SEARCH(";organización internacional;",U2)),1,0) -> 1 | AW2: =IF(N2="","",IF(AND(N2=1,('3 · Cálculo 2025 · f. nueva'!$C$25-C2)>'3 · Cálculo 2025 · f. nueva'!$C$26),0,N2)) -> 2 | AX2: =IF(SUM(AP2:AV2)<2,"",IF(AP2=1,"GL+","")&IF(AQ2=1,"GN+","")&IF(AR2=1,"OIP+","")&IF(AS2=1,"EMP+","")&IF(AT2=1,"UNI+","")&IF(AU2=1,"SC+","")&IF(AV2=1,"OI+","")) -> GN+OI+ | AY2: =IF(AX2="",0,IF(COUNTIFS($A$1:A1,A2,$AX$1:AX1,AX2)=0,1,0)) -> 1
A3: BR | B3: Portal e-Cidadania: Marcado automático de respuestas ciudadanas en videos de audiencias públicas | C3: 2025 | D3: Implementación de IA para identificar y marcar en los videos de eventos las respuestas dadas a preguntas ciudadanas, incluso cuando estas no fueron respondidas directamente durante las audiencias. | E3: Senado Federal de Brasil | F3: Público | G3: Governanza Colaborativa | H3: Traducción Política | I3: Plataforma | J3: Gobierno | K3: Nacional | L3: Voz a Texto, LLM, NLP | M3: gobierno nacional | N3: 2 | O3: Plataforma activa; posible nivel 3 si se verifica recurrencia (override) | P3: =";"&LOWER(SUBSTITUTE(SUBSTITUTE(SUBSTITUTE(G3,"; ",";"),", ",";"),",",";"))&";" -> ;governanza colaborativa; | Q3: =";"&LOWER(SUBSTITUTE(SUBSTITUTE(SUBSTITUTE(H3,"; ",";"),", ",";"),",",";"))&";" -> ;traducción política; | R3: =";"&LOWER(SUBSTITUTE(SUBSTITUTE(SUBSTITUTE(J3,"; ",";"),", ",";"),",",";"))&";" -> ;gobierno; | S3: =";"&LOWER(SUBSTITUTE(SUBSTITUTE(SUBSTITUTE(K3,"; ",";"),", ",";"),",",";"))&";" -> ;nacional; | T3: =";"&LOWER(SUBSTITUTE(SUBSTITUTE(SUBSTITUTE(L3,"; ",";"),", ",";"),",",";"))&";" -> ;voz a texto;llm;nlp; | U3: =";"&LOWER(SUBSTITUTE(SUBSTITUTE(SUBSTITUTE(M3,"; ",";"),", ",";"),",",";"))&";" -> ;gobierno nacional; | V3: =IF(ISNUMBER(SEARCH(";participación digital;",P3)),1,0) -> 0 | W3: =IF(OR(ISNUMBER(SEARCH(";governanza colaborativa;",P3)),ISNUMBER(SEARCH(";gobernanza colaborativa;",P3))),1,0) -> 1 | X3: =IF(ISNUMBER(SEARCH(";mini públicos;",P3)),1,0) -> 0 | Y3: =IF(ISNUMBER(SEARCH(";referendos e iniciativas populares;",P3)),1,0) -> 0 | Z3: =IF(ISNUMBER(SEARCH(";presupuestos participativos;",P3)),1,0) -> 0 | AA3: =IF(ISNUMBER(SEARCH("planif",Q3)),1,0) -> 0 | AB3: =IF(ISNUMBER(SEARCH("implement",Q3)),1,0) -> 0 | AC3: =IF(ISNUMBER(SEARCH("análisis",Q3)),1,0) -> 0 | AD3: =IF(ISNUMBER(SEARCH("traducción",Q3)),1,0) -> 1 | AE3: =IF(ISNUMBER(SEARCH("público",F3)),1,0) -> 1 | AF3: =IF(ISNUMBER(SEARCH("privado",F3)),1,0) -> 0 | AG3: =IF(ISNUMBER(SEARCH("mixto",F3)),1,0) -> 0 | AH3: =IF(ISNUMBER(SEARCH("único",I3)),1,0) -> 0 | AI3: =IF(ISNUMBER(SEARCH("plataforma",I3)),1,0) -> 1 | AJ3: =IF(ISNUMBER(SEARCH(";industria;",R3)),1,0) -> 0 | AK3: =IF(ISNUMBER(SEARCH(";academia;",R3)),1,0) -> 0 | AL3: =IF(ISNUMBER(SEARCH(";gobierno;",R3)),1,0) -> 1 | AM3: =IF(ISNUMBER(SEARCH(";sociedad civil;",R3)),1,0) -> 0 | AN3: =IF(ISNUMBER(SEARCH(";nacional;",S3)),1,0) -> 1 | AO3: =IF(ISNUMBER(SEARCH(";internacional;",S3)),1,0) -> 0 | AP3: =IF(ISNUMBER(SEARCH(";gobierno local;",U3)),1,0) -> 0 | AQ3: =IF(ISNUMBER(SEARCH(";gobierno nacional;",U3)),1,0) -> 1 | AR3: =IF(ISNUMBER(SEARCH(";otra institución pública;",U3)),1,0) -> 0 | AS3: =IF(ISNUMBER(SEARCH(";empresa;",U3)),1,0) -> 0 | AT3: =IF(ISNUMBER(SEARCH(";universidad;",U3)),1,0) -> 0 | AU3: =IF(ISNUMBER(SEARCH(";sociedad civil;",U3)),1,0) -> 0 | AV3: =IF(ISNUMBER(SEARCH(";organización internacional;",U3)),1,0) -> 0 | AW3: =IF(N3="","",IF(AND(N3=1,('3 · Cálculo 2025 · f. nueva'!$C$25-C3)>'3 · Cálculo 2025 · f. nueva'!$C$26),0,N3)) -> 2 | AX3: =IF(SUM(AP3:AV3)<2,"",IF(AP3=1,"GL+","")&IF(AQ3=1,"GN+","")&IF(AR3=1,"OIP+","")&IF(AS3=1,"EMP+","")&IF(AT3=1,"UNI+","")&IF(AU3=1,"SC+","")&IF(AV3=1,"OI+","")) | AY3: =IF(AX3="",0,IF(COUNTIFS($A$1:A2,A3,$AX$1:AX2,AX3)=0,1,0)) -> 0
A4: BR | B4: Plan Plurianual de la ciudad de Natal | C4: 2025 | D4: Recolección de información a través de tres preguntas habilitadas por WhatsApp para diseñar el Plan Plurianual de la ciudad 2026-2029 | E4: Prefeitura Municipal de Natal, a través de la Secretaría Municipal de Planeamiento (SEMPLA) | F4: Público | G4: Governanza Colaborativa | H4: Implementación, Análisis | I4: Plataforma | J4: Gobierno, Industria | K4: Nacional, Internacional | L4: LLM, NLP | M4: gobierno local | N4: 2 | P4: =";"&LOWER(SUBSTITUTE(SUBSTITUTE(SUBSTITUTE(G4,"; ",";"),", ",";"),",",";"))&";" -> ;governanza colaborativa; | Q4: =";"&LOWER(SUBSTITUTE(SUBSTITUTE(SUBSTITUTE(H4,"; ",";"),", ",";"),",",";"))&";" -> ;implementación;análisis; | R4: =";"&LOWER(SUBSTITUTE(SUBSTITUTE(SUBSTITUTE(J4,"; ",";"),", ",";"),",",";"))&";" -> ;gobierno;industria; | S4: =";"&LOWER(SUBSTITUTE(SUBSTITUTE(SUBSTITUTE(K4,"; ",";"),", ",";"),",",";"))&";" -> ;nacional;internacional; | T4: =";"&LOWER(SUBSTITUTE(SUBSTITUTE(SUBSTITUTE(L4,"; ",";"),", ",";"),",",";"))&";" -> ;llm;nlp; | U4: =";"&LOWER(SUBSTITUTE(SUBSTITUTE(SUBSTITUTE(M4,"; ",";"),", ",";"),",",";"))&";" -> ;gobierno local; | V4: =IF(ISNUMBER(SEARCH(";participación digital;",P4)),1,0) -> 0 | W4: =IF(OR(ISNUMBER(SEARCH(";governanza colaborativa;",P4)),ISNUMBER(SEARCH(";gobernanza colaborativa;",P4))),1,0) -> 1 | X4: =IF(ISNUMBER(SEARCH(";mini públicos;",P4)),1,0) -> 0 | Y4: =IF(ISNUMBER(SEARCH(";referendos e iniciativas populares;",P4)),1,0) -> 0 | Z4: =IF(ISNUMBER(SEARCH(";presupuestos participativos;",P4)),1,0) -> 0 | AA4: =IF(ISNUMBER(SEARCH("planif",Q4)),1,0) -> 0 | AB4: =IF(ISNUMBER(SEARCH("implement",Q4)),1,0) -> 1 | AC4: =IF(ISNUMBER(SEARCH("análisis",Q4)),1,0) -> 1 | AD4: =IF(ISNUMBER(SEARCH("traducción",Q4)),1,0) -> 0 | AE4: =IF(ISNUMBER(SEARCH("público",F4)),1,0) -> 1 | AF4: =IF(ISNUMBER(SEARCH("privado",F4)),1,0) -> 0 | AG4: =IF(ISNUMBER(SEARCH("mixto",F4)),1,0) -> 0 | AH4: =IF(ISNUMBER(SEARCH("único",I4)),1,0) -> 0 | AI4: =IF(ISNUMBER(SEARCH("plataforma",I4)),1,0) -> 1 | AJ4: =IF(ISNUMBER(SEARCH(";industria;",R4)),1,0) -> 1 | AK4: =IF(ISNUMBER(SEARCH(";academia;",R4)),1,0) -> 0 | AL4: =IF(ISNUMBER(SEARCH(";gobierno;",R4)),1,0) -> 1 | AM4: =IF(ISNUMBER(SEARCH(";sociedad civil;",R4)),1,0) -> 0 | AN4: =IF(ISNUMBER(SEARCH(";nacional;",S4)),1,0) -> 1 | AO4: =IF(ISNUMBER(SEARCH(";internacional;",S4)),1,0) -> 1 | AP4: =IF(ISNUMBER(SEARCH(";gobierno local;",U4)),1,0) -> 1 | AQ4: =IF(ISNUMBER(SEARCH(";gobierno nacional;",U4)),1,0) -> 0 | AR4: =IF(ISNUMBER(SEARCH(";otra institución pública;",U4)),1,0) -> 0 | AS4: =IF(ISNUMBER(SEARCH(";empresa;",U4)),1,0) -> 0 | AT4: =IF(ISNUMBER(SEARCH(";universidad;",U4)),1,0) -> 0 | AU4: =IF(ISNUMBER(SEARCH(";sociedad civil;",U4)),1,0) -> 0 | AV4: =IF(ISNUMBER(SEARCH(";organización internacional;",U4)),1,0) -> 0 | AW4: =IF(N4="","",IF(AND(N4=1,('3 · Cálculo 2025 · f. nueva'!$C$25-C4)>'3 · Cálculo 2025 · f. nueva'!$C$26),0,N4)) -> 2 | AX4: =IF(SUM(AP4:AV4)<2,"",IF(AP4=1,"GL+","")&IF(AQ4=1,"GN+","")&IF(AR4=1,"OIP+","")&IF(AS4=1,"EMP+","")&IF(AT4=1,"UNI+","")&IF(AU4=1,"SC+","")&IF(AV4=1,"OI+","")) | AY4: =IF(AX4="",0,IF(COUNTIFS($A$1:A3,A4,$AX$1:AX3,AX4)=0,1,0)) -> 0
A5: BR | B5: Colab | C5: 2013 | D5: Colab es una plataforma GovTech que permite a los ciudadanos reportar problemas urbanos, sugerir ideas, participar en encuestas y votar en decisiones municipales. Utiliza IA para optimizar la gestión pública, automatizar procesos y mejorar la eficiencia en la prestación de servicios públicos. Entre los servicios que ofrece están las consultas. | E5: Colab | F5: Privado | G5: Governanza Colaborativa | H5: Análisis | I5: Plataforma | J5: Industria | K5: Nacional | L5: ML - Inespecífico | M5: empresa | N5: 2 | O5: Plataforma desde 2013; posible nivel 3 con evidencia de recurrencia | P5: =";"&LOWER(SUBSTITUTE(SUBSTITUTE(SUBSTITUTE(G5,"; ",";"),", ",";"),",",";"))&";" -> ;governanza colaborativa; | Q5: =";"&LOWER(SUBSTITUTE(SUBSTITUTE(SUBSTITUTE(H5,"; ",";"),", ",";"),",",";"))&";" -> ;análisis; | R5: =";"&LOWER(SUBSTITUTE(SUBSTITUTE(SUBSTITUTE(J5,"; ",";"),", ",";"),",",";"))&";" -> ;industria; | S5: =";"&LOWER(SUBSTITUTE(SUBSTITUTE(SUBSTITUTE(K5,"; ",";"),", ",";"),",",";"))&";" -> ;nacional; | T5: =";"&LOWER(SUBSTITUTE(SUBSTITUTE(SUBSTITUTE(L5,"; ",";"),", ",";"),",",";"))&";" -> ;ml - inespecífico; | U5: =";"&LOWER(SUBSTITUTE(SUBSTITUTE(SUBSTITUTE(M5,"; ",";"),", ",";"),",",";"))&";" -> ;empresa; | V5: =IF(ISNUMBER(SEARCH(";participación digital;",P5)),1,0) -> 0 | W5: =IF(OR(ISNUMBER(SEARCH(";governanza colaborativa;",P5)),ISNUMBER(SEARCH(";gobernanza colaborativa;",P5))),1,0) -> 1 | X5: =IF(ISNUMBER(SEARCH(";mini públicos;",P5)),1,0) -> 0 | Y5: =IF(ISNUMBER(SEARCH(";referendos e iniciativas populares;",P5)),1,0) -> 0 | Z5: =IF(ISNUMBER(SEARCH(";presupuestos participativos;",P5)),1,0) -> 0 | AA5: =IF(ISNUMBER(SEARCH("planif",Q5)),1,0) -> 0 | AB5: =IF(ISNUMBER(SEARCH("implement",Q5)),1,0) -> 0 | AC5: =IF(ISNUMBER(SEARCH("análisis",Q5)),1,0) -> 1 | AD5: =IF(ISNUMBER(SEARCH("traducción",Q5)),1,0) -> 0 | AE5: =IF(ISNUMBER(SEARCH("público",F5)),1,0) -> 0 | AF5: =IF(ISNUMBER(SEARCH("privado",F5)),1,0) -> 1 | AG5: =IF(ISNUMBER(SEARCH("mixto",F5)),1,0) -> 0 | AH5: =IF(ISNUMBER(SEARCH("único",I5)),1,0) -> 0 | AI5: =IF(ISNUMBER(SEARCH("plataforma",I5)),1,0) -> 1 | AJ5: =IF(ISNUMBER(SEARCH(";industria;",R5)),1,0) -> 1 | AK5: =IF(ISNUMBER(SEARCH(";academia;",R5)),1,0) -> 0 | AL5: =IF(ISNUMBER(SEARCH(";gobierno;",R5)),1,0) -> 0 | AM5: =IF(ISNUMBER(SEARCH(";sociedad civil;",R5)),1,0) -> 0 | AN5: =IF(ISNUMBER(SEARCH(";nacional;",S5)),1,0) -> 1 | AO5: =IF(ISNUMBER(SEARCH(";internacional;",S5)),1,0) -> 0 | AP5: =IF(ISNUMBER(SEARCH(";gobierno local;",U5)),1,0) -> 0 | AQ5: =IF(ISNUMBER(SEARCH(";gobierno nacional;",U5)),1,0) -> 0 | AR5: =IF(ISNUMBER(SEARCH(";otra institución pública;",U5)),1,0) -> 0 | AS5: =IF(ISNUMBER(SEARCH(";empresa;",U5)),1,0) -> 1 | AT5: =IF(ISNUMBER(SEARCH(";universidad;",U5)),1,0) -> 0 | AU5: =IF(ISNUMBER(SEARCH(";sociedad civil;",U5)),1,0) -> 0 | AV5: =IF(ISNUMBER(SEARCH(";organización internacional;",U5)),1,0) -> 0 | AW5: =IF(N5="","",IF(AND(N5=1,('3 · Cálculo 2025 · f. nueva'!$C$25-C5)>'3 · Cálculo 2025 · f. nueva'!$C$26),0,N5)) -> 2 | AX5: =IF(SUM(AP5:AV5)<2,"",IF(AP5=1,"GL+","")&IF(AQ5=1,"GN+","")&IF(AR5=1,"OIP+","")&IF(AS5=1,"EMP+","")&IF(AT5=1,"UNI+","")&IF(AU5=1,"SC+","")&IF(AV5=1,"OI+","")) | AY5: =IF(AX5="",0,IF(COUNTIFS($A$1:A4,A5,$AX$1:AX4,AX5)=0,1,0)) -> 0
A6: BR | B6: ParticipACT Brasil | C6: 2018 | D6: ParticipAct es una plataforma brasileña de ciencia ciudadana de código abierto que permite a los ciudadanos reportar problemas urbanos directamente a las agencias públicas a través de una aplicación web y móvil. Utiliza inteligencia artificial para facilitar el registro de los reportes, analizar los datos y mejorar la comunicación con el público mediante chatbots, con el fin de fomentar la colaboración para resolver los problemas de la ciudad. | E6: ParticipAct | F6: Privado | G6: Governanza Colaborativa | H6: Análisis, Implementación, Traducción Política | I6: Plataforma | J6: Academia | K6: Nacional | L6: NLP, Chatbot - Inespecífico, ML - Inespecífico | M6: universidad | N6: 2 | O6: Convocante ambiguo: universidad vs sociedad civil | P6: =";"&LOWER(SUBSTITUTE(SUBSTITUTE(SUBSTITUTE(G6,"; ",";"),", ",";"),",",";"))&";" -> ;governanza colaborativa; | Q6: =";"&LOWER(SUBSTITUTE(SUBSTITUTE(SUBSTITUTE(H6,"; ",";"),", ",";"),",",";"))&";" -> ;análisis;implementación;traducción política; | R6: =";"&LOWER(SUBSTITUTE(SUBSTITUTE(SUBSTITUTE(J6,"; ",";"),", ",";"),",",";"))&";" -> ;academia; | S6: =";"&LOWER(SUBSTITUTE(SUBSTITUTE(SUBSTITUTE(K6,"; ",";"),", ",";"),",",";"))&";" -> ;nacional; | T6: =";"&LOWER(SUBSTITUTE(SUBSTITUTE(SUBSTITUTE(L6,"; ",";"),", ",";"),",",";"))&";" -> ;nlp;chatbot - inespecífico;ml - inespecífico; | U6: =";"&LOWER(SUBSTITUTE(SUBSTITUTE(SUBSTITUTE(M6,"; ",";"),", ",";"),",",";"))&";" -> ;universidad; | V6: =IF(ISNUMBER(SEARCH(";participación digital;",P6)),1,0) -> 0 | W6: =IF(OR(ISNUMBER(SEARCH(";governanza colaborativa;",P6)),ISNUMBER(SEARCH(";gobernanza colaborativa;",P6))),1,0) -> 1 | X6: =IF(ISNUMBER(SEARCH(";mini públicos;",P6)),1,0) -> 0 | Y6: =IF(ISNUMBER(SEARCH(";referendos e iniciativas populares;",P6)),1,0) -> 0 | Z6: =IF(ISNUMBER(SEARCH(";presupuestos participativos;",P6)),1,0) -> 0 | AA6: =IF(ISNUMBER(SEARCH("planif",Q6)),1,0) -> 0 | AB6: =IF(ISNUMBER(SEARCH("implement",Q6)),1,0) -> 1 | AC6: =IF(ISNUMBER(SEARCH("análisis",Q6)),1,0) -> 1 | AD6: =IF(ISNUMBER(SEARCH("traducción",Q6)),1,0) -> 1 | AE6: =IF(ISNUMBER(SEARCH("público",F6)),1,0) -> 0 | AF6: =IF(ISNUMBER(SEARCH("privado",F6)),1,0) -> 1 | AG6: =IF(ISNUMBER(SEARCH("mixto",F6)),1,0) -> 0 | AH6: =IF(ISNUMBER(SEARCH("único",I6)),1,0) -> 0 | AI6: =IF(ISNUMBER(SEARCH("plataforma",I6)),1,0) -> 1 | AJ6: =IF(ISNUMBER(SEARCH(";industria;",R6)),1,0) -> 0 | AK6: =IF(ISNUMBER(SEARCH(";academia;",R6)),1,0) -> 1 | AL6: =IF(ISNUMBER(SEARCH(";gobierno;",R6)),1,0) -> 0 | AM6: =IF(ISNUMBER(SEARCH(";sociedad civil;",R6)),1,0) -> 0 | AN6: =IF(ISNUMBER(SEARCH(";nacional;",S6)),1,0) -> 1 | AO6: =IF(ISNUMBER(SEARCH(";internacional;",S6)),1,0) -> 0 | AP6: =IF(ISNUMBER(SEARCH(";gobierno local;",U6)),1,0) -> 0 | AQ6: =IF(ISNUMBER(SEARCH(";gobierno nacional;",U6)),1,0) -> 0 | AR6: =IF(ISNUMBER(SEARCH(";otra institución pública;",U6)),1,0) -> 0 | AS6: =IF(ISNUMBER(SEARCH(";empresa;",U6)),1,0) -> 0 | AT6: =IF(ISNUMBER(SEARCH(";universidad;",U6)),1,0) -> 1 | AU6: =IF(ISNUMBER(SEARCH(";sociedad civil;",U6)),1,0) -> 0 | AV6: =IF(ISNUMBER(SEARCH(";organización internacional;",U6)),1,0) -> 0 | AW6: =IF(N6="","",IF(AND(N6=1,('3 · Cálculo 2025 · f. nueva'!$C$25-C6)>'3 · Cálculo 2025 · f. nueva'!$C$26),0,N6)) -> 2 | AX6: =IF(SUM(AP6:AV6)<2,"",IF(AP6=1,"GL+","")&IF(AQ6=1,"GN+","")&IF(AR6=1,"OIP+","")&IF(AS6=1,"EMP+","")&IF(AT6=1,"UNI+","")&IF(AU6=1,"SC+","")&IF(AV6=1,"OI+","")) | AY6: =IF(AX6="",0,IF(COUNTIFS($A$1:A5,A6,$AX$1:AX5,AX6)=0,1,0)) -> 0
A7: CL | B7: Cabildos 2016 | C7: 2016 | D7: Análisis de los cabildos del proceso constitucional en 2016 | E7: Biblioteca del Congreso Nacional | F7: Público | G7: Governanza Colaborativa | H7: Análisis | I7: Uso único | J7: Academia | K7: Nacional | L7: NLP - Tópicos | M7: otra institución pública | N7: 2 | O7: BCN: otra institución pública vs gobierno nacional | P7: =";"&LOWER(SUBSTITUTE(SUBSTITUTE(SUBSTITUTE(G7,"; ",";"),", ",";"),",",";"))&";" -> ;governanza colaborativa; | Q7: =";"&LOWER(SUBSTITUTE(SUBSTITUTE(SUBSTITUTE(H7,"; ",";"),", ",";"),",",";"))&";" -> ;análisis; | R7: =";"&LOWER(SUBSTITUTE(SUBSTITUTE(SUBSTITUTE(J7,"; ",";"),", ",";"),",",";"))&";" -> ;academia; | S7: =";"&LOWER(SUBSTITUTE(SUBSTITUTE(SUBSTITUTE(K7,"; ",";"),", ",";"),",",";"))&";" -> ;nacional; | T7: =";"&LOWER(SUBSTITUTE(SUBSTITUTE(SUBSTITUTE(L7,"; ",";"),", ",";"),",",";"))&";" -> ;nlp - tópicos; | U7: =";"&LOWER(SUBSTITUTE(SUBSTITUTE(SUBSTITUTE(M7,"; ",";"),", ",";"),",",";"))&";" -> ;otra institución pública; | V7: =IF(ISNUMBER(SEARCH(";participación digital;",P7)),1,0) -> 0 | W7: =IF(OR(ISNUMBER(SEARCH(";governanza colaborativa;",P7)),ISNUMBER(SEARCH(";gobernanza colaborativa;",P7))),1,0) -> 1 | X7: =IF(ISNUMBER(SEARCH(";mini públicos;",P7)),1,0) -> 0 | Y7: =IF(ISNUMBER(SEARCH(";referendos e iniciativas populares;",P7)),1,0) -> 0 | Z7: =IF(ISNUMBER(SEARCH(";presupuestos participativos;",P7)),1,0) -> 0 | AA7: =IF(ISNUMBER(SEARCH("planif",Q7)),1,0) -> 0 | AB7: =IF(ISNUMBER(SEARCH("implement",Q7)),1,0) -> 0 | AC7: =IF(ISNUMBER(SEARCH("análisis",Q7)),1,0) -> 1 | AD7: =IF(ISNUMBER(SEARCH("traducción",Q7)),1,0) -> 0 | AE7: =IF(ISNUMBER(SEARCH("público",F7)),1,0) -> 1 | AF7: =IF(ISNUMBER(SEARCH("privado",F7)),1,0) -> 0 | AG7: =IF(ISNUMBER(SEARCH("mixto",F7)),1,0) -> 0 | AH7: =IF(ISNUMBER(SEARCH("único",I7)),1,0) -> 1 | AI7: =IF(ISNUMBER(SEARCH("plataforma",I7)),1,0) -> 0 | AJ7: =IF(ISNUMBER(SEARCH(";industria;",R7)),1,0) -> 0 | AK7: =IF(ISNUMBER(SEARCH(";academia;",R7)),1,0) -> 1 | AL7: =IF(ISNUMBER(SEARCH(";gobierno;",R7)),1,0) -> 0 | AM7: =IF(ISNUMBER(SEARCH(";sociedad civil;",R7)),1,0) -> 0 | AN7: =IF(ISNUMBER(SEARCH(";nacional;",S7)),1,0) -> 1 | AO7: =IF(ISNUMBER(SEARCH(";internacional;",S7)),1,0) -> 0 | AP7: =IF(ISNUMBER(SEARCH(";gobierno local;",U7)),1,0) -> 0 | AQ7: =IF(ISNUMBER(SEARCH(";gobierno nacional;",U7)),1,0) -> 0 | AR7: =IF(ISNUMBER(SEARCH(";otra institución pública;",U7)),1,0) -> 1 | AS7: =IF(ISNUMBER(SEARCH(";empresa;",U7)),1,0) -> 0 | AT7: =IF(ISNUMBER(SEARCH(";universidad;",U7)),1,0) -> 0 | AU7: =IF(ISNUMBER(SEARCH(";sociedad civil;",U7)),1,0) -> 0 | AV7: =IF(ISNUMBER(SEARCH(";organización internacional;",U7)),1,0) -> 0 | AW7: =IF(N7="","",IF(AND(N7=1,('3 · Cálculo 2025 · f. nueva'!$C$25-C7)>'3 · Cálculo 2025 · f. nueva'!$C$26),0,N7)) -> 2 | AX7: =IF(SUM(AP7:AV7)<2,"",IF(AP7=1,"GL+","")&IF(AQ7=1,"GN+","")&IF(AR7=1,"OIP+","")&IF(AS7=1,"EMP+","")&IF(AT7=1,"UNI+","")&IF(AU7=1,"SC+","")&IF(AV7=1,"OI+","")) | AY7: =IF(AX7="",0,IF(COUNTIFS($A$1:A6,A7,$AX$1:AX6,AX7)=0,1,0)) -> 0
A8: CL | B8: Estudio dIAlogos - Percepciones de Futuro | C8: 2021 | D8: Estudio que utilizó distintas herramientas de IA para conocer las percepciones de futuro de la población chilena | E8: Fundación Encuentros del Futuro y Merlín Research | F8: Mixto | G8: Governanza Colaborativa | H8: Implementación, Análisis | I8: Uso único | J8: Industria | K8: Internacional | L8: NLP | M8: sociedad civil; empresa | N8: 2 | P8: =";"&LOWER(SUBSTITUTE(SUBSTITUTE(SUBSTITUTE(G8,"; ",";"),", ",";"),",",";"))&";" -> ;governanza colaborativa; | Q8: =";"&LOWER(SUBSTITUTE(SUBSTITUTE(SUBSTITUTE(H8,"; ",";"),", ",";"),",",";"))&";" -> ;implementación;análisis; | R8: =";"&LOWER(SUBSTITUTE(SUBSTITUTE(SUBSTITUTE(J8,"; ",";"),", ",";"),",",";"))&";" -> ;industria; | S8: =";"&LOWER(SUBSTITUTE(SUBSTITUTE(SUBSTITUTE(K8,"; ",";"),", ",";"),",",";"))&";" -> ;internacional; | T8: =";"&LOWER(SUBSTITUTE(SUBSTITUTE(SUBSTITUTE(L8,"; ",";"),", ",";"),",",";"))&";" -> ;nlp; | U8: =";"&LOWER(SUBSTITUTE(SUBSTITUTE(SUBSTITUTE(M8,"; ",";"),", ",";"),",",";"))&";" -> ;sociedad civil;empresa; | V8: =IF(ISNUMBER(SEARCH(";participación digital;",P8)),1,0) -> 0 | W8: =IF(OR(ISNUMBER(SEARCH(";governanza colaborativa;",P8)),ISNUMBER(SEARCH(";gobernanza colaborativa;",P8))),1,0) -> 1 | X8: =IF(ISNUMBER(SEARCH(";mini públicos;",P8)),1,0) -> 0 | Y8: =IF(ISNUMBER(SEARCH(";referendos e iniciativas populares;",P8)),1,0) -> 0 | Z8: =IF(ISNUMBER(SEARCH(";presupuestos participativos;",P8)),1,0) -> 0 | AA8: =IF(ISNUMBER(SEARCH("planif",Q8)),1,0) -> 0 | AB8: =IF(ISNUMBER(SEARCH("implement",Q8)),1,0) -> 1 | AC8: =IF(ISNUMBER(SEARCH("análisis",Q8)),1,0) -> 1 | AD8: =IF(ISNUMBER(SEARCH("traducción",Q8)),1,0) -> 0 | AE8: =IF(ISNUMBER(SEARCH("público",F8)),1,0) -> 0 | AF8: =IF(ISNUMBER(SEARCH("privado",F8)),1,0) -> 0 | AG8: =IF(ISNUMBER(SEARCH("mixto",F8)),1,0) -> 1 | AH8: =IF(ISNUMBER(SEARCH("único",I8)),1,0) -> 1 | AI8: =IF(ISNUMBER(SEARCH("plataforma",I8)),1,0) -> 0 | AJ8: =IF(ISNUMBER(SEARCH(";industria;",R8)),1,0) -> 1 | AK8: =IF(ISNUMBER(SEARCH(";academia;",R8)),1,0) -> 0 | AL8: =IF(ISNUMBER(SEARCH(";gobierno;",R8)),1,0) -> 0 | AM8: =IF(ISNUMBER(SEARCH(";sociedad civil;",R8)),1,0) -> 0 | AN8: =IF(ISNUMBER(SEARCH(";nacional;",S8)),1,0) -> 0 | AO8: =IF(ISNUMBER(SEARCH(";internacional;",S8)),1,0) -> 1 | AP8: =IF(ISNUMBER(SEARCH(";gobierno local;",U8)),1,0) -> 0 | AQ8: =IF(ISNUMBER(SEARCH(";gobierno nacional;",U8)),1,0) -> 0 | AR8: =IF(ISNUMBER(SEARCH(";otra institución pública;",U8)),1,0) -> 0 | AS8: =IF(ISNUMBER(SEARCH(";empresa;",U8)),1,0) -> 1 | AT8: =IF(ISNUMBER(SEARCH(";universidad;",U8)),1,0) -> 0 | AU8: =IF(ISNUMBER(SEARCH(";sociedad civil;",U8)),1,0) -> 1 | AV8: =IF(ISNUMBER(SEARCH(";organización internacional;",U8)),1,0) -> 0 | AW8: =IF(N8="","",IF(AND(N8=1,('3 · Cálculo 2025 · f. nueva'!$C$25-C8)>'3 · Cálculo 2025 · f. nueva'!$C$26),0,N8)) -> 2 | AX8: =IF(SUM(AP8:AV8)<2,"",IF(AP8=1,"GL+","")&IF(AQ8=1,"GN+","")&IF(AR8=1,"OIP+","")&IF(AS8=1,"EMP+","")&IF(AT8=1,"UNI+","")&IF(AU8=1,"SC+","")&IF(AV8=1,"OI+","")) -> EMP+SC+ | AY8: =IF(AX8="",0,IF(COUNTIFS($A$1:A7,A8,$AX$1:AX7,AX8)=0,1,0)) -> 1
A9: CL | B9: Tenemos que hablar de Chile | C9: 2021 | D9: Iniciativa de diálogo y participación llevada a cabo por la UCH y PUC en el contexto de manifestaciones sociales | E9: Universidad de Chile y Pontificia Universidad Católica de Chile | F9: Mixto | G9: Governanza Colaborativa | H9: Análisis | I9: Uso único | J9: Academia | K9: Nacional | L9: NLP - Tópicos | M9: universidad | N9: 2 | O9: Escenario B: caso en revisión (puede salir) | P9: =";"&LOWER(SUBSTITUTE(SUBSTITUTE(SUBSTITUTE(G9,"; ",";"),", ",";"),",",";"))&";" -> ;governanza colaborativa; | Q9: =";"&LOWER(SUBSTITUTE(SUBSTITUTE(SUBSTITUTE(H9,"; ",";"),", ",";"),",",";"))&";" -> ;análisis; | R9: =";"&LOWER(SUBSTITUTE(SUBSTITUTE(SUBSTITUTE(J9,"; ",";"),", ",";"),",",";"))&";" -> ;academia; | S9: =";"&LOWER(SUBSTITUTE(SUBSTITUTE(SUBSTITUTE(K9,"; ",";"),", ",";"),",",";"))&";" -> ;nacional; | T9: =";"&LOWER(SUBSTITUTE(SUBSTITUTE(SUBSTITUTE(L9,"; ",";"),", ",";"),",",";"))&";" -> ;nlp - tópicos; | U9: =";"&LOWER(SUBSTITUTE(SUBSTITUTE(SUBSTITUTE(M9,"; ",";"),", ",";"),",",";"))&";" -> ;universidad; | V9: =IF(ISNUMBER(SEARCH(";participación digital;",P9)),1,0) -> 0 | W9: =IF(OR(ISNUMBER(SEARCH(";governanza colaborativa;",P9)),ISNUMBER(SEARCH(";gobernanza colaborativa;",P9))),1,0) -> 1 | X9: =IF(ISNUMBER(SEARCH(";mini públicos;",P9)),1,0) -> 0 | Y9: =IF(ISNUMBER(SEARCH(";referendos e iniciativas populares;",P9)),1,0) -> 0 | Z9: =IF(ISNUMBER(SEARCH(";presupuestos participativos;",P9)),1,0) -> 0 | AA9: =IF(ISNUMBER(SEARCH("planif",Q9)),1,0) -> 0 | AB9: =IF(ISNUMBER(SEARCH("implement",Q9)),1,0) -> 0 | AC9: =IF(ISNUMBER(SEARCH("análisis",Q9)),1,0) -> 1 | AD9: =IF(ISNUMBER(SEARCH("traducción",Q9)),1,0) -> 0 | AE9: =IF(ISNUMBER(SEARCH("público",F9)),1,0) -> 0 | AF9: =IF(ISNUMBER(SEARCH("privado",F9)),1,0) -> 0 | AG9: =IF(ISNUMBER(SEARCH("mixto",F9)),1,0) -> 1 | AH9: =IF(ISNUMBER(SEARCH("único",I9)),1,0) -> 1 | AI9: =IF(ISNUMBER(SEARCH("plataforma",I9)),1,0) -> 0 | AJ9: =IF(ISNUMBER(SEARCH(";industria;",R9)),1,0) -> 0 | AK9: =IF(ISNUMBER(SEARCH(";academia;",R9)),1,0) -> 1 | AL9: =IF(ISNUMBER(SEARCH(";gobierno;",R9)),1,0) -> 0 | AM9: =IF(ISNUMBER(SEARCH(";sociedad civil;",R9)),1,0) -> 0 | AN9: =IF(ISNUMBER(SEARCH(";nacional;",S9)),1,0) -> 1 | AO9: =IF(ISNUMBER(SEARCH(";internacional;",S9)),1,0) -> 0 | AP9: =IF(ISNUMBER(SEARCH(";gobierno local;",U9)),1,0) -> 0 | AQ9: =IF(ISNUMBER(SEARCH(";gobierno nacional;",U9)),1,0) -> 0 | AR9: =IF(ISNUMBER(SEARCH(";otra institución pública;",U9)),1,0) -> 0 | AS9: =IF(ISNUMBER(SEARCH(";empresa;",U9)),1,0) -> 0 | AT9: =IF(ISNUMBER(SEARCH(";universidad;",U9)),1,0) -> 1 | AU9: =IF(ISNUMBER(SEARCH(";sociedad civil;",U9)),1,0) -> 0 | AV9: =IF(ISNUMBER(SEARCH(";organización internacional;",U9)),1,0) -> 0 | AW9: =IF(N9="","",IF(AND(N9=1,('3 · Cálculo 2025 · f. nueva'!$C$25-C9)>'3 · Cálculo 2025 · f. nueva'!$C$26),0,N9)) -> 2 | AX9: =IF(SUM(AP9:AV9)<2,"",IF(AP9=1,"GL+","")&IF(AQ9=1,"GN+","")&IF(AR9=1,"OIP+","")&IF(AS9=1,"EMP+","")&IF(AT9=1,"UNI+","")&IF(AU9=1,"SC+","")&IF(AV9=1,"OI+","")) | AY9: =IF(AX9="",0,IF(COUNTIFS($A$1:A8,A9,$AX$1:AX8,AX9)=0,1,0)) -> 0
A10: CL | B10: Jornada de Escucha Lanzamiento Instituto de Políticas Públicas UNAB | C10: 2022 | D10: Jornadas de diálogo de la comunidad académica y otos stakeholders. | E10: Universidad Andres Bello | F10: Privado | G10: Governanza Colaborativa | H10: Análisis | I10: Uso único | J10: Industria | K10: Nacional | L10: NLP - Tópicos | M10: universidad | N10: 2 | P10: =";"&LOWER(SUBSTITUTE(SUBSTITUTE(SUBSTITUTE(G10,"; ",";"),", ",";"),",",";"))&";" -> ;governanza colaborativa; | Q10: =";"&LOWER(SUBSTITUTE(SUBSTITUTE(SUBSTITUTE(H10,"; ",";"),", ",";"),",",";"))&";" -> ;análisis; | R10: =";"&LOWER(SUBSTITUTE(SUBSTITUTE(SUBSTITUTE(J10,"; ",";"),", ",";"),",",";"))&";" -> ;industria; | S10: =";"&LOWER(SUBSTITUTE(SUBSTITUTE(SUBSTITUTE(K10,"; ",";"),", ",";"),",",";"))&";" -> ;nacional; | T10: =";"&LOWER(SUBSTITUTE(SUBSTITUTE(SUBSTITUTE(L10,"; ",";"),", ",";"),",",";"))&";" -> ;nlp - tópicos; | U10: =";"&LOWER(SUBSTITUTE(SUBSTITUTE(SUBSTITUTE(M10,"; ",";"),", ",";"),",",";"))&";" -> ;universidad; | V10: =IF(ISNUMBER(SEARCH(";participación digital;",P10)),1,0) -> 0 | W10: =IF(OR(ISNUMBER(SEARCH(";governanza colaborativa;",P10)),ISNUMBER(SEARCH(";gobernanza colaborativa;",P10))),1,0) -> 1 | X10: =IF(ISNUMBER(SEARCH(";mini públicos;",P10)),1,0) -> 0 | Y10: =IF(ISNUMBER(SEARCH(";referendos e iniciativas populares;",P10)),1,0) -> 0 | Z10: =IF(ISNUMBER(SEARCH(";presupuestos participativos;",P10)),1,0) -> 0 | AA10: =IF(ISNUMBER(SEARCH("planif",Q10)),1,0) -> 0 | AB10: =IF(ISNUMBER(SEARCH("implement",Q10)),1,0) -> 0 | AC10: =IF(ISNUMBER(SEARCH("análisis",Q10)),1,0) -> 1 | AD10: =IF(ISNUMBER(SEARCH("traducción",Q10)),1,0) -> 0 | AE10: =IF(ISNUMBER(SEARCH("público",F10)),1,0) -> 0 | AF10: =IF(ISNUMBER(SEARCH("privado",F10)),1,0) -> 1 | AG10: =IF(ISNUMBER(SEARCH("mixto",F10)),1,0) -> 0 | AH10: =IF(ISNUMBER(SEARCH("único",I10)),1,0) -> 1 | AI10: =IF(ISNUMBER(SEARCH("plataforma",I10)),1,0) -> 0 | AJ10: =IF(ISNUMBER(SEARCH(";industria;",R10)),1,0) -> 1 | AK10: =IF(ISNUMBER(SEARCH(";academia;",R10)),1,0) -> 0 | AL10: =IF(ISNUMBER(SEARCH(";gobierno;",R10)),1,0) -> 0 | AM10: =IF(ISNUMBER(SEARCH(";sociedad civil;",R10)),1,0) -> 0 | AN10: =IF(ISNUMBER(SEARCH(";nacional;",S10)),1,0) -> 1 | AO10: =IF(ISNUMBER(SEARCH(";internacional;",S10)),1,0) -> 0 | AP10: =IF(ISNUMBER(SEARCH(";gobierno local;",U10)),1,0) -> 0 | AQ10: =IF(ISNUMBER(SEARCH(";gobierno nacional;",U10)),1,0) -> 0 | AR10: =IF(ISNUMBER(SEARCH(";otra institución pública;",U10)),1,0) -> 0 | AS10: =IF(ISNUMBER(SEARCH(";empresa;",U10)),1,0) -> 0 | AT10: =IF(ISNUMBER(SEARCH(";universidad;",U10)),1,0) -> 1 | AU10: =IF(ISNUMBER(SEARCH(";sociedad civil;",U10)),1,0) -> 0 | AV10: =IF(ISNUMBER(SEARCH(";organización internacional;",U10)),1,0) -> 0 | AW10: =IF(N10="","",IF(AND(N10=1,('3 · Cálculo 2025 · f. nueva'!$C$25-C10)>'3 · Cálculo 2025 · f. nueva'!$C$26),0,N10)) -> 2 | AX10: =IF(SUM(AP10:AV10)<2,"",IF(AP10=1,"GL+","")&IF(AQ10=1,"GN+","")&IF(AR10=1,"OIP+","")&IF(AS10=1,"EMP+","")&IF(AT10=1,"UNI+","")&IF(AU10=1,"SC+","")&IF(AV10=1,"OI+","")) | AY10: =IF(AX10="",0,IF(COUNTIFS($A$1:A9,A10,$AX$1:AX9,AX10)=0,1,0)) -> 0
A11: CL | B11: Participación Ciudadana Proceso Constitucional | C11: 2023 | D11: Análisis de los resultados obtenidos de los Diálogos Ciudadanos Autoconvocados dentro del proceso constitucional | E11: Secretaría de Participación Ciudadana | F11: Público | G11: Governanza Colaborativa | H11: Análisis | I11: Uso único | J11: Industria | K11: Nacional | L11: NLP - Tópicos | M11: gobierno nacional | N11: 2 | O11: Aplica a los dos casos homónimos (autoconvocados y audiencias) | P11: =";"&LOWER(SUBSTITUTE(SUBSTITUTE(SUBSTITUTE(G11,"; ",";"),", ",";"),",",";"))&";" -> ;governanza colaborativa; | Q11: =";"&LOWER(SUBSTITUTE(SUBSTITUTE(SUBSTITUTE(H11,"; ",";"),", ",";"),",",";"))&";" -> ;análisis; | R11: =";"&LOWER(SUBSTITUTE(SUBSTITUTE(SUBSTITUTE(J11,"; ",";"),", ",";"),",",";"))&";" -> ;industria; | S11: =";"&LOWER(SUBSTITUTE(SUBSTITUTE(SUBSTITUTE(K11,"; ",";"),", ",";"),",",";"))&";" -> ;nacional; | T11: =";"&LOWER(SUBSTITUTE(SUBSTITUTE(SUBSTITUTE(L11,"; ",";"),", ",";"),",",";"))&";" -> ;nlp - tópicos; | U11: =";"&LOWER(SUBSTITUTE(SUBSTITUTE(SUBSTITUTE(M11,"; ",";"),", ",";"),",",";"))&";" -> ;gobierno nacional; | V11: =IF(ISNUMBER(SEARCH(";participación digital;",P11)),1,0) -> 0 | W11: =IF(OR(ISNUMBER(SEARCH(";governanza colaborativa;",P11)),ISNUMBER(SEARCH(";gobernanza colaborativa;",P11))),1,0) -> 1 | X11: =IF(ISNUMBER(SEARCH(";mini públicos;",P11)),1,0) -> 0 | Y11: =IF(ISNUMBER(SEARCH(";referendos e iniciativas populares;",P11)),1,0) -> 0 | Z11: =IF(ISNUMBER(SEARCH(";presupuestos participativos;",P11)),1,0) -> 0 | AA11: =IF(ISNUMBER(SEARCH("planif",Q11)),1,0) -> 0 | AB11: =IF(ISNUMBER(SEARCH("implement",Q11)),1,0) -> 0 | AC11: =IF(ISNUMBER(SEARCH("análisis",Q11)),1,0) -> 1 | AD11: =IF(ISNUMBER(SEARCH("traducción",Q11)),1,0) -> 0 | AE11: =IF(ISNUMBER(SEARCH("público",F11)),1,0) -> 1 | AF11: =IF(ISNUMBER(SEARCH("privado",F11)),1,0) -> 0 | AG11: =IF(ISNUMBER(SEARCH("mixto",F11)),1,0) -> 0 | AH11: =IF(ISNUMBER(SEARCH("único",I11)),1,0) -> 1 | AI11: =IF(ISNUMBER(SEARCH("plataforma",I11)),1,0) -> 0 | AJ11: =IF(ISNUMBER(SEARCH(";industria;",R11)),1,0) -> 1 | AK11: =IF(ISNUMBER(SEARCH(";academia;",R11)),1,0) -> 0 | AL11: =IF(ISNUMBER(SEARCH(";gobierno;",R11)),1,0) -> 0 | AM11: =IF(ISNUMBER(SEARCH(";sociedad civil;",R11)),1,0) -> 0 | AN11: =IF(ISNUMBER(SEARCH(";nacional;",S11)),1,0) -> 1 | AO11: =IF(ISNUMBER(SEARCH(";internacional;",S11)),1,0) -> 0 | AP11: =IF(ISNUMBER(SEARCH(";gobierno local;",U11)),1,0) -> 0 | AQ11: =IF(ISNUMBER(SEARCH(";gobierno nacional;",U11)),1,0) -> 1 | AR11: =IF(ISNUMBER(SEARCH(";otra institución pública;",U11)),1,0) -> 0 | AS11: =IF(ISNUMBER(SEARCH(";empresa;",U11)),1,0) -> 0 | AT11: =IF(ISNUMBER(SEARCH(";universidad;",U11)),1,0) -> 0 | AU11: =IF(ISNUMBER(SEARCH(";sociedad civil;",U11)),1,0) -> 0 | AV11: =IF(ISNUMBER(SEARCH(";organización internacional;",U11)),1,0) -> 0 | AW11: =IF(N11="","",IF(AND(N11=1,('3 · Cálculo 2025 · f. nueva'!$C$25-C11)>'3 · Cálculo 2025 · f. nueva'!$C$26),0,N11)) -> 2 | AX11: =IF(SUM(AP11:AV11)<2,"",IF(AP11=1,"GL+","")&IF(AQ11=1,"GN+","")&IF(AR11=1,"OIP+","")&IF(AS11=1,"EMP+","")&IF(AT11=1,"UNI+","")&IF(AU11=1,"SC+","")&IF(AV11=1,"OI+","")) | AY11: =IF(AX11="",0,IF(COUNTIFS($A$1:A10,A11,$AX$1:AX10,AX11)=0,1,0)) -> 0
A12: CL | B12: Participación Ciudadana Proceso Constitucional | C12: 2023 | D12: Análisis de las audiencias públicas dentro de los mecanismos de participación ciudadana en el proceso constitucional | E12: Secretaría de Participación Ciudadana | F12: Público | G12: Governanza Colaborativa | H12: Análisis | I12: Uso único | J12: Industria | K12: Nacional | L12: Voz a Texto, NLP - Tópicos | M12: gobierno nacional | N12: 2 | O12: Aplica a los dos casos homónimos (autoconvocados y audiencias) | P12: =";"&LOWER(SUBSTITUTE(SUBSTITUTE(SUBSTITUTE(G12,"; ",";"),", ",";"),",",";"))&";" -> ;governanza colaborativa; | Q12: =";"&LOWER(SUBSTITUTE(SUBSTITUTE(SUBSTITUTE(H12,"; ",";"),", ",";"),",",";"))&";" -> ;análisis; | R12: =";"&LOWER(SUBSTITUTE(SUBSTITUTE(SUBSTITUTE(J12,"; ",";"),", ",";"),",",";"))&";" -> ;industria; | S12: =";"&LOWER(SUBSTITUTE(SUBSTITUTE(SUBSTITUTE(K12,"; ",";"),", ",";"),",",";"))&";" -> ;nacional; | T12: =";"&LOWER(SUBSTITUTE(SUBSTITUTE(SUBSTITUTE(L12,"; ",";"),", ",";"),",",";"))&";" -> ;voz a texto;nlp - tópicos; | U12: =";"&LOWER(SUBSTITUTE(SUBSTITUTE(SUBSTITUTE(M12,"; ",";"),", ",";"),",",";"))&";" -> ;gobierno nacional; | V12: =IF(ISNUMBER(SEARCH(";participación digital;",P12)),1,0) -> 0 | W12: =IF(OR(ISNUMBER(SEARCH(";governanza colaborativa;",P12)),ISNUMBER(SEARCH(";gobernanza colaborativa;",P12))),1,0) -> 1 | X12: =IF(ISNUMBER(SEARCH(";mini públicos;",P12)),1,0) -> 0 | Y12: =IF(ISNUMBER(SEARCH(";referendos e iniciativas populares;",P12)),1,0) -> 0 | Z12: =IF(ISNUMBER(SEARCH(";presupuestos participativos;",P12)),1,0) -> 0 | AA12: =IF(ISNUMBER(SEARCH("planif",Q12)),1,0) -> 0 | AB12: =IF(ISNUMBER(SEARCH("implement",Q12)),1,0) -> 0 | AC12: =IF(ISNUMBER(SEARCH("análisis",Q12)),1,0) -> 1 | AD12: =IF(ISNUMBER(SEARCH("traducción",Q12)),1,0) -> 0 | AE12: =IF(ISNUMBER(SEARCH("público",F12)),1,0) -> 1 | AF12: =IF(ISNUMBER(SEARCH("privado",F12)),1,0) -> 0 | AG12: =IF(ISNUMBER(SEARCH("mixto",F12)),1,0) -> 0 | AH12: =IF(ISNUMBER(SEARCH("único",I12)),1,0) -> 1 | AI12: =IF(ISNUMBER(SEARCH("plataforma",I12)),1,0) -> 0 | AJ12: =IF(ISNUMBER(SEARCH(";industria;",R12)),1,0) -> 1 | AK12: =IF(ISNUMBER(SEARCH(";academia;",R12)),1,0) -> 0 | AL12: =IF(ISNUMBER(SEARCH(";gobierno;",R12)),1,0) -> 0 | AM12: =IF(ISNUMBER(SEARCH(";sociedad civil;",R12)),1,0) -> 0 | AN12: =IF(ISNUMBER(SEARCH(";nacional;",S12)),1,0) -> 1 | AO12: =IF(ISNUMBER(SEARCH(";internacional;",S12)),1,0) -> 0 | AP12: =IF(ISNUMBER(SEARCH(";gobierno local;",U12)),1,0) -> 0 | AQ12: =IF(ISNUMBER(SEARCH(";gobierno nacional;",U12)),1,0) -> 1 | AR12: =IF(ISNUMBER(SEARCH(";otra institución pública;",U12)),1,0) -> 0 | AS12: =IF(ISNUMBER(SEARCH(";empresa;",U12)),1,0) -> 0 | AT12: =IF(ISNUMBER(SEARCH(";universidad;",U12)),1,0) -> 0 | AU12: =IF(ISNUMBER(SEARCH(";sociedad civil;",U12)),1,0) -> 0 | AV12: =IF(ISNUMBER(SEARCH(";organización internacional;",U12)),1,0) -> 0 | AW12: =IF(N12="","",IF(AND(N12=1,('3 · Cálculo 2025 · f. nueva'!$C$25-C12)>'3 · Cálculo 2025 · f. nueva'!$C$26),0,N12)) -> 2 | AX12: =IF(SUM(AP12:AV12)<2,"",IF(AP12=1,"GL+","")&IF(AQ12=1,"GN+","")&IF(AR12=1,"OIP+","")&IF(AS12=1,"EMP+","")&IF(AT12=1,"UNI+","")&IF(AU12=1,"SC+","")&IF(AV12=1,"OI+","")) | AY12: =IF(AX12="",0,IF(COUNTIFS($A$1:A11,A12,$AX$1:AX11,AX12)=0,1,0)) -> 0
A13: CL | B13: La voz de los nuevos votantes | C13: 2023 | D13: Análisis de Lenguaje Natural para los audios transcritos de encuesta realizada en persona. | E13: Universidad Andres Bello | F13: Privado | G13: Governanza Colaborativa | H13: Implementación, Análisis | I13: Uso único | J13: Industria | K13: Nacional | L13: NLP - Tópicos | M13: universidad | N13: 2 | P13: =";"&LOWER(SUBSTITUTE(SUBSTITUTE(SUBSTITUTE(G13,"; ",";"),", ",";"),",",";"))&";" -> ;governanza colaborativa; | Q13: =";"&LOWER(SUBSTITUTE(SUBSTITUTE(SUBSTITUTE(H13,"; ",";"),", ",";"),",",";"))&";" -> ;implementación;análisis; | R13: =";"&LOWER(SUBSTITUTE(SUBSTITUTE(SUBSTITUTE(J13,"; ",";"),", ",";"),",",";"))&";" -> ;industria; | S13: =";"&LOWER(SUBSTITUTE(SUBSTITUTE(SUBSTITUTE(K13,"; ",";"),", ",";"),",",";"))&";" -> ;nacional; | T13: =";"&LOWER(SUBSTITUTE(SUBSTITUTE(SUBSTITUTE(L13,"; ",";"),", ",";"),",",";"))&";" -> ;nlp - tópicos; | U13: =";"&LOWER(SUBSTITUTE(SUBSTITUTE(SUBSTITUTE(M13,"; ",";"),", ",";"),",",";"))&";" -> ;universidad; | V13: =IF(ISNUMBER(SEARCH(";participación digital;",P13)),1,0) -> 0 | W13: =IF(OR(ISNUMBER(SEARCH(";governanza colaborativa;",P13)),ISNUMBER(SEARCH(";gobernanza colaborativa;",P13))),1,0) -> 1 | X13: =IF(ISNUMBER(SEARCH(";mini públicos;",P13)),1,0) -> 0 | Y13: =IF(ISNUMBER(SEARCH(";referendos e iniciativas populares;",P13)),1,0) -> 0 | Z13: =IF(ISNUMBER(SEARCH(";presupuestos participativos;",P13)),1,0) -> 0 | AA13: =IF(ISNUMBER(SEARCH("planif",Q13)),1,0) -> 0 | AB13: =IF(ISNUMBER(SEARCH("implement",Q13)),1,0) -> 1 | AC13: =IF(ISNUMBER(SEARCH("análisis",Q13)),1,0) -> 1 | AD13: =IF(ISNUMBER(SEARCH("traducción",Q13)),1,0) -> 0 | AE13: =IF(ISNUMBER(SEARCH("público",F13)),1,0) -> 0 | AF13: =IF(ISNUMBER(SEARCH("privado",F13)),1,0) -> 1 | AG13: =IF(ISNUMBER(SEARCH("mixto",F13)),1,0) -> 0 | AH13: =IF(ISNUMBER(SEARCH("único",I13)),1,0) -> 1 | AI13: =IF(ISNUMBER(SEARCH("plataforma",I13)),1,0) -> 0 | AJ13: =IF(ISNUMBER(SEARCH(";industria;",R13)),1,0) -> 1 | AK13: =IF(ISNUMBER(SEARCH(";academia;",R13)),1,0) -> 0 | AL13: =IF(ISNUMBER(SEARCH(";gobierno;",R13)),1,0) -> 0 | AM13: =IF(ISNUMBER(SEARCH(";sociedad civil;",R13)),1,0) -> 0 | AN13: =IF(ISNUMBER(SEARCH(";nacional;",S13)),1,0) -> 1 | AO13: =IF(ISNUMBER(SEARCH(";internacional;",S13)),1,0) -> 0 | AP13: =IF(ISNUMBER(SEARCH(";gobierno local;",U13)),1,0) -> 0 | AQ13: =IF(ISNUMBER(SEARCH(";gobierno nacional;",U13)),1,0) -> 0 | AR13: =IF(ISNUMBER(SEARCH(";otra institución pública;",U13)),1,0) -> 0 | AS13: =IF(ISNUMBER(SEARCH(";empresa;",U13)),1,0) -> 0 | AT13: =IF(ISNUMBER(SEARCH(";universidad;",U13)),1,0) -> 1 | AU13: =IF(ISNUMBER(SEARCH(";sociedad civil;",U13)),1,0) -> 0 | AV13: =IF(ISNUMBER(SEARCH(";organización internacional;",U13)),1,0) -> 0 | AW13: =IF(N13="","",IF(AND(N13=1,('3 · Cálculo 2025 · f. nueva'!$C$25-C13)>'3 · Cálculo 2025 · f. nueva'!$C$26),0,N13)) -> 2 | AX13: =IF(SUM(AP13:AV13)<2,"",IF(AP13=1,"GL+","")&IF(AQ13=1,"GN+","")&IF(AR13=1,"OIP+","")&IF(AS13=1,"EMP+","")&IF(AT13=1,"UNI+","")&IF(AU13=1,"SC+","")&IF(AV13=1,"OI+","")) | AY13: =IF(AX13="",0,IF(COUNTIFS($A$1:A12,A13,$AX$1:AX12,AX13)=0,1,0)) -> 0
A14: CL | B14: Un encuentro para la equidad de género en la movilidad en Chile | C14: 2023 | D14: Espacio participativo para levantar opiniones y propuestas de autoridades, miembros de la sociedad civil y académicos sobre la movilidad con perspectiva de género en Chile. | E14: Universidad Andres Bello | F14: Privado | G14: Governanza Colaborativa | H14: Análisis | I14: Uso único | J14: Industria | K14: Nacional | L14: NLP - Tópicos | M14: universidad | N14: 2 | P14: =";"&LOWER(SUBSTITUTE(SUBSTITUTE(SUBSTITUTE(G14,"; ",";"),", ",";"),",",";"))&";" -> ;governanza colaborativa; | Q14: =";"&LOWER(SUBSTITUTE(SUBSTITUTE(SUBSTITUTE(H14,"; ",";"),", ",";"),",",";"))&";" -> ;análisis; | R14: =";"&LOWER(SUBSTITUTE(SUBSTITUTE(SUBSTITUTE(J14,"; ",";"),", ",";"),",",";"))&";" -> ;industria; | S14: =";"&LOWER(SUBSTITUTE(SUBSTITUTE(SUBSTITUTE(K14,"; ",";"),", ",";"),",",";"))&";" -> ;nacional; | T14: =";"&LOWER(SUBSTITUTE(SUBSTITUTE(SUBSTITUTE(L14,"; ",";"),", ",";"),",",";"))&";" -> ;nlp - tópicos; | U14: =";"&LOWER(SUBSTITUTE(SUBSTITUTE(SUBSTITUTE(M14,"; ",";"),", ",";"),",",";"))&";" -> ;universidad; | V14: =IF(ISNUMBER(SEARCH(";participación digital;",P14)),1,0) -> 0 | W14: =IF(OR(ISNUMBER(SEARCH(";governanza colaborativa;",P14)),ISNUMBER(SEARCH(";gobernanza colaborativa;",P14))),1,0) -> 1 | X14: =IF(ISNUMBER(SEARCH(";mini públicos;",P14)),1,0) -> 0 | Y14: =IF(ISNUMBER(SEARCH(";referendos e iniciativas populares;",P14)),1,0) -> 0 | Z14: =IF(ISNUMBER(SEARCH(";presupuestos participativos;",P14)),1,0) -> 0 | AA14: =IF(ISNUMBER(SEARCH("planif",Q14)),1,0) -> 0 | AB14: =IF(ISNUMBER(SEARCH("implement",Q14)),1,0) -> 0 | AC14: =IF(ISNUMBER(SEARCH("análisis",Q14)),1,0) -> 1 | AD14: =IF(ISNUMBER(SEARCH("traducción",Q14)),1,0) -> 0 | AE14: =IF(ISNUMBER(SEARCH("público",F14)),1,0) -> 0 | AF14: =IF(ISNUMBER(SEARCH("privado",F14)),1,0) -> 1 | AG14: =IF(ISNUMBER(SEARCH("mixto",F14)),1,0) -> 0 | AH14: =IF(ISNUMBER(SEARCH("único",I14)),1,0) -> 1 | AI14: =IF(ISNUMBER(SEARCH("plataforma",I14)),1,0) -> 0 | AJ14: =IF(ISNUMBER(SEARCH(";industria;",R14)),1,0) -> 1 | AK14: =IF(ISNUMBER(SEARCH(";academia;",R14)),1,0) -> 0 | AL14: =IF(ISNUMBER(SEARCH(";gobierno;",R14)),1,0) -> 0 | AM14: =IF(ISNUMBER(SEARCH(";sociedad civil;",R14)),1,0) -> 0 | AN14: =IF(ISNUMBER(SEARCH(";nacional;",S14)),1,0) -> 1 | AO14: =IF(ISNUMBER(SEARCH(";internacional;",S14)),1,0) -> 0 | AP14: =IF(ISNUMBER(SEARCH(";gobierno local;",U14)),1,0) -> 0 | AQ14: =IF(ISNUMBER(SEARCH(";gobierno nacional;",U14)),1,0) -> 0 | AR14: =IF(ISNUMBER(SEARCH(";otra institución pública;",U14)),1,0) -> 0 | AS14: =IF(ISNUMBER(SEARCH(";empresa;",U14)),1,0) -> 0 | AT14: =IF(ISNUMBER(SEARCH(";universidad;",U14)),1,0) -> 1 | AU14: =IF(ISNUMBER(SEARCH(";sociedad civil;",U14)),1,0) -> 0 | AV14: =IF(ISNUMBER(SEARCH(";organización internacional;",U14)),1,0) -> 0 | AW14: =IF(N14="","",IF(AND(N14=1,('3 · Cálculo 2025 · f. nueva'!$C$25-C14)>'3 · Cálculo 2025 · f. nueva'!$C$26),0,N14)) -> 2 | AX14: =IF(SUM(AP14:AV14)<2,"",IF(AP14=1,"GL+","")&IF(AQ14=1,"GN+","")&IF(AR14=1,"OIP+","")&IF(AS14=1,"EMP+","")&IF(AT14=1,"UNI+","")&IF(AU14=1,"SC+","")&IF(AV14=1,"OI+","")) | AY14: =IF(AX14="",0,IF(COUNTIFS($A$1:A13,A14,$AX$1:AX13,AX14)=0,1,0)) -> 0
A15: CL | B15: Estrategia de Gobierno Digital. Informe proceso participativo segunda consulta ciudadana | C15: 2025 | D15: Uso de IA para analizar datos cualitativos en consulta ciudadana. | E15: Secretaría de Gobierno Digital | F15: Público | G15: Governanza Colaborativa | H15: Análisis | I15: Uso único | J15: Industria | K15: Nacional | L15: NLP - Tópicos | M15: gobierno nacional | N15: 2 | P15: =";"&LOWER(SUBSTITUTE(SUBSTITUTE(SUBSTITUTE(G15,"; ",";"),", ",";"),",",";"))&";" -> ;governanza colaborativa; | Q15: =";"&LOWER(SUBSTITUTE(SUBSTITUTE(SUBSTITUTE(H15,"; ",";"),", ",";"),",",";"))&";" -> ;análisis; | R15: =";"&LOWER(SUBSTITUTE(SUBSTITUTE(SUBSTITUTE(J15,"; ",";"),", ",";"),",",";"))&";" -> ;industria; | S15: =";"&LOWER(SUBSTITUTE(SUBSTITUTE(SUBSTITUTE(K15,"; ",";"),", ",";"),",",";"))&";" -> ;nacional; | T15: =";"&LOWER(SUBSTITUTE(SUBSTITUTE(SUBSTITUTE(L15,"; ",";"),", ",";"),",",";"))&";" -> ;nlp - tópicos; | U15: =";"&LOWER(SUBSTITUTE(SUBSTITUTE(SUBSTITUTE(M15,"; ",";"),", ",";"),",",";"))&";" -> ;gobierno nacional; | V15: =IF(ISNUMBER(SEARCH(";participación digital;",P15)),1,0) -> 0 | W15: =IF(OR(ISNUMBER(SEARCH(";governanza colaborativa;",P15)),ISNUMBER(SEARCH(";gobernanza colaborativa;",P15))),1,0) -> 1 | X15: =IF(ISNUMBER(SEARCH(";mini públicos;",P15)),1,0) -> 0 | Y15: =IF(ISNUMBER(SEARCH(";referendos e iniciativas populares;",P15)),1,0) -> 0 | Z15: =IF(ISNUMBER(SEARCH(";presupuestos participativos;",P15)),1,0) -> 0 | AA15: =IF(ISNUMBER(SEARCH("planif",Q15)),1,0) -> 0 | AB15: =IF(ISNUMBER(SEARCH("implement",Q15)),1,0) -> 0 | AC15: =IF(ISNUMBER(SEARCH("análisis",Q15)),1,0) -> 1 | AD15: =IF(ISNUMBER(SEARCH("traducción",Q15)),1,0) -> 0 | AE15: =IF(ISNUMBER(SEARCH("público",F15)),1,0) -> 1 | AF15: =IF(ISNUMBER(SEARCH("privado",F15)),1,0) -> 0 | AG15: =IF(ISNUMBER(SEARCH("mixto",F15)),1,0) -> 0 | AH15: =IF(ISNUMBER(SEARCH("único",I15)),1,0) -> 1 | AI15: =IF(ISNUMBER(SEARCH("plataforma",I15)),1,0) -> 0 | AJ15: =IF(ISNUMBER(SEARCH(";industria;",R15)),1,0) -> 1 | AK15: =IF(ISNUMBER(SEARCH(";academia;",R15)),1,0) -> 0 | AL15: =IF(ISNUMBER(SEARCH(";gobierno;",R15)),1,0) -> 0 | AM15: =IF(ISNUMBER(SEARCH(";sociedad civil;",R15)),1,0) -> 0 | AN15: =IF(ISNUMBER(SEARCH(";nacional;",S15)),1,0) -> 1 | AO15: =IF(ISNUMBER(SEARCH(";internacional;",S15)),1,0) -> 0 | AP15: =IF(ISNUMBER(SEARCH(";gobierno local;",U15)),1,0) -> 0 | AQ15: =IF(ISNUMBER(SEARCH(";gobierno nacional;",U15)),1,0) -> 1 | AR15: =IF(ISNUMBER(SEARCH(";otra institución pública;",U15)),1,0) -> 0 | AS15: =IF(ISNUMBER(SEARCH(";empresa;",U15)),1,0) -> 0 | AT15: =IF(ISNUMBER(SEARCH(";universidad;",U15)),1,0) -> 0 | AU15: =IF(ISNUMBER(SEARCH(";sociedad civil;",U15)),1,0) -> 0 | AV15: =IF(ISNUMBER(SEARCH(";organización internacional;",U15)),1,0) -> 0 | AW15: =IF(N15="","",IF(AND(N15=1,('3 · Cálculo 2025 · f. nueva'!$C$25-C15)>'3 · Cálculo 2025 · f. nueva'!$C$26),0,N15)) -> 2 | AX15: =IF(SUM(AP15:AV15)<2,"",IF(AP15=1,"GL+","")&IF(AQ15=1,"GN+","")&IF(AR15=1,"OIP+","")&IF(AS15=1,"EMP+","")&IF(AT15=1,"UNI+","")&IF(AU15=1,"SC+","")&IF(AV15=1,"OI+","")) | AY15: =IF(AX15="",0,IF(COUNTIFS($A$1:A14,A15,$AX$1:AX14,AX15)=0,1,0)) -> 0
A16: CO | B16: ECHO – HáblameD Medellín | C16: 2019 | D16: IA que capta voz ciudadana en debates guiados y clasifica cada enunciado en metas ODS, generando visualizaciones para la planificación territorial | E16: UNFPA Colombia (Laboratorio de Innovación) y Personería de Medellín | F16: Mixto | G16: Governanza Colaborativa | H16: Implementación, Análisis | I16: Uso único | J16: Gobierno | K16: Internacional | L16: Voz a Texto, NLP, LLM | M16: organización internacional; gobierno local | N16: 2 | P16: =";"&LOWER(SUBSTITUTE(SUBSTITUTE(SUBSTITUTE(G16,"; ",";"),", ",";"),",",";"))&";" -> ;governanza colaborativa; | Q16: =";"&LOWER(SUBSTITUTE(SUBSTITUTE(SUBSTITUTE(H16,"; ",";"),", ",";"),",",";"))&";" -> ;implementación;análisis; | R16: =";"&LOWER(SUBSTITUTE(SUBSTITUTE(SUBSTITUTE(J16,"; ",";"),", ",";"),",",";"))&";" -> ;gobierno; | S16: =";"&LOWER(SUBSTITUTE(SUBSTITUTE(SUBSTITUTE(K16,"; ",";"),", ",";"),",",";"))&";" -> ;internacional; | T16: =";"&LOWER(SUBSTITUTE(SUBSTITUTE(SUBSTITUTE(L16,"; ",";"),", ",";"),",",";"))&";" -> ;voz a texto;nlp;llm; | U16: =";"&LOWER(SUBSTITUTE(SUBSTITUTE(SUBSTITUTE(M16,"; ",";"),", ",";"),",",";"))&";" -> ;organización internacional;gobierno local; | V16: =IF(ISNUMBER(SEARCH(";participación digital;",P16)),1,0) -> 0 | W16: =IF(OR(ISNUMBER(SEARCH(";governanza colaborativa;",P16)),ISNUMBER(SEARCH(";gobernanza colaborativa;",P16))),1,0) -> 1 | X16: =IF(ISNUMBER(SEARCH(";mini públicos;",P16)),1,0) -> 0 | Y16: =IF(ISNUMBER(SEARCH(";referendos e iniciativas populares;",P16)),1,0) -> 0 | Z16: =IF(ISNUMBER(SEARCH(";presupuestos participativos;",P16)),1,0) -> 0 | AA16: =IF(ISNUMBER(SEARCH("planif",Q16)),1,0) -> 0 | AB16: =IF(ISNUMBER(SEARCH("implement",Q16)),1,0) -> 1 | AC16: =IF(ISNUMBER(SEARCH("análisis",Q16)),1,0) -> 1 | AD16: =IF(ISNUMBER(SEARCH("traducción",Q16)),1,0) -> 0 | AE16: =IF(ISNUMBER(SEARCH("público",F16)),1,0) -> 0 | AF16: =IF(ISNUMBER(SEARCH("privado",F16)),1,0) -> 0 | AG16: =IF(ISNUMBER(SEARCH("mixto",F16)),1,0) -> 1 | AH16: =IF(ISNUMBER(SEARCH("único",I16)),1,0) -> 1 | AI16: =IF(ISNUMBER(SEARCH("plataforma",I16)),1,0) -> 0 | AJ16: =IF(ISNUMBER(SEARCH(";industria;",R16)),1,0) -> 0 | AK16: =IF(ISNUMBER(SEARCH(";academia;",R16)),1,0) -> 0 | AL16: =IF(ISNUMBER(SEARCH(";gobierno;",R16)),1,0) -> 1 | AM16: =IF(ISNUMBER(SEARCH(";sociedad civil;",R16)),1,0) -> 0 | AN16: =IF(ISNUMBER(SEARCH(";nacional;",S16)),1,0) -> 0 | AO16: =IF(ISNUMBER(SEARCH(";internacional;",S16)),1,0) -> 1 | AP16: =IF(ISNUMBER(SEARCH(";gobierno local;",U16)),1,0) -> 1 | AQ16: =IF(ISNUMBER(SEARCH(";gobierno nacional;",U16)),1,0) -> 0 | AR16: =IF(ISNUMBER(SEARCH(";otra institución pública;",U16)),1,0) -> 0 | AS16: =IF(ISNUMBER(SEARCH(";empresa;",U16)),1,0) -> 0 | AT16: =IF(ISNUMBER(SEARCH(";universidad;",U16)),1,0) -> 0 | AU16: =IF(ISNUMBER(SEARCH(";sociedad civil;",U16)),1,0) -> 0 | AV16: =IF(ISNUMBER(SEARCH(";organización internacional;",U16)),1,0) -> 1 | AW16: =IF(N16="","",IF(AND(N16=1,('3 · Cálculo 2025 · f. nueva'!$C$25-C16)>'3 · Cálculo 2025 · f. nueva'!$C$26),0,N16)) -> 2 | AX16: =IF(SUM(AP16:AV16)<2,"",IF(AP16=1,"GL+","")&IF(AQ16=1,"GN+","")&IF(AR16=1,"OIP+","")&IF(AS16=1,"EMP+","")&IF(AT16=1,"UNI+","")&IF(AU16=1,"SC+","")&IF(AV16=1,"OI+","")) -> GL+OI+ | AY16: =IF(AX16="",0,IF(COUNTIFS($A$1:A15,A16,$AX$1:AX15,AX16)=0,1,0)) -> 1
A17: CO | B17: Tenemos que hablar de Colombia | C17: 2022 | D17: Plataforma colaborativa de diálogo e incidencia ciudadana para la conversación entre diversos actores de la sociedad colombiana, surgido a partir de eventos de manifestaciones sociales. | E17: Alianza entre seis universidades colombianas (EAFIT, Universidad Nacional de Colombia, Universidad de los Andes, Universidad del Valle, Universidad del Norte y Universidad Industrial de Santander), con el apoyo del Grupo SURA y la Fundación Ideas para la Paz. | F17: Mixto | G17: Governanza Colaborativa | H17: Análisis | I17: Uso único | J17: Sociedad Civil | K17: Nacional | L17: NLP - Tópicos, NLP - Sentiment | M17: universidad; empresa; sociedad civil | N17: 2 | P17: =";"&LOWER(SUBSTITUTE(SUBSTITUTE(SUBSTITUTE(G17,"; ",";"),", ",";"),",",";"))&";" -> ;governanza colaborativa; | Q17: =";"&LOWER(SUBSTITUTE(SUBSTITUTE(SUBSTITUTE(H17,"; ",";"),", ",";"),",",";"))&";" -> ;análisis; | R17: =";"&LOWER(SUBSTITUTE(SUBSTITUTE(SUBSTITUTE(J17,"; ",";"),", ",";"),",",";"))&";" -> ;sociedad civil; | S17: =";"&LOWER(SUBSTITUTE(SUBSTITUTE(SUBSTITUTE(K17,"; ",";"),", ",";"),",",";"))&";" -> ;nacional; | T17: =";"&LOWER(SUBSTITUTE(SUBSTITUTE(SUBSTITUTE(L17,"; ",";"),", ",";"),",",";"))&";" -> ;nlp - tópicos;nlp - sentiment; | U17: =";"&LOWER(SUBSTITUTE(SUBSTITUTE(SUBSTITUTE(M17,"; ",";"),", ",";"),",",";"))&";" -> ;universidad;empresa;sociedad civil; | V17: =IF(ISNUMBER(SEARCH(";participación digital;",P17)),1,0) -> 0 | W17: =IF(OR(ISNUMBER(SEARCH(";governanza colaborativa;",P17)),ISNUMBER(SEARCH(";gobernanza colaborativa;",P17))),1,0) -> 1 | X17: =IF(ISNUMBER(SEARCH(";mini públicos;",P17)),1,0) -> 0 | Y17: =IF(ISNUMBER(SEARCH(";referendos e iniciativas populares;",P17)),1,0) -> 0 | Z17: =IF(ISNUMBER(SEARCH(";presupuestos participativos;",P17)),1,0) -> 0 | AA17: =IF(ISNUMBER(SEARCH("planif",Q17)),1,0) -> 0 | AB17: =IF(ISNUMBER(SEARCH("implement",Q17)),1,0) -> 0 | AC17: =IF(ISNUMBER(SEARCH("análisis",Q17)),1,0) -> 1 | AD17: =IF(ISNUMBER(SEARCH("traducción",Q17)),1,0) -> 0 | AE17: =IF(ISNUMBER(SEARCH("público",F17)),1,0) -> 0 | AF17: =IF(ISNUMBER(SEARCH("privado",F17)),1,0) -> 0 | AG17: =IF(ISNUMBER(SEARCH("mixto",F17)),1,0) -> 1 | AH17: =IF(ISNUMBER(SEARCH("único",I17)),1,0) -> 1 | AI17: =IF(ISNUMBER(SEARCH("plataforma",I17)),1,0) -> 0 | AJ17: =IF(ISNUMBER(SEARCH(";industria;",R17)),1,0) -> 0 | AK17: =IF(ISNUMBER(SEARCH(";academia;",R17)),1,0) -> 0 | AL17: =IF(ISNUMBER(SEARCH(";gobierno;",R17)),1,0) -> 0 | AM17: =IF(ISNUMBER(SEARCH(";sociedad civil;",R17)),1,0) -> 1 | AN17: =IF(ISNUMBER(SEARCH(";nacional;",S17)),1,0) -> 1 | AO17: =IF(ISNUMBER(SEARCH(";internacional;",S17)),1,0) -> 0 | AP17: =IF(ISNUMBER(SEARCH(";gobierno local;",U17)),1,0) -> 0 | AQ17: =IF(ISNUMBER(SEARCH(";gobierno nacional;",U17)),1,0) -> 0 | AR17: =IF(ISNUMBER(SEARCH(";otra institución pública;",U17)),1,0) -> 0 | AS17: =IF(ISNUMBER(SEARCH(";empresa;",U17)),1,0) -> 1 | AT17: =IF(ISNUMBER(SEARCH(";universidad;",U17)),1,0) -> 1 | AU17: =IF(ISNUMBER(SEARCH(";sociedad civil;",U17)),1,0) -> 1 | AV17: =IF(ISNUMBER(SEARCH(";organización internacional;",U17)),1,0) -> 0 | AW17: =IF(N17="","",IF(AND(N17=1,('3 · Cálculo 2025 · f. nueva'!$C$25-C17)>'3 · Cálculo 2025 · f. nueva'!$C$26),0,N17)) -> 2 | AX17: =IF(SUM(AP17:AV17)<2,"",IF(AP17=1,"GL+","")&IF(AQ17=1,"GN+","")&IF(AR17=1,"OIP+","")&IF(AS17=1,"EMP+","")&IF(AT17=1,"UNI+","")&IF(AU17=1,"SC+","")&IF(AV17=1,"OI+","")) -> EMP+UNI+SC+ | AY17: =IF(AX17="",0,IF(COUNTIFS($A$1:A16,A17,$AX$1:AX16,AX17)=0,1,0)) -> 1
A18: CO | B18: Chatico | C18: 2024 | D18: Atención automatizada mediante procesamiento de lenguaje natural, análisis de datos y algoritmos de inteligencia artificial para responder consultas ciudadanas sobre más de 400 temas de interés. | E18: Secretaría General de la Alcaldía Mayor de Bogotá | F18: Público | G18: Referendos e Iniciativas Populares, Presupuestos Participativos | H18: Implementación | I18: Plataforma | J18: Industria, Gobierno | K18: Nacional | L18: NLP, LLM | M18: gobierno local | N18: 2 | P18: =";"&LOWER(SUBSTITUTE(SUBSTITUTE(SUBSTITUTE(G18,"; ",";"),", ",";"),",",";"))&";" -> ;referendos e iniciativas populares;presupuestos participativos; | Q18: =";"&LOWER(SUBSTITUTE(SUBSTITUTE(SUBSTITUTE(H18,"; ",";"),", ",";"),",",";"))&";" -> ;implementación; | R18: =";"&LOWER(SUBSTITUTE(SUBSTITUTE(SUBSTITUTE(J18,"; ",";"),", ",";"),",",";"))&";" -> ;industria;gobierno; | S18: =";"&LOWER(SUBSTITUTE(SUBSTITUTE(SUBSTITUTE(K18,"; ",";"),", ",";"),",",";"))&";" -> ;nacional; | T18: =";"&LOWER(SUBSTITUTE(SUBSTITUTE(SUBSTITUTE(L18,"; ",";"),", ",";"),",",";"))&";" -> ;nlp;llm; | U18: =";"&LOWER(SUBSTITUTE(SUBSTITUTE(SUBSTITUTE(M18,"; ",";"),", ",";"),",",";"))&";" -> ;gobierno local; | V18: =IF(ISNUMBER(SEARCH(";participación digital;",P18)),1,0) -> 0 | W18: =IF(OR(ISNUMBER(SEARCH(";governanza colaborativa;",P18)),ISNUMBER(SEARCH(";gobernanza colaborativa;",P18))),1,0) -> 0 | X18: =IF(ISNUMBER(SEARCH(";mini públicos;",P18)),1,0) -> 0 | Y18: =IF(ISNUMBER(SEARCH(";referendos e iniciativas populares;",P18)),1,0) -> 1 | Z18: =IF(ISNUMBER(SEARCH(";presupuestos participativos;",P18)),1,0) -> 1 | AA18: =IF(ISNUMBER(SEARCH("planif",Q18)),1,0) -> 0 | AB18: =IF(ISNUMBER(SEARCH("implement",Q18)),1,0) -> 1 | AC18: =IF(ISNUMBER(SEARCH("análisis",Q18)),1,0) -> 0 | AD18: =IF(ISNUMBER(SEARCH("traducción",Q18)),1,0) -> 0 | AE18: =IF(ISNUMBER(SEARCH("público",F18)),1,0) -> 1 | AF18: =IF(ISNUMBER(SEARCH("privado",F18)),1,0) -> 0 | AG18: =IF(ISNUMBER(SEARCH("mixto",F18)),1,0) -> 0 | AH18: =IF(ISNUMBER(SEARCH("único",I18)),1,0) -> 0 | AI18: =IF(ISNUMBER(SEARCH("plataforma",I18)),1,0) -> 1 | AJ18: =IF(ISNUMBER(SEARCH(";industria;",R18)),1,0) -> 1 | AK18: =IF(ISNUMBER(SEARCH(";academia;",R18)),1,0) -> 0 | AL18: =IF(ISNUMBER(SEARCH(";gobierno;",R18)),1,0) -> 1 | AM18: =IF(ISNUMBER(SEARCH(";sociedad civil;",R18)),1,0) -> 0 | AN18: =IF(ISNUMBER(SEARCH(";nacional;",S18)),1,0) -> 1 | AO18: =IF(ISNUMBER(SEARCH(";internacional;",S18)),1,0) -> 0 | AP18: =IF(ISNUMBER(SEARCH(";gobierno local;",U18)),1,0) -> 1 | AQ18: =IF(ISNUMBER(SEARCH(";gobierno nacional;",U18)),1,0) -> 0 | AR18: =IF(ISNUMBER(SEARCH(";otra institución pública;",U18)),1,0) -> 0 | AS18: =IF(ISNUMBER(SEARCH(";empresa;",U18)),1,0) -> 0 | AT18: =IF(ISNUMBER(SEARCH(";universidad;",U18)),1,0) -> 0 | AU18: =IF(ISNUMBER(SEARCH(";sociedad civil;",U18)),1,0) -> 0 | AV18: =IF(ISNUMBER(SEARCH(";organización internacional;",U18)),1,0) -> 0 | AW18: =IF(N18="","",IF(AND(N18=1,('3 · Cálculo 2025 · f. nueva'!$C$25-C18)>'3 · Cálculo 2025 · f. nueva'!$C$26),0,N18)) -> 2 | AX18: =IF(SUM(AP18:AV18)<2,"",IF(AP18=1,"GL+","")&IF(AQ18=1,"GN+","")&IF(AR18=1,"OIP+","")&IF(AS18=1,"EMP+","")&IF(AT18=1,"UNI+","")&IF(AU18=1,"SC+","")&IF(AV18=1,"OI+","")) | AY18: =IF(AX18="",0,IF(COUNTIFS($A$1:A17,A18,$AX$1:AX17,AX18)=0,1,0)) -> 0
A19: CO | B19: Descongestión de solicitudes diarias del programa Ingreso Solidario | C19: 2020 | D19: El Departamento Administrativo para la Prosperidad Social (DPS) implementó un sistema de Inteligencia Artificial para descongestionar las solicitudes diarias del programa Ingreso Solidario, que recibía más de 10.000 correos cada día. Empleando herramientas de QnA Maker para la clasificación semántica de consultas y Azure Logic Apps para extracción de metadatos (remitente, asunto, adjuntos y contenido), el proyecto redujo en un 50 % el tiempo dedicado por los funcionarios de Participación Ciudadana, transformó un backlog de tres meses de correos en solo dos semanas y pasó de respuestas en dos meses a respuestas en cuestión de minutos. | E19: Prosperidad Social | F19: Público | G19: Governanza Colaborativa | H19: Análisis | I19: Plataforma | J19: Industria | K19: Internacional | L19: NLP | M19: gobierno nacional | N19: 2 | O19: Exclusión FIRME (recodificación 2026): atención/apoyo, no contenido participativo | P19: =";"&LOWER(SUBSTITUTE(SUBSTITUTE(SUBSTITUTE(G19,"; ",";"),", ",";"),",",";"))&";" -> ;governanza colaborativa; | Q19: =";"&LOWER(SUBSTITUTE(SUBSTITUTE(SUBSTITUTE(H19,"; ",";"),", ",";"),",",";"))&";" -> ;análisis; | R19: =";"&LOWER(SUBSTITUTE(SUBSTITUTE(SUBSTITUTE(J19,"; ",";"),", ",";"),",",";"))&";" -> ;industria; | S19: =";"&LOWER(SUBSTITUTE(SUBSTITUTE(SUBSTITUTE(K19,"; ",";"),", ",";"),",",";"))&";" -> ;internacional; | T19: =";"&LOWER(SUBSTITUTE(SUBSTITUTE(SUBSTITUTE(L19,"; ",";"),", ",";"),",",";"))&";" -> ;nlp; | U19: =";"&LOWER(SUBSTITUTE(SUBSTITUTE(SUBSTITUTE(M19,"; ",";"),", ",";"),",",";"))&";" -> ;gobierno nacional; | V19: =IF(ISNUMBER(SEARCH(";participación digital;",P19)),1,0) -> 0 | W19: =IF(OR(ISNUMBER(SEARCH(";governanza colaborativa;",P19)),ISNUMBER(SEARCH(";gobernanza colaborativa;",P19))),1,0) -> 1 | X19: =IF(ISNUMBER(SEARCH(";mini públicos;",P19)),1,0) -> 0 | Y19: =IF(ISNUMBER(SEARCH(";referendos e iniciativas populares;",P19)),1,0) -> 0 | Z19: =IF(ISNUMBER(SEARCH(";presupuestos participativos;",P19)),1,0) -> 0 | AA19: =IF(ISNUMBER(SEARCH("planif",Q19)),1,0) -> 0 | AB19: =IF(ISNUMBER(SEARCH("implement",Q19)),1,0) -> 0 | AC19: =IF(ISNUMBER(SEARCH("análisis",Q19)),1,0) -> 1 | AD19: =IF(ISNUMBER(SEARCH("traducción",Q19)),1,0) -> 0 | AE19: =IF(ISNUMBER(SEARCH("público",F19)),1,0) -> 1 | AF19: =IF(ISNUMBER(SEARCH("privado",F19)),1,0) -> 0 | AG19: =IF(ISNUMBER(SEARCH("mixto",F19)),1,0) -> 0 | AH19: =IF(ISNUMBER(SEARCH("único",I19)),1,0) -> 0 | AI19: =IF(ISNUMBER(SEARCH("plataforma",I19)),1,0) -> 1 | AJ19: =IF(ISNUMBER(SEARCH(";industria;",R19)),1,0) -> 1 | AK19: =IF(ISNUMBER(SEARCH(";academia;",R19)),1,0) -> 0 | AL19: =IF(ISNUMBER(SEARCH(";gobierno;",R19)),1,0) -> 0 | AM19: =IF(ISNUMBER(SEARCH(";sociedad civil;",R19)),1,0) -> 0 | AN19: =IF(ISNUMBER(SEARCH(";nacional;",S19)),1,0) -> 0 | AO19: =IF(ISNUMBER(SEARCH(";internacional;",S19)),1,0) -> 1 | AP19: =IF(ISNUMBER(SEARCH(";gobierno local;",U19)),1,0) -> 0 | AQ19: =IF(ISNUMBER(SEARCH(";gobierno nacional;",U19)),1,0) -> 1 | AR19: =IF(ISNUMBER(SEARCH(";otra institución pública;",U19)),1,0) -> 0 | AS19: =IF(ISNUMBER(SEARCH(";empresa;",U19)),1,0) -> 0 | AT19: =IF(ISNUMBER(SEARCH(";universidad;",U19)),1,0) -> 0 | AU19: =IF(ISNUMBER(SEARCH(";sociedad civil;",U19)),1,0) -> 0 | AV19: =IF(ISNUMBER(SEARCH(";organización internacional;",U19)),1,0) -> 0 | AW19: =IF(N19="","",IF(AND(N19=1,('3 · Cálculo 2025 · f. nueva'!$C$25-C19)>'3 · Cálculo 2025 · f. nueva'!$C$26),0,N19)) -> 2 | AX19: =IF(SUM(AP19:AV19)<2,"",IF(AP19=1,"GL+","")&IF(AQ19=1,"GN+","")&IF(AR19=1,"OIP+","")&IF(AS19=1,"EMP+","")&IF(AT19=1,"UNI+","")&IF(AU19=1,"SC+","")&IF(AV19=1,"OI+","")) | AY19: =IF(AX19="",0,IF(COUNTIFS($A$1:A18,A19,$AX$1:AX18,AX19)=0,1,0)) -> 0
A20: CR | B20: dIAra | C20: 2024 | D20: Sistema de monitoreo de la ejecución de los proyectos de obras públicas en tiempo real mediante inteligencia artificial, donde los ciudadanos pueden fiscalizar y levantar alertas en caso de irregularidades y corrupción en el proyecto | E20: Contraloría General de la República de Costa Rica | F20: Público | G20: Participación Digital | H20: Traducción Política | I20: Plataforma | J20: Academia | K20: Nacional | L20: Visión computacional | M20: otra institución pública | N20: 2 | O20: Revisar rol_IA: monitoreo de obras (traducción política) | P20: =";"&LOWER(SUBSTITUTE(SUBSTITUTE(SUBSTITUTE(G20,"; ",";"),", ",";"),",",";"))&";" -> ;participación digital; | Q20: =";"&LOWER(SUBSTITUTE(SUBSTITUTE(SUBSTITUTE(H20,"; ",";"),", ",";"),",",";"))&";" -> ;traducción política; | R20: =";"&LOWER(SUBSTITUTE(SUBSTITUTE(SUBSTITUTE(J20,"; ",";"),", ",";"),",",";"))&";" -> ;academia; | S20: =";"&LOWER(SUBSTITUTE(SUBSTITUTE(SUBSTITUTE(K20,"; ",";"),", ",";"),",",";"))&";" -> ;nacional; | T20: =";"&LOWER(SUBSTITUTE(SUBSTITUTE(SUBSTITUTE(L20,"; ",";"),", ",";"),",",";"))&";" -> ;visión computacional; | U20: =";"&LOWER(SUBSTITUTE(SUBSTITUTE(SUBSTITUTE(M20,"; ",";"),", ",";"),",",";"))&";" -> ;otra institución pública; | V20: =IF(ISNUMBER(SEARCH(";participación digital;",P20)),1,0) -> 1 | W20: =IF(OR(ISNUMBER(SEARCH(";governanza colaborativa;",P20)),ISNUMBER(SEARCH(";gobernanza colaborativa;",P20))),1,0) -> 0 | X20: =IF(ISNUMBER(SEARCH(";mini públicos;",P20)),1,0) -> 0 | Y20: =IF(ISNUMBER(SEARCH(";referendos e iniciativas populares;",P20)),1,0) -> 0 | Z20: =IF(ISNUMBER(SEARCH(";presupuestos participativos;",P20)),1,0) -> 0 | AA20: =IF(ISNUMBER(SEARCH("planif",Q20)),1,0) -> 0 | AB20: =IF(ISNUMBER(SEARCH("implement",Q20)),1,0) -> 0 | AC20: =IF(ISNUMBER(SEARCH("análisis",Q20)),1,0) -> 0 | AD20: =IF(ISNUMBER(SEARCH("traducción",Q20)),1,0) -> 1 | AE20: =IF(ISNUMBER(SEARCH("público",F20)),1,0) -> 1 | AF20: =IF(ISNUMBER(SEARCH("privado",F20)),1,0) -> 0 | AG20: =IF(ISNUMBER(SEARCH("mixto",F20)),1,0) -> 0 | AH20: =IF(ISNUMBER(SEARCH("único",I20)),1,0) -> 0 | AI20: =IF(ISNUMBER(SEARCH("plataforma",I20)),1,0) -> 1 | AJ20: =IF(ISNUMBER(SEARCH(";industria;",R20)),1,0) -> 0 | AK20: =IF(ISNUMBER(SEARCH(";academia;",R20)),1,0) -> 1 | AL20: =IF(ISNUMBER(SEARCH(";gobierno;",R20)),1,0) -> 0 | AM20: =IF(ISNUMBER(SEARCH(";sociedad civil;",R20)),1,0) -> 0 | AN20: =IF(ISNUMBER(SEARCH(";nacional;",S20)),1,0) -> 1 | AO20: =IF(ISNUMBER(SEARCH(";internacional;",S20)),1,0) -> 0 | AP20: =IF(ISNUMBER(SEARCH(";gobierno local;",U20)),1,0) -> 0 | AQ20: =IF(ISNUMBER(SEARCH(";gobierno nacional;",U20)),1,0) -> 0 | AR20: =IF(ISNUMBER(SEARCH(";otra institución pública;",U20)),1,0) -> 1 | AS20: =IF(ISNUMBER(SEARCH(";empresa;",U20)),1,0) -> 0 | AT20: =IF(ISNUMBER(SEARCH(";universidad;",U20)),1,0) -> 0 | AU20: =IF(ISNUMBER(SEARCH(";sociedad civil;",U20)),1,0) -> 0 | AV20: =IF(ISNUMBER(SEARCH(";organización internacional;",U20)),1,0) -> 0 | AW20: =IF(N20="","",IF(AND(N20=1,('3 · Cálculo 2025 · f. nueva'!$C$25-C20)>'3 · Cálculo 2025 · f. nueva'!$C$26),0,N20)) -> 2 | AX20: =IF(SUM(AP20:AV20)<2,"",IF(AP20=1,"GL+","")&IF(AQ20=1,"GN+","")&IF(AR20=1,"OIP+","")&IF(AS20=1,"EMP+","")&IF(AT20=1,"UNI+","")&IF(AU20=1,"SC+","")&IF(AV20=1,"OI+","")) | AY20: =IF(AX20="",0,IF(COUNTIFS($A$1:A19,A20,$AX$1:AX19,AX20)=0,1,0)) -> 0
A21: CR | B21: U-Report Costa Rica – chatbot juvenil | D21: U-Report es una plataforma global de UNICEF que empodera a adolescentes y jóvenes, permitiéndoles opinar sobre temas sociales cruciales a través de canales que ya utilizan, como WhatsApp, SMS y Facebook Messenger. | E21: Unicef | F21: Público | G21: Participación Digital | H21: Análisis | I21: Plataforma | J21: Sociedad Civil, Industria | K21: Internacional | L21: NLP | M21: organización internacional | N21: 2 | P21: =";"&LOWER(SUBSTITUTE(SUBSTITUTE(SUBSTITUTE(G21,"; ",";"),", ",";"),",",";"))&";" -> ;participación digital; | Q21: =";"&LOWER(SUBSTITUTE(SUBSTITUTE(SUBSTITUTE(H21,"; ",";"),", ",";"),",",";"))&";" -> ;análisis; | R21: =";"&LOWER(SUBSTITUTE(SUBSTITUTE(SUBSTITUTE(J21,"; ",";"),", ",";"),",",";"))&";" -> ;sociedad civil;industria; | S21: =";"&LOWER(SUBSTITUTE(SUBSTITUTE(SUBSTITUTE(K21,"; ",";"),", ",";"),",",";"))&";" -> ;internacional; | T21: =";"&LOWER(SUBSTITUTE(SUBSTITUTE(SUBSTITUTE(L21,"; ",";"),", ",";"),",",";"))&";" -> ;nlp; | U21: =";"&LOWER(SUBSTITUTE(SUBSTITUTE(SUBSTITUTE(M21,"; ",";"),", ",";"),",",";"))&";" -> ;organización internacional; | V21: =IF(ISNUMBER(SEARCH(";participación digital;",P21)),1,0) -> 1 | W21: =IF(OR(ISNUMBER(SEARCH(";governanza colaborativa;",P21)),ISNUMBER(SEARCH(";gobernanza colaborativa;",P21))),1,0) -> 0 | X21: =IF(ISNUMBER(SEARCH(";mini públicos;",P21)),1,0) -> 0 | Y21: =IF(ISNUMBER(SEARCH(";referendos e iniciativas populares;",P21)),1,0) -> 0 | Z21: =IF(ISNUMBER(SEARCH(";presupuestos participativos;",P21)),1,0) -> 0 | AA21: =IF(ISNUMBER(SEARCH("planif",Q21)),1,0) -> 0 | AB21: =IF(ISNUMBER(SEARCH("implement",Q21)),1,0) -> 0 | AC21: =IF(ISNUMBER(SEARCH("análisis",Q21)),1,0) -> 1 | AD21: =IF(ISNUMBER(SEARCH("traducción",Q21)),1,0) -> 0 | AE21: =IF(ISNUMBER(SEARCH("público",F21)),1,0) -> 1 | AF21: =IF(ISNUMBER(SEARCH("privado",F21)),1,0) -> 0 | AG21: =IF(ISNUMBER(SEARCH("mixto",F21)),1,0) -> 0 | AH21: =IF(ISNUMBER(SEARCH("único",I21)),1,0) -> 0 | AI21: =IF(ISNUMBER(SEARCH("plataforma",I21)),1,0) -> 1 | AJ21: =IF(ISNUMBER(SEARCH(";industria;",R21)),1,0) -> 1 | AK21: =IF(ISNUMBER(SEARCH(";academia;",R21)),1,0) -> 0 | AL21: =IF(ISNUMBER(SEARCH(";gobierno;",R21)),1,0) -> 0 | AM21: =IF(ISNUMBER(SEARCH(";sociedad civil;",R21)),1,0) -> 1 | AN21: =IF(ISNUMBER(SEARCH(";nacional;",S21)),1,0) -> 0 | AO21: =IF(ISNUMBER(SEARCH(";internacional;",S21)),1,0) -> 1 | AP21: =IF(ISNUMBER(SEARCH(";gobierno local;",U21)),1,0) -> 0 | AQ21: =IF(ISNUMBER(SEARCH(";gobierno nacional;",U21)),1,0) -> 0 | AR21: =IF(ISNUMBER(SEARCH(";otra institución pública;",U21)),1,0) -> 0 | AS21: =IF(ISNUMBER(SEARCH(";empresa;",U21)),1,0) -> 0 | AT21: =IF(ISNUMBER(SEARCH(";universidad;",U21)),1,0) -> 0 | AU21: =IF(ISNUMBER(SEARCH(";sociedad civil;",U21)),1,0) -> 0 | AV21: =IF(ISNUMBER(SEARCH(";organización internacional;",U21)),1,0) -> 1 | AW21: =IF(N21="","",IF(AND(N21=1,('3 · Cálculo 2025 · f. nueva'!$C$25-C21)>'3 · Cálculo 2025 · f. nueva'!$C$26),0,N21)) -> 2 | AX21: =IF(SUM(AP21:AV21)<2,"",IF(AP21=1,"GL+","")&IF(AQ21=1,"GN+","")&IF(AR21=1,"OIP+","")&IF(AS21=1,"EMP+","")&IF(AT21=1,"UNI+","")&IF(AU21=1,"SC+","")&IF(AV21=1,"OI+","")) | AY21: =IF(AX21="",0,IF(COUNTIFS($A$1:A20,A21,$AX$1:AX20,AX21)=0,1,0)) -> 0
A22: DO | B22: CiudadanIA | C22: 2023 | D22: Sistema de interacción ciudadana basado en inteligencia artificial, diseñado para recopilar datos representativos que permitan el entrenamiento avanzado de IA en la prestación de servicios públicos. A través de ventanillas ubicadas en puntos estratégicos de alto tránsito, ofrece asistencia, información y recomendaciones personalizadas, fomentando la participación activa de la ciudadanía en el diseño y desarrollo de un sistema de Gobierno Inteligente. | E22: GENIA Latinoamérica, en colaboración con la Universidad del Caribe (UNICARIBE), el Ministerio de la Presidencia (MINPRE) y la Oficina Gubernamental de Tecnologías de la Información y Comunicación (OGTIC) | F22: Mixto | G22: Governanza Colaborativa | H22: Implementación | I22: Plataforma | J22: Industria | K22: Nacional | L22: Sistemas de recomendación, LLM | M22: empresa; universidad; gobierno nacional | N22: 2 | O22: Escenario B: caso en revisión (puede salir). GENIA: empresa/soc. civil (ambiguo) | P22: =";"&LOWER(SUBSTITUTE(SUBSTITUTE(SUBSTITUTE(G22,"; ",";"),", ",";"),",",";"))&";" -> ;governanza colaborativa; | Q22: =";"&LOWER(SUBSTITUTE(SUBSTITUTE(SUBSTITUTE(H22,"; ",";"),", ",";"),",",";"))&";" -> ;implementación; | R22: =";"&LOWER(SUBSTITUTE(SUBSTITUTE(SUBSTITUTE(J22,"; ",";"),", ",";"),",",";"))&";" -> ;industria; | S22: =";"&LOWER(SUBSTITUTE(SUBSTITUTE(SUBSTITUTE(K22,"; ",";"),", ",";"),",",";"))&";" -> ;nacional; | T22: =";"&LOWER(SUBSTITUTE(SUBSTITUTE(SUBSTITUTE(L22,"; ",";"),", ",";"),",",";"))&";" -> ;sistemas de recomendación;llm; | U22: =";"&LOWER(SUBSTITUTE(SUBSTITUTE(SUBSTITUTE(M22,"; ",";"),", ",";"),",",";"))&";" -> ;empresa;universidad;gobierno nacional; | V22: =IF(ISNUMBER(SEARCH(";participación digital;",P22)),1,0) -> 0 | W22: =IF(OR(ISNUMBER(SEARCH(";governanza colaborativa;",P22)),ISNUMBER(SEARCH(";gobernanza colaborativa;",P22))),1,0) -> 1 | X22: =IF(ISNUMBER(SEARCH(";mini públicos;",P22)),1,0) -> 0 | Y22: =IF(ISNUMBER(SEARCH(";referendos e iniciativas populares;",P22)),1,0) -> 0 | Z22: =IF(ISNUMBER(SEARCH(";presupuestos participativos;",P22)),1,0) -> 0 | AA22: =IF(ISNUMBER(SEARCH("planif",Q22)),1,0) -> 0 | AB22: =IF(ISNUMBER(SEARCH("implement",Q22)),1,0) -> 1 | AC22: =IF(ISNUMBER(SEARCH("análisis",Q22)),1,0) -> 0 | AD22: =IF(ISNUMBER(SEARCH("traducción",Q22)),1,0) -> 0 | AE22: =IF(ISNUMBER(SEARCH("público",F22)),1,0) -> 0 | AF22: =IF(ISNUMBER(SEARCH("privado",F22)),1,0) -> 0 | AG22: =IF(ISNUMBER(SEARCH("mixto",F22)),1,0) -> 1 | AH22: =IF(ISNUMBER(SEARCH("único",I22)),1,0) -> 0 | AI22: =IF(ISNUMBER(SEARCH("plataforma",I22)),1,0) -> 1 | AJ22: =IF(ISNUMBER(SEARCH(";industria;",R22)),1,0) -> 1 | AK22: =IF(ISNUMBER(SEARCH(";academia;",R22)),1,0) -> 0 | AL22: =IF(ISNUMBER(SEARCH(";gobierno;",R22)),1,0) -> 0 | AM22: =IF(ISNUMBER(SEARCH(";sociedad civil;",R22)),1,0) -> 0 | AN22: =IF(ISNUMBER(SEARCH(";nacional;",S22)),1,0) -> 1 | AO22: =IF(ISNUMBER(SEARCH(";internacional;",S22)),1,0) -> 0 | AP22: =IF(ISNUMBER(SEARCH(";gobierno local;",U22)),1,0) -> 0 | AQ22: =IF(ISNUMBER(SEARCH(";gobierno nacional;",U22)),1,0) -> 1 | AR22: =IF(ISNUMBER(SEARCH(";otra institución pública;",U22)),1,0) -> 0 | AS22: =IF(ISNUMBER(SEARCH(";empresa;",U22)),1,0) -> 1 | AT22: =IF(ISNUMBER(SEARCH(";universidad;",U22)),1,0) -> 1 | AU22: =IF(ISNUMBER(SEARCH(";sociedad civil;",U22)),1,0) -> 0 | AV22: =IF(ISNUMBER(SEARCH(";organización internacional;",U22)),1,0) -> 0 | AW22: =IF(N22="","",IF(AND(N22=1,('3 · Cálculo 2025 · f. nueva'!$C$25-C22)>'3 · Cálculo 2025 · f. nueva'!$C$26),0,N22)) -> 2 | AX22: =IF(SUM(AP22:AV22)<2,"",IF(AP22=1,"GL+","")&IF(AQ22=1,"GN+","")&IF(AR22=1,"OIP+","")&IF(AS22=1,"EMP+","")&IF(AT22=1,"UNI+","")&IF(AU22=1,"SC+","")&IF(AV22=1,"OI+","")) -> GN+EMP+UNI+ | AY22: =IF(AX22="",0,IF(COUNTIFS($A$1:A21,A22,$AX$1:AX21,AX22)=0,1,0)) -> 1
A23: EC | B23: PAGA IA | C23: 2023 | D23: Plataforma que utiliza inteligencia artificial para asistir en la creación de compromisos de Estado Abierto. Analiza datos de planes de acción de gobierno abierto de Ecuador y otros países de Hispanoamérica para sugerir actividades e hitos relacionados con temas propuestos por los usuarios | E23: Gobierno Abierto Ecuador, en colaboración con la Fundación de Ayuda por Internet (Fundapi) | F23: Mixto | G23: Referendos e Iniciativas Populares | H23: Implementación | I23: Plataforma | J23: Sociedad Civil | K23: Nacional | L23: LLM | M23: gobierno nacional; sociedad civil | N23: 2 | P23: =";"&LOWER(SUBSTITUTE(SUBSTITUTE(SUBSTITUTE(G23,"; ",";"),", ",";"),",",";"))&";" -> ;referendos e iniciativas populares; | Q23: =";"&LOWER(SUBSTITUTE(SUBSTITUTE(SUBSTITUTE(H23,"; ",";"),", ",";"),",",";"))&";" -> ;implementación; | R23: =";"&LOWER(SUBSTITUTE(SUBSTITUTE(SUBSTITUTE(J23,"; ",";"),", ",";"),",",";"))&";" -> ;sociedad civil; | S23: =";"&LOWER(SUBSTITUTE(SUBSTITUTE(SUBSTITUTE(K23,"; ",";"),", ",";"),",",";"))&";" -> ;nacional; | T23: =";"&LOWER(SUBSTITUTE(SUBSTITUTE(SUBSTITUTE(L23,"; ",";"),", ",";"),",",";"))&";" -> ;llm; | U23: =";"&LOWER(SUBSTITUTE(SUBSTITUTE(SUBSTITUTE(M23,"; ",";"),", ",";"),",",";"))&";" -> ;gobierno nacional;sociedad civil; | V23: =IF(ISNUMBER(SEARCH(";participación digital;",P23)),1,0) -> 0 | W23: =IF(OR(ISNUMBER(SEARCH(";governanza colaborativa;",P23)),ISNUMBER(SEARCH(";gobernanza colaborativa;",P23))),1,0) -> 0 | X23: =IF(ISNUMBER(SEARCH(";mini públicos;",P23)),1,0) -> 0 | Y23: =IF(ISNUMBER(SEARCH(";referendos e iniciativas populares;",P23)),1,0) -> 1 | Z23: =IF(ISNUMBER(SEARCH(";presupuestos participativos;",P23)),1,0) -> 0 | AA23: =IF(ISNUMBER(SEARCH("planif",Q23)),1,0) -> 0 | AB23: =IF(ISNUMBER(SEARCH("implement",Q23)),1,0) -> 1 | AC23: =IF(ISNUMBER(SEARCH("análisis",Q23)),1,0) -> 0 | AD23: =IF(ISNUMBER(SEARCH("traducción",Q23)),1,0) -> 0 | AE23: =IF(ISNUMBER(SEARCH("público",F23)),1,0) -> 0 | AF23: =IF(ISNUMBER(SEARCH("privado",F23)),1,0) -> 0 | AG23: =IF(ISNUMBER(SEARCH("mixto",F23)),1,0) -> 1 | AH23: =IF(ISNUMBER(SEARCH("único",I23)),1,0) -> 0 | AI23: =IF(ISNUMBER(SEARCH("plataforma",I23)),1,0) -> 1 | AJ23: =IF(ISNUMBER(SEARCH(";industria;",R23)),1,0) -> 0 | AK23: =IF(ISNUMBER(SEARCH(";academia;",R23)),1,0) -> 0 | AL23: =IF(ISNUMBER(SEARCH(";gobierno;",R23)),1,0) -> 0 | AM23: =IF(ISNUMBER(SEARCH(";sociedad civil;",R23)),1,0) -> 1 | AN23: =IF(ISNUMBER(SEARCH(";nacional;",S23)),1,0) -> 1 | AO23: =IF(ISNUMBER(SEARCH(";internacional;",S23)),1,0) -> 0 | AP23: =IF(ISNUMBER(SEARCH(";gobierno local;",U23)),1,0) -> 0 | AQ23: =IF(ISNUMBER(SEARCH(";gobierno nacional;",U23)),1,0) -> 1 | AR23: =IF(ISNUMBER(SEARCH(";otra institución pública;",U23)),1,0) -> 0 | AS23: =IF(ISNUMBER(SEARCH(";empresa;",U23)),1,0) -> 0 | AT23: =IF(ISNUMBER(SEARCH(";universidad;",U23)),1,0) -> 0 | AU23: =IF(ISNUMBER(SEARCH(";sociedad civil;",U23)),1,0) -> 1 | AV23: =IF(ISNUMBER(SEARCH(";organización internacional;",U23)),1,0) -> 0 | AW23: =IF(N23="","",IF(AND(N23=1,('3 · Cálculo 2025 · f. nueva'!$C$25-C23)>'3 · Cálculo 2025 · f. nueva'!$C$26),0,N23)) -> 2 | AX23: =IF(SUM(AP23:AV23)<2,"",IF(AP23=1,"GL+","")&IF(AQ23=1,"GN+","")&IF(AR23=1,"OIP+","")&IF(AS23=1,"EMP+","")&IF(AT23=1,"UNI+","")&IF(AU23=1,"SC+","")&IF(AV23=1,"OI+","")) -> GN+SC+ | AY23: =IF(AX23="",0,IF(COUNTIFS($A$1:A22,A23,$AX$1:AX22,AX23)=0,1,0)) -> 1
A24: GT | B24: Guatemala Joven Conversa | C24: 2024 | D24: Iniciativa de diálogos digitales asistidos por inteligencia artificial que reunió a más de 300 jóvenes de los 22 departamentos de Guatemala para discutir temas como la reforma electoral, la participación juvenil en el desarrollo y la lucha contra la corrupción. | E24: Oficina del Coordinador Residente de las Naciones Unidas en Guatemala y Fundación Esquipulas para la Paz, la Democracia, el Desarrollo y la Integración | F24: Mixto | G24: Governanza Colaborativa | H24: Implementación | I24: Uso único | J24: Gobierno | K24: Internacional | L24: NLP - Sentiment, NLP - Tópicos | M24: organización internacional; sociedad civil | N24: 2 | P24: =";"&LOWER(SUBSTITUTE(SUBSTITUTE(SUBSTITUTE(G24,"; ",";"),", ",";"),",",";"))&";" -> ;governanza colaborativa; | Q24: =";"&LOWER(SUBSTITUTE(SUBSTITUTE(SUBSTITUTE(H24,"; ",";"),", ",";"),",",";"))&";" -> ;implementación; | R24: =";"&LOWER(SUBSTITUTE(SUBSTITUTE(SUBSTITUTE(J24,"; ",";"),", ",";"),",",";"))&";" -> ;gobierno; | S24: =";"&LOWER(SUBSTITUTE(SUBSTITUTE(SUBSTITUTE(K24,"; ",";"),", ",";"),",",";"))&";" -> ;internacional; | T24: =";"&LOWER(SUBSTITUTE(SUBSTITUTE(SUBSTITUTE(L24,"; ",";"),", ",";"),",",";"))&";" -> ;nlp - sentiment;nlp - tópicos; | U24: =";"&LOWER(SUBSTITUTE(SUBSTITUTE(SUBSTITUTE(M24,"; ",";"),", ",";"),",",";"))&";" -> ;organización internacional;sociedad civil; | V24: =IF(ISNUMBER(SEARCH(";participación digital;",P24)),1,0) -> 0 | W24: =IF(OR(ISNUMBER(SEARCH(";governanza colaborativa;",P24)),ISNUMBER(SEARCH(";gobernanza colaborativa;",P24))),1,0) -> 1 | X24: =IF(ISNUMBER(SEARCH(";mini públicos;",P24)),1,0) -> 0 | Y24: =IF(ISNUMBER(SEARCH(";referendos e iniciativas populares;",P24)),1,0) -> 0 | Z24: =IF(ISNUMBER(SEARCH(";presupuestos participativos;",P24)),1,0) -> 0 | AA24: =IF(ISNUMBER(SEARCH("planif",Q24)),1,0) -> 0 | AB24: =IF(ISNUMBER(SEARCH("implement",Q24)),1,0) -> 1 | AC24: =IF(ISNUMBER(SEARCH("análisis",Q24)),1,0) -> 0 | AD24: =IF(ISNUMBER(SEARCH("traducción",Q24)),1,0) -> 0 | AE24: =IF(ISNUMBER(SEARCH("público",F24)),1,0) -> 0 | AF24: =IF(ISNUMBER(SEARCH("privado",F24)),1,0) -> 0 | AG24: =IF(ISNUMBER(SEARCH("mixto",F24)),1,0) -> 1 | AH24: =IF(ISNUMBER(SEARCH("único",I24)),1,0) -> 1 | AI24: =IF(ISNUMBER(SEARCH("plataforma",I24)),1,0) -> 0 | AJ24: =IF(ISNUMBER(SEARCH(";industria;",R24)),1,0) -> 0 | AK24: =IF(ISNUMBER(SEARCH(";academia;",R24)),1,0) -> 0 | AL24: =IF(ISNUMBER(SEARCH(";gobierno;",R24)),1,0) -> 1 | AM24: =IF(ISNUMBER(SEARCH(";sociedad civil;",R24)),1,0) -> 0 | AN24: =IF(ISNUMBER(SEARCH(";nacional;",S24)),1,0) -> 0 | AO24: =IF(ISNUMBER(SEARCH(";internacional;",S24)),1,0) -> 1 | AP24: =IF(ISNUMBER(SEARCH(";gobierno local;",U24)),1,0) -> 0 | AQ24: =IF(ISNUMBER(SEARCH(";gobierno nacional;",U24)),1,0) -> 0 | AR24: =IF(ISNUMBER(SEARCH(";otra institución pública;",U24)),1,0) -> 0 | AS24: =IF(ISNUMBER(SEARCH(";empresa;",U24)),1,0) -> 0 | AT24: =IF(ISNUMBER(SEARCH(";universidad;",U24)),1,0) -> 0 | AU24: =IF(ISNUMBER(SEARCH(";sociedad civil;",U24)),1,0) -> 1 | AV24: =IF(ISNUMBER(SEARCH(";organización internacional;",U24)),1,0) -> 1 | AW24: =IF(N24="","",IF(AND(N24=1,('3 · Cálculo 2025 · f. nueva'!$C$25-C24)>'3 · Cálculo 2025 · f. nueva'!$C$26),0,N24)) -> 2 | AX24: =IF(SUM(AP24:AV24)<2,"",IF(AP24=1,"GL+","")&IF(AQ24=1,"GN+","")&IF(AR24=1,"OIP+","")&IF(AS24=1,"EMP+","")&IF(AT24=1,"UNI+","")&IF(AU24=1,"SC+","")&IF(AV24=1,"OI+","")) -> SC+OI+ | AY24: =IF(AX24="",0,IF(COUNTIFS($A$1:A23,A24,$AX$1:AX23,AX24)=0,1,0)) -> 1
A25: HN | B25: RedPública + iVerify | C25: 2023 | D25: Plataforma digital que recibe propuestas de ley y proyectos sociales, con un módulo de análisis que agrupa temas y genera tableros de tendencias. Integra iVerify, una herramienta que utiliza aprendizaje automático para detectar y clasificar desinformación electoral antes de su publicación. | E25: Programa de las Naciones Unidas para el Desarrollo (PNUD) en colaboración con CEUTEC y la Unión Europea. | F25: Público | G25: Referendos e Iniciativas Populares | H25: Análisis | I25: Uso único | J25: Gobierno, Academia | K25: Internacional, Nacional | L25: NLP - Tópicos | M25: organización internacional; universidad | N25: 2 | P25: =";"&LOWER(SUBSTITUTE(SUBSTITUTE(SUBSTITUTE(G25,"; ",";"),", ",";"),",",";"))&";" -> ;referendos e iniciativas populares; | Q25: =";"&LOWER(SUBSTITUTE(SUBSTITUTE(SUBSTITUTE(H25,"; ",";"),", ",";"),",",";"))&";" -> ;análisis; | R25: =";"&LOWER(SUBSTITUTE(SUBSTITUTE(SUBSTITUTE(J25,"; ",";"),", ",";"),",",";"))&";" -> ;gobierno;academia; | S25: =";"&LOWER(SUBSTITUTE(SUBSTITUTE(SUBSTITUTE(K25,"; ",";"),", ",";"),",",";"))&";" -> ;internacional;nacional; | T25: =";"&LOWER(SUBSTITUTE(SUBSTITUTE(SUBSTITUTE(L25,"; ",";"),", ",";"),",",";"))&";" -> ;nlp - tópicos; | U25: =";"&LOWER(SUBSTITUTE(SUBSTITUTE(SUBSTITUTE(M25,"; ",";"),", ",";"),",",";"))&";" -> ;organización internacional;universidad; | V25: =IF(ISNUMBER(SEARCH(";participación digital;",P25)),1,0) -> 0 | W25: =IF(OR(ISNUMBER(SEARCH(";governanza colaborativa;",P25)),ISNUMBER(SEARCH(";gobernanza colaborativa;",P25))),1,0) -> 0 | X25: =IF(ISNUMBER(SEARCH(";mini públicos;",P25)),1,0) -> 0 | Y25: =IF(ISNUMBER(SEARCH(";referendos e iniciativas populares;",P25)),1,0) -> 1 | Z25: =IF(ISNUMBER(SEARCH(";presupuestos participativos;",P25)),1,0) -> 0 | AA25: =IF(ISNUMBER(SEARCH("planif",Q25)),1,0) -> 0 | AB25: =IF(ISNUMBER(SEARCH("implement",Q25)),1,0) -> 0 | AC25: =IF(ISNUMBER(SEARCH("análisis",Q25)),1,0) -> 1 | AD25: =IF(ISNUMBER(SEARCH("traducción",Q25)),1,0) -> 0 | AE25: =IF(ISNUMBER(SEARCH("público",F25)),1,0) -> 1 | AF25: =IF(ISNUMBER(SEARCH("privado",F25)),1,0) -> 0 | AG25: =IF(ISNUMBER(SEARCH("mixto",F25)),1,0) -> 0 | AH25: =IF(ISNUMBER(SEARCH("único",I25)),1,0) -> 1 | AI25: =IF(ISNUMBER(SEARCH("plataforma",I25)),1,0) -> 0 | AJ25: =IF(ISNUMBER(SEARCH(";industria;",R25)),1,0) -> 0 | AK25: =IF(ISNUMBER(SEARCH(";academia;",R25)),1,0) -> 1 | AL25: =IF(ISNUMBER(SEARCH(";gobierno;",R25)),1,0) -> 1 | AM25: =IF(ISNUMBER(SEARCH(";sociedad civil;",R25)),1,0) -> 0 | AN25: =IF(ISNUMBER(SEARCH(";nacional;",S25)),1,0) -> 1 | AO25: =IF(ISNUMBER(SEARCH(";internacional;",S25)),1,0) -> 1 | AP25: =IF(ISNUMBER(SEARCH(";gobierno local;",U25)),1,0) -> 0 | AQ25: =IF(ISNUMBER(SEARCH(";gobierno nacional;",U25)),1,0) -> 0 | AR25: =IF(ISNUMBER(SEARCH(";otra institución pública;",U25)),1,0) -> 0 | AS25: =IF(ISNUMBER(SEARCH(";empresa;",U25)),1,0) -> 0 | AT25: =IF(ISNUMBER(SEARCH(";universidad;",U25)),1,0) -> 1 | AU25: =IF(ISNUMBER(SEARCH(";sociedad civil;",U25)),1,0) -> 0 | AV25: =IF(ISNUMBER(SEARCH(";organización internacional;",U25)),1,0) -> 1 | AW25: =IF(N25="","",IF(AND(N25=1,('3 · Cálculo 2025 · f. nueva'!$C$25-C25)>'3 · Cálculo 2025 · f. nueva'!$C$26),0,N25)) -> 2 | AX25: =IF(SUM(AP25:AV25)<2,"",IF(AP25=1,"GL+","")&IF(AQ25=1,"GN+","")&IF(AR25=1,"OIP+","")&IF(AS25=1,"EMP+","")&IF(AT25=1,"UNI+","")&IF(AU25=1,"SC+","")&IF(AV25=1,"OI+","")) -> UNI+OI+ | AY25: =IF(AX25="",0,IF(COUNTIFS($A$1:A24,A25,$AX$1:AX24,AX25)=0,1,0)) -> 1
A26: MX | B26: Sufragio seguro | C26: 2024 | D26: Sistema inteligente de detección de situaciones estresantes en el proceso de emisión de sufragio para la reducción de procesos de coacción de sufragio a partir de técnicas de Machine Learning. | E26: Tecnológico Nacional de México | F26: Privado | G26: Referendos e Iniciativas Populares | H26: Implementación | I26: Plataforma | J26: Academia | K26: Nacional | L26: Visión computacional | M26: universidad | N26: 2 | O26: Exclusión FIRME (recodificación 2026): integridad/proceso electoral, no contenido | P26: =";"&LOWER(SUBSTITUTE(SUBSTITUTE(SUBSTITUTE(G26,"; ",";"),", ",";"),",",";"))&";" -> ;referendos e iniciativas populares; | Q26: =";"&LOWER(SUBSTITUTE(SUBSTITUTE(SUBSTITUTE(H26,"; ",";"),", ",";"),",",";"))&";" -> ;implementación; | R26: =";"&LOWER(SUBSTITUTE(SUBSTITUTE(SUBSTITUTE(J26,"; ",";"),", ",";"),",",";"))&";" -> ;academia; | S26: =";"&LOWER(SUBSTITUTE(SUBSTITUTE(SUBSTITUTE(K26,"; ",";"),", ",";"),",",";"))&";" -> ;nacional; | T26: =";"&LOWER(SUBSTITUTE(SUBSTITUTE(SUBSTITUTE(L26,"; ",";"),", ",";"),",",";"))&";" -> ;visión computacional; | U26: =";"&LOWER(SUBSTITUTE(SUBSTITUTE(SUBSTITUTE(M26,"; ",";"),", ",";"),",",";"))&";" -> ;universidad; | V26: =IF(ISNUMBER(SEARCH(";participación digital;",P26)),1,0) -> 0 | W26: =IF(OR(ISNUMBER(SEARCH(";governanza colaborativa;",P26)),ISNUMBER(SEARCH(";gobernanza colaborativa;",P26))),1,0) -> 0 | X26: =IF(ISNUMBER(SEARCH(";mini públicos;",P26)),1,0) -> 0 | Y26: =IF(ISNUMBER(SEARCH(";referendos e iniciativas populares;",P26)),1,0) -> 1 | Z26: =IF(ISNUMBER(SEARCH(";presupuestos participativos;",P26)),1,0) -> 0 | AA26: =IF(ISNUMBER(SEARCH("planif",Q26)),1,0) -> 0 | AB26: =IF(ISNUMBER(SEARCH("implement",Q26)),1,0) -> 1 | AC26: =IF(ISNUMBER(SEARCH("análisis",Q26)),1,0) -> 0 | AD26: =IF(ISNUMBER(SEARCH("traducción",Q26)),1,0) -> 0 | AE26: =IF(ISNUMBER(SEARCH("público",F26)),1,0) -> 0 | AF26: =IF(ISNUMBER(SEARCH("privado",F26)),1,0) -> 1 | AG26: =IF(ISNUMBER(SEARCH("mixto",F26)),1,0) -> 0 | AH26: =IF(ISNUMBER(SEARCH("único",I26)),1,0) -> 0 | AI26: =IF(ISNUMBER(SEARCH("plataforma",I26)),1,0) -> 1 | AJ26: =IF(ISNUMBER(SEARCH(";industria;",R26)),1,0) -> 0 | AK26: =IF(ISNUMBER(SEARCH(";academia;",R26)),1,0) -> 1 | AL26: =IF(ISNUMBER(SEARCH(";gobierno;",R26)),1,0) -> 0 | AM26: =IF(ISNUMBER(SEARCH(";sociedad civil;",R26)),1,0) -> 0 | AN26: =IF(ISNUMBER(SEARCH(";nacional;",S26)),1,0) -> 1 | AO26: =IF(ISNUMBER(SEARCH(";internacional;",S26)),1,0) -> 0 | AP26: =IF(ISNUMBER(SEARCH(";gobierno local;",U26)),1,0) -> 0 | AQ26: =IF(ISNUMBER(SEARCH(";gobierno nacional;",U26)),1,0) -> 0 | AR26: =IF(ISNUMBER(SEARCH(";otra institución pública;",U26)),1,0) -> 0 | AS26: =IF(ISNUMBER(SEARCH(";empresa;",U26)),1,0) -> 0 | AT26: =IF(ISNUMBER(SEARCH(";universidad;",U26)),1,0) -> 1 | AU26: =IF(ISNUMBER(SEARCH(";sociedad civil;",U26)),1,0) -> 0 | AV26: =IF(ISNUMBER(SEARCH(";organización internacional;",U26)),1,0) -> 0 | AW26: =IF(N26="","",IF(AND(N26=1,('3 · Cálculo 2025 · f. nueva'!$C$25-C26)>'3 · Cálculo 2025 · f. nueva'!$C$26),0,N26)) -> 2 | AX26: =IF(SUM(AP26:AV26)<2,"",IF(AP26=1,"GL+","")&IF(AQ26=1,"GN+","")&IF(AR26=1,"OIP+","")&IF(AS26=1,"EMP+","")&IF(AT26=1,"UNI+","")&IF(AU26=1,"SC+","")&IF(AV26=1,"OI+","")) | AY26: =IF(AX26="",0,IF(COUNTIFS($A$1:A25,A26,$AX$1:AX25,AX26)=0,1,0)) -> 0
A27: MX | B27: Presupuesto CRECES | C27: 2025 | D27: Presupuesto participativo del Ayuntamiento de Hermosillo en México. Utiliza un chatbot que a través de IA simplifica y facilita la votación de los presupuestos participativos | E27: Ayundamiento de Hermosilla | F27: Público | G27: Presupuestos Participativos | H27: Implementación | I27: Uso único | J27: Industria | K27: Nacional | L27: Chatbot - Inespecífico | M27: gobierno local | N27: 2 | P27: =";"&LOWER(SUBSTITUTE(SUBSTITUTE(SUBSTITUTE(G27,"; ",";"),", ",";"),",",";"))&";" -> ;presupuestos participativos; | Q27: =";"&LOWER(SUBSTITUTE(SUBSTITUTE(SUBSTITUTE(H27,"; ",";"),", ",";"),",",";"))&";" -> ;implementación; | R27: =";"&LOWER(SUBSTITUTE(SUBSTITUTE(SUBSTITUTE(J27,"; ",";"),", ",";"),",",";"))&";" -> ;industria; | S27: =";"&LOWER(SUBSTITUTE(SUBSTITUTE(SUBSTITUTE(K27,"; ",";"),", ",";"),",",";"))&";" -> ;nacional; | T27: =";"&LOWER(SUBSTITUTE(SUBSTITUTE(SUBSTITUTE(L27,"; ",";"),", ",";"),",",";"))&";" -> ;chatbot - inespecífico; | U27: =";"&LOWER(SUBSTITUTE(SUBSTITUTE(SUBSTITUTE(M27,"; ",";"),", ",";"),",",";"))&";" -> ;gobierno local; | V27: =IF(ISNUMBER(SEARCH(";participación digital;",P27)),1,0) -> 0 | W27: =IF(OR(ISNUMBER(SEARCH(";governanza colaborativa;",P27)),ISNUMBER(SEARCH(";gobernanza colaborativa;",P27))),1,0) -> 0 | X27: =IF(ISNUMBER(SEARCH(";mini públicos;",P27)),1,0) -> 0 | Y27: =IF(ISNUMBER(SEARCH(";referendos e iniciativas populares;",P27)),1,0) -> 0 | Z27: =IF(ISNUMBER(SEARCH(";presupuestos participativos;",P27)),1,0) -> 1 | AA27: =IF(ISNUMBER(SEARCH("planif",Q27)),1,0) -> 0 | AB27: =IF(ISNUMBER(SEARCH("implement",Q27)),1,0) -> 1 | AC27: =IF(ISNUMBER(SEARCH("análisis",Q27)),1,0) -> 0 | AD27: =IF(ISNUMBER(SEARCH("traducción",Q27)),1,0) -> 0 | AE27: =IF(ISNUMBER(SEARCH("público",F27)),1,0) -> 1 | AF27: =IF(ISNUMBER(SEARCH("privado",F27)),1,0) -> 0 | AG27: =IF(ISNUMBER(SEARCH("mixto",F27)),1,0) -> 0 | AH27: =IF(ISNUMBER(SEARCH("único",I27)),1,0) -> 1 | AI27: =IF(ISNUMBER(SEARCH("plataforma",I27)),1,0) -> 0 | AJ27: =IF(ISNUMBER(SEARCH(";industria;",R27)),1,0) -> 1 | AK27: =IF(ISNUMBER(SEARCH(";academia;",R27)),1,0) -> 0 | AL27: =IF(ISNUMBER(SEARCH(";gobierno;",R27)),1,0) -> 0 | AM27: =IF(ISNUMBER(SEARCH(";sociedad civil;",R27)),1,0) -> 0 | AN27: =IF(ISNUMBER(SEARCH(";nacional;",S27)),1,0) -> 1 | AO27: =IF(ISNUMBER(SEARCH(";internacional;",S27)),1,0) -> 0 | AP27: =IF(ISNUMBER(SEARCH(";gobierno local;",U27)),1,0) -> 1 | AQ27: =IF(ISNUMBER(SEARCH(";gobierno nacional;",U27)),1,0) -> 0 | AR27: =IF(ISNUMBER(SEARCH(";otra institución pública;",U27)),1,0) -> 0 | AS27: =IF(ISNUMBER(SEARCH(";empresa;",U27)),1,0) -> 0 | AT27: =IF(ISNUMBER(SEARCH(";universidad;",U27)),1,0) -> 0 | AU27: =IF(ISNUMBER(SEARCH(";sociedad civil;",U27)),1,0) -> 0 | AV27: =IF(ISNUMBER(SEARCH(";organización internacional;",U27)),1,0) -> 0 | AW27: =IF(N27="","",IF(AND(N27=1,('3 · Cálculo 2025 · f. nueva'!$C$25-C27)>'3 · Cálculo 2025 · f. nueva'!$C$26),0,N27)) -> 2 | AX27: =IF(SUM(AP27:AV27)<2,"",IF(AP27=1,"GL+","")&IF(AQ27=1,"GN+","")&IF(AR27=1,"OIP+","")&IF(AS27=1,"EMP+","")&IF(AT27=1,"UNI+","")&IF(AU27=1,"SC+","")&IF(AV27=1,"OI+","")) | AY27: =IF(AX27="",0,IF(COUNTIFS($A$1:A26,A27,$AX$1:AX26,AX27)=0,1,0)) -> 0
A28: PE | B28: Consulta Ciudadana sobre el Proyecto Nacional de Educación | C28: 2019 | D28: Una consulta pública para recoger opiniones sobre el Proyecto Educativo Nacional 2036, utilizando encuestas en línea, talleres y mesas deliberativas. | E28: Consejo Nacional de Educación del Perú | F28: Público | G28: Governanza Colaborativa | H28: Análisis | I28: Uso único | J28: Industria | K28: Internacional | L28: NLP - Tópicos, NLP - Sentiment | M28: otra institución pública | N28: 2 | O28: CNE: organismo autónomo (otra pública) vs gobierno nacional | P28: =";"&LOWER(SUBSTITUTE(SUBSTITUTE(SUBSTITUTE(G28,"; ",";"),", ",";"),",",";"))&";" -> ;governanza colaborativa; | Q28: =";"&LOWER(SUBSTITUTE(SUBSTITUTE(SUBSTITUTE(H28,"; ",";"),", ",";"),",",";"))&";" -> ;análisis; | R28: =";"&LOWER(SUBSTITUTE(SUBSTITUTE(SUBSTITUTE(J28,"; ",";"),", ",";"),",",";"))&";" -> ;industria; | S28: =";"&LOWER(SUBSTITUTE(SUBSTITUTE(SUBSTITUTE(K28,"; ",";"),", ",";"),",",";"))&";" -> ;internacional; | T28: =";"&LOWER(SUBSTITUTE(SUBSTITUTE(SUBSTITUTE(L28,"; ",";"),", ",";"),",",";"))&";" -> ;nlp - tópicos;nlp - sentiment; | U28: =";"&LOWER(SUBSTITUTE(SUBSTITUTE(SUBSTITUTE(M28,"; ",";"),", ",";"),",",";"))&";" -> ;otra institución pública; | V28: =IF(ISNUMBER(SEARCH(";participación digital;",P28)),1,0) -> 0 | W28: =IF(OR(ISNUMBER(SEARCH(";governanza colaborativa;",P28)),ISNUMBER(SEARCH(";gobernanza colaborativa;",P28))),1,0) -> 1 | X28: =IF(ISNUMBER(SEARCH(";mini públicos;",P28)),1,0) -> 0 | Y28: =IF(ISNUMBER(SEARCH(";referendos e iniciativas populares;",P28)),1,0) -> 0 | Z28: =IF(ISNUMBER(SEARCH(";presupuestos participativos;",P28)),1,0) -> 0 | AA28: =IF(ISNUMBER(SEARCH("planif",Q28)),1,0) -> 0 | AB28: =IF(ISNUMBER(SEARCH("implement",Q28)),1,0) -> 0 | AC28: =IF(ISNUMBER(SEARCH("análisis",Q28)),1,0) -> 1 | AD28: =IF(ISNUMBER(SEARCH("traducción",Q28)),1,0) -> 0 | AE28: =IF(ISNUMBER(SEARCH("público",F28)),1,0) -> 1 | AF28: =IF(ISNUMBER(SEARCH("privado",F28)),1,0) -> 0 | AG28: =IF(ISNUMBER(SEARCH("mixto",F28)),1,0) -> 0 | AH28: =IF(ISNUMBER(SEARCH("único",I28)),1,0) -> 1 | AI28: =IF(ISNUMBER(SEARCH("plataforma",I28)),1,0) -> 0 | AJ28: =IF(ISNUMBER(SEARCH(";industria;",R28)),1,0) -> 1 | AK28: =IF(ISNUMBER(SEARCH(";academia;",R28)),1,0) -> 0 | AL28: =IF(ISNUMBER(SEARCH(";gobierno;",R28)),1,0) -> 0 | AM28: =IF(ISNUMBER(SEARCH(";sociedad civil;",R28)),1,0) -> 0 | AN28: =IF(ISNUMBER(SEARCH(";nacional;",S28)),1,0) -> 0 | AO28: =IF(ISNUMBER(SEARCH(";internacional;",S28)),1,0) -> 1 | AP28: =IF(ISNUMBER(SEARCH(";gobierno local;",U28)),1,0) -> 0 | AQ28: =IF(ISNUMBER(SEARCH(";gobierno nacional;",U28)),1,0) -> 0 | AR28: =IF(ISNUMBER(SEARCH(";otra institución pública;",U28)),1,0) -> 1 | AS28: =IF(ISNUMBER(SEARCH(";empresa;",U28)),1,0) -> 0 | AT28: =IF(ISNUMBER(SEARCH(";universidad;",U28)),1,0) -> 0 | AU28: =IF(ISNUMBER(SEARCH(";sociedad civil;",U28)),1,0) -> 0 | AV28: =IF(ISNUMBER(SEARCH(";organización internacional;",U28)),1,0) -> 0 | AW28: =IF(N28="","",IF(AND(N28=1,('3 · Cálculo 2025 · f. nueva'!$C$25-C28)>'3 · Cálculo 2025 · f. nueva'!$C$26),0,N28)) -> 2 | AX28: =IF(SUM(AP28:AV28)<2,"",IF(AP28=1,"GL+","")&IF(AQ28=1,"GN+","")&IF(AR28=1,"OIP+","")&IF(AS28=1,"EMP+","")&IF(AT28=1,"UNI+","")&IF(AU28=1,"SC+","")&IF(AV28=1,"OI+","")) | AY28: =IF(AX28="",0,IF(COUNTIFS($A$1:A27,A28,$AX$1:AX27,AX28)=0,1,0)) -> 0
A29: PE | B29: Sistema de cómputo con IA para las Elecciones Generales 2026 | C29: 2026 | D29: La ONPE implementará un sistema de cómputo de resultados que usa IA (OCR) para reconocer los números de las actas escaneadas, agilizando el conteo y aumentando la transparencia. | E29: Oficina Nacional de Procesos Electorales (ONPE) | F29: Público | G29: Referendos e Iniciativas Populares | H29: Implementación | I29: Plataforma | J29: Gobierno | K29: Nacional | L29: Visión computacional | M29: gobierno nacional | N29: 1 | O29: Exclusión FIRME (recodificación 2026): conteo electoral (OCR), no participación; estado 'Próximamente' = anuncio | P29: =";"&LOWER(SUBSTITUTE(SUBSTITUTE(SUBSTITUTE(G29,"; ",";"),", ",";"),",",";"))&";" -> ;referendos e iniciativas populares; | Q29: =";"&LOWER(SUBSTITUTE(SUBSTITUTE(SUBSTITUTE(H29,"; ",";"),", ",";"),",",";"))&";" -> ;implementación; | R29: =";"&LOWER(SUBSTITUTE(SUBSTITUTE(SUBSTITUTE(J29,"; ",";"),", ",";"),",",";"))&";" -> ;gobierno; | S29: =";"&LOWER(SUBSTITUTE(SUBSTITUTE(SUBSTITUTE(K29,"; ",";"),", ",";"),",",";"))&";" -> ;nacional; | T29: =";"&LOWER(SUBSTITUTE(SUBSTITUTE(SUBSTITUTE(L29,"; ",";"),", ",";"),",",";"))&";" -> ;visión computacional; | U29: =";"&LOWER(SUBSTITUTE(SUBSTITUTE(SUBSTITUTE(M29,"; ",";"),", ",";"),",",";"))&";" -> ;gobierno nacional; | V29: =IF(ISNUMBER(SEARCH(";participación digital;",P29)),1,0) -> 0 | W29: =IF(OR(ISNUMBER(SEARCH(";governanza colaborativa;",P29)),ISNUMBER(SEARCH(";gobernanza colaborativa;",P29))),1,0) -> 0 | X29: =IF(ISNUMBER(SEARCH(";mini públicos;",P29)),1,0) -> 0 | Y29: =IF(ISNUMBER(SEARCH(";referendos e iniciativas populares;",P29)),1,0) -> 1 | Z29: =IF(ISNUMBER(SEARCH(";presupuestos participativos;",P29)),1,0) -> 0 | AA29: =IF(ISNUMBER(SEARCH("planif",Q29)),1,0) -> 0 | AB29: =IF(ISNUMBER(SEARCH("implement",Q29)),1,0) -> 1 | AC29: =IF(ISNUMBER(SEARCH("análisis",Q29)),1,0) -> 0 | AD29: =IF(ISNUMBER(SEARCH("traducción",Q29)),1,0) -> 0 | AE29: =IF(ISNUMBER(SEARCH("público",F29)),1,0) -> 1 | AF29: =IF(ISNUMBER(SEARCH("privado",F29)),1,0) -> 0 | AG29: =IF(ISNUMBER(SEARCH("mixto",F29)),1,0) -> 0 | AH29: =IF(ISNUMBER(SEARCH("único",I29)),1,0) -> 0 | AI29: =IF(ISNUMBER(SEARCH("plataforma",I29)),1,0) -> 1 | AJ29: =IF(ISNUMBER(SEARCH(";industria;",R29)),1,0) -> 0 | AK29: =IF(ISNUMBER(SEARCH(";academia;",R29)),1,0) -> 0 | AL29: =IF(ISNUMBER(SEARCH(";gobierno;",R29)),1,0) -> 1 | AM29: =IF(ISNUMBER(SEARCH(";sociedad civil;",R29)),1,0) -> 0 | AN29: =IF(ISNUMBER(SEARCH(";nacional;",S29)),1,0) -> 1 | AO29: =IF(ISNUMBER(SEARCH(";internacional;",S29)),1,0) -> 0 | AP29: =IF(ISNUMBER(SEARCH(";gobierno local;",U29)),1,0) -> 0 | AQ29: =IF(ISNUMBER(SEARCH(";gobierno nacional;",U29)),1,0) -> 1 | AR29: =IF(ISNUMBER(SEARCH(";otra institución pública;",U29)),1,0) -> 0 | AS29: =IF(ISNUMBER(SEARCH(";empresa;",U29)),1,0) -> 0 | AT29: =IF(ISNUMBER(SEARCH(";universidad;",U29)),1,0) -> 0 | AU29: =IF(ISNUMBER(SEARCH(";sociedad civil;",U29)),1,0) -> 0 | AV29: =IF(ISNUMBER(SEARCH(";organización internacional;",U29)),1,0) -> 0 | AW29: =IF(N29="","",IF(AND(N29=1,('3 · Cálculo 2025 · f. nueva'!$C$25-C29)>'3 · Cálculo 2025 · f. nueva'!$C$26),0,N29)) -> 1 | AX29: =IF(SUM(AP29:AV29)<2,"",IF(AP29=1,"GL+","")&IF(AQ29=1,"GN+","")&IF(AR29=1,"OIP+","")&IF(AS29=1,"EMP+","")&IF(AT29=1,"UNI+","")&IF(AU29=1,"SC+","")&IF(AV29=1,"OI+","")) | AY29: =IF(AX29="",0,IF(COUNTIFS($A$1:A28,A29,$AX$1:AX28,AX29)=0,1,0)) -> 0
A32: NOTAS Y SUPUESTOS — pestaña 1
A33: · AZUL = dato (28 casos de la BBDD 2025, solo lectura, + recodificación 2026 BORRADOR de data/baseline/recodificacion_2025.csv: convocante 7-cat y nivel 0-3 con override aplicado). NEGRO = fórmula.
A34: · Las columnas «norm …» normalizan separadores («, » y «;» → «;») y minúsculas; los flags 0/1 buscan el token exacto entre «;» (imprescindible en Origen: «nacional» es subcadena de «internacional»).
A35: · «Governanza Colaborativa» (grafía 2025) y «Gobernanza Colaborativa» cuentan como el mismo tipo de proceso.
A36: · Nivel efectivo: un anuncio (Nivel=1) caduca a los 2 años sin implementación (parámetros en pestaña 3). Solo aplica a la fórmula NUEVA; la fórmula antigua usa Continuidad 2025 (Uso único / Plataforma).
A37: · Clave de combinación: conjunto de ≥2 tipos de convocante que co-convocan la misma iniciativa (GL=gob. local, GN=gob. nacional, OIP=otra inst. pública, EMP=empresa, UNI=universidad, SC=sociedad civil, OI=org. internacional).
A38: · Los flags ORG/CONT alimentan SOLO la fórmula antigua; CONV/Nivel efectivo alimentan SOLO la nueva; TP/ET/DEV/ORIGEN/sistemas alimentan ambas.

Sheet 2 · Cálculo 2025 · f. antigua
A1: CÁLCULO 2025 CON LA FÓRMULA ANTIGUA (legacy 2025 · 4 variables · como se publicó el ILIA 2025)
A2: País | B2: N casos | C2: nº tipos de proceso | D2: V Tipos (nº÷5×100) | E2: nº etapas | F2: V Etapas (nº÷4×100) | G2: nº modalidades continuidad (UU/PL) | H2: V Continuidad (nº÷2×100) | I2: nº tipos org (Púb/Priv/Mixto) | J2: V Público-Privado (nº÷3×100) | K2: Sub1 Uso (promedio 4 V) | L2: Sub1 red. | M2: dev. nacionales (tipos) | N2: dev. internacionales (tipos) | O2: V Desarrollador | P2: nº sistemas IA | Q2: V Tipos de IA | R2: Sub2 Desarrollo | S2: Sub2 red. | T2: INDICADOR 2025 · fórmula antigua | U2: Sub1 oficial 2025 | V2: Sub2 oficial 2025 | W2: Indicador oficial 2025 | X2: Control |Δ|≤1
A3: AR | B3: =COUNTIF('1 · BBDD 2025 (insumo)'!$A$2:$A$29,$A3) -> 0 | C3: =$G$29 -> 0 | D3: =C3/5*100 -> 0 | E3: =$F$53 -> 0 | F3: =E3/4*100 -> 0 | G3: =$D$77 -> 0 | H3: =G3/2*100 -> 0 | I3: =$E$101 -> 0 | J3: =I3/3*100 -> 0 | K3: =(D3+F3+H3+J3)/4 -> 0 | L3: =ROUND(K3,0) -> 0 | M3: =$F$125 -> 0 | N3: =$F$149 -> 0 | O3: =(IF($C$24=0,0,M3/$C$24)+IF($C$25=0,0,N3/$C$25))/2*100 -> 0 | P3: =$K$173 -> 0 | Q3: =IF($C$26=0,0,P3/$C$26*100) -> 0 | R3: =(O3+Q3)/2 -> 0 | S3: =ROUND(R3,0) -> 0 | T3: =ROUND((L3+S3)/2,0) -> 0 | U3: 0 | V3: 0 | W3: 0 | X3: =IF(W3="s/d","s/d",IF(ABS(T3-W3)<=1,"✓","✗")) -> ✓
A4: BO | B4: =COUNTIF('1 · BBDD 2025 (insumo)'!$A$2:$A$29,$A4) -> 1 | C4: =$G$30 -> 1 | D4: =C4/5*100 -> 20 | E4: =$F$54 -> 2 | F4: =E4/4*100 -> 50 | G4: =$D$78 -> 1 | H4: =G4/2*100 -> 50 | I4: =$E$102 -> 1 | J4: =I4/3*100 -> 33.333333 | K4: =(D4+F4+H4+J4)/4 -> 38.333333 | L4: =ROUND(K4,0) -> 38 | M4: =$F$126 -> 0 | N4: =$F$150 -> 1 | O4: =(IF($C$24=0,0,M4/$C$24)+IF($C$25=0,0,N4/$C$25))/2*100 -> 25 | P4: =$K$174 -> 1 | Q4: =IF($C$26=0,0,P4/$C$26*100) -> 20 | R4: =(O4+Q4)/2 -> 22.5 | S4: =ROUND(R4,0) -> 23 | T4: =ROUND((L4+S4)/2,0) -> 31 | U4: 38 | V4: 23 | W4: 30 | X4: =IF(W4="s/d","s/d",IF(ABS(T4-W4)<=1,"✓","✗")) -> ✓
A5: BR | B5: =COUNTIF('1 · BBDD 2025 (insumo)'!$A$2:$A$29,$A5) -> 4 | C5: =$G$31 -> 1 | D5: =C5/5*100 -> 20 | E5: =$F$55 -> 3 | F5: =E5/4*100 -> 75 | G5: =$D$79 -> 1 | H5: =G5/2*100 -> 50 | I5: =$E$103 -> 2 | J5: =I5/3*100 -> 66.666667 | K5: =(D5+F5+H5+J5)/4 -> 52.916667 | L5: =ROUND(K5,0) -> 53 | M5: =$F$127 -> 3 | N5: =$F$151 -> 2 | O5: =(IF($C$24=0,0,M5/$C$24)+IF($C$25=0,0,N5/$C$25))/2*100 -> 100 | P5: =$K$175 -> 5 | Q5: =IF($C$26=0,0,P5/$C$26*100) -> 100 | R5: =(O5+Q5)/2 -> 100 | S5: =ROUND(R5,0) -> 100 | T5: =ROUND((L5+S5)/2,0) -> 77 | U5: 53 | V5: 100 | W5: 76 | X5: =IF(W5="s/d","s/d",IF(ABS(T5-W5)<=1,"✓","✗")) -> ✓
A6: CL | B6: =COUNTIF('1 · BBDD 2025 (insumo)'!$A$2:$A$29,$A6) -> 9 | C6: =$G$32 -> 1 | D6: =C6/5*100 -> 20 | E6: =$F$56 -> 2 | F6: =E6/4*100 -> 50 | G6: =$D$80 -> 1 | H6: =G6/2*100 -> 50 | I6: =$E$104 -> 3 | J6: =I6/3*100 -> 100 | K6: =(D6+F6+H6+J6)/4 -> 55 | L6: =ROUND(K6,0) -> 55 | M6: =$F$128 -> 2 | N6: =$F$152 -> 1 | O6: =(IF($C$24=0,0,M6/$C$24)+IF($C$25=0,0,N6/$C$25))/2*100 -> 58.333333 | P6: =$K$176 -> 3 | Q6: =IF($C$26=0,0,P6/$C$26*100) -> 60 | R6: =(O6+Q6)/2 -> 59.166667 | S6: =ROUND(R6,0) -> 59 | T6: =ROUND((L6+S6)/2,0) -> 57 | U6: 55 | V6: 59 | W6: 57 | X6: =IF(W6="s/d","s/d",IF(ABS(T6-W6)<=1,"✓","✗")) -> ✓
A7: CO | B7: =COUNTIF('1 · BBDD 2025 (insumo)'!$A$2:$A$29,$A7) -> 4 | C7: =$G$33 -> 3 | D7: =C7/5*100 -> 60 | E7: =$F$57 -> 2 | F7: =E7/4*100 -> 50 | G7: =$D$81 -> 2 | H7: =G7/2*100 -> 100 | I7: =$E$105 -> 2 | J7: =I7/3*100 -> 66.666667 | K7: =(D7+F7+H7+J7)/4 -> 69.166667 | L7: =ROUND(K7,0) -> 69 | M7: =$F$129 -> 3 | N7: =$F$153 -> 2 | O7: =(IF($C$24=0,0,M7/$C$24)+IF($C$25=0,0,N7/$C$25))/2*100 -> 100 | P7: =$K$177 -> 5 | Q7: =IF($C$26=0,0,P7/$C$26*100) -> 100 | R7: =(O7+Q7)/2 -> 100 | S7: =ROUND(R7,0) -> 100 | T7: =ROUND((L7+S7)/2,0) -> 85 | U7: 69 | V7: 100 | W7: 85 | X7: =IF(W7="s/d","s/d",IF(ABS(T7-W7)<=1,"✓","✗")) -> ✓
A8: CR | B8: =COUNTIF('1 · BBDD 2025 (insumo)'!$A$2:$A$29,$A8) -> 2 | C8: =$G$34 -> 1 | D8: =C8/5*100 -> 20 | E8: =$F$58 -> 2 | F8: =E8/4*100 -> 50 | G8: =$D$82 -> 1 | H8: =G8/2*100 -> 50 | I8: =$E$106 -> 1 | J8: =I8/3*100 -> 33.333333 | K8: =(D8+F8+H8+J8)/4 -> 38.333333 | L8: =ROUND(K8,0) -> 38 | M8: =$F$130 -> 1 | N8: =$F$154 -> 2 | O8: =(IF($C$24=0,0,M8/$C$24)+IF($C$25=0,0,N8/$C$25))/2*100 -> 66.666667 | P8: =$K$178 -> 2 | Q8: =IF($C$26=0,0,P8/$C$26*100) -> 40 | R8: =(O8+Q8)/2 -> 53.333333 | S8: =ROUND(R8,0) -> 53 | T8: =ROUND((L8+S8)/2,0) -> 46 | U8: 38 | V8: 53 | W8: 46 | X8: =IF(W8="s/d","s/d",IF(ABS(T8-W8)<=1,"✓","✗")) -> ✓
A9: CU | B9: =COUNTIF('1 · BBDD 2025 (insumo)'!$A$2:$A$29,$A9) -> 0 | C9: =$G$35 -> 0 | D9: =C9/5*100 -> 0 | E9: =$F$59 -> 0 | F9: =E9/4*100 -> 0 | G9: =$D$83 -> 0 | H9: =G9/2*100 -> 0 | I9: =$E$107 -> 0 | J9: =I9/3*100 -> 0 | K9: =(D9+F9+H9+J9)/4 -> 0 | L9: =ROUND(K9,0) -> 0 | M9: =$F$131 -> 0 | N9: =$F$155 -> 0 | O9: =(IF($C$24=0,0,M9/$C$24)+IF($C$25=0,0,N9/$C$25))/2*100 -> 0 | P9: =$K$179 -> 0 | Q9: =IF($C$26=0,0,P9/$C$26*100) -> 0 | R9: =(O9+Q9)/2 -> 0 | S9: =ROUND(R9,0) -> 0 | T9: =ROUND((L9+S9)/2,0) -> 0 | U9: 0 | V9: 0 | W9: 0 | X9: =IF(W9="s/d","s/d",IF(ABS(T9-W9)<=1,"✓","✗")) -> ✓
A10: DO | B10: =COUNTIF('1 · BBDD 2025 (insumo)'!$A$2:$A$29,$A10) -> 1 | C10: =$G$36 -> 1 | D10: =C10/5*100 -> 20 | E10: =$F$60 -> 1 | F10: =E10/4*100 -> 25 | G10: =$D$84 -> 1 | H10: =G10/2*100 -> 50 | I10: =$E$108 -> 1 | J10: =I10/3*100 -> 33.333333 | K10: =(D10+F10+H10+J10)/4 -> 32.083333 | L10: =ROUND(K10,0) -> 32 | M10: =$F$132 -> 1 | N10: =$F$156 -> 0 | O10: =(IF($C$24=0,0,M10/$C$24)+IF($C$25=0,0,N10/$C$25))/2*100 -> 16.666667 | P10: =$K$180 -> 2 | Q10: =IF($C$26=0,0,P10/$C$26*100) -> 40 | R10: =(O10+Q10)/2 -> 28.333333 | S10: =ROUND(R10,0) -> 28 | T10: =ROUND((L10+S10)/2,0) -> 30 | U10: 32 | V10: 28 | W10: 30 | X10: =IF(W10="s/d","s/d",IF(ABS(T10-W10)<=1,"✓","✗")) -> ✓
A11: EC | B11: =COUNTIF('1 · BBDD 2025 (insumo)'!$A$2:$A$29,$A11) -> 1 | C11: =$G$37 -> 1 | D11: =C11/5*100 -> 20 | E11: =$F$61 -> 1 | F11: =E11/4*100 -> 25 | G11: =$D$85 -> 1 | H11: =G11/2*100 -> 50 | I11: =$E$109 -> 1 | J11: =I11/3*100 -> 33.333333 | K11: =(D11+F11+H11+J11)/4 -> 32.083333 | L11: =ROUND(K11,0) -> 32 | M11: =$F$133 -> 1 | N11: =$F$157 -> 0 | O11: =(IF($C$24=0,0,M11/$C$24)+IF($C$25=0,0,N11/$C$25))/2*100 -> 16.666667 | P11: =$K$181 -> 1 | Q11: =IF($C$26=0,0,P11/$C$26*100) -> 20 | R11: =(O11+Q11)/2 -> 18.333333 | S11: =ROUND(R11,0) -> 18 | T11: =ROUND((L11+S11)/2,0) -> 25 | U11: 32 | V11: 18 | W11: 25 | X11: =IF(W11="s/d","s/d",IF(ABS(T11-W11)<=1,"✓","✗")) -> ✓
A12: GT | B12: =COUNTIF('1 · BBDD 2025 (insumo)'!$A$2:$A$29,$A12) -> 1 | C12: =$G$38 -> 1 | D12: =C12/5*100 -> 20 | E12: =$F$62 -> 1 | F12: =E12/4*100 -> 25 | G12: =$D$86 -> 1 | H12: =G12/2*100 -> 50 | I12: =$E$110 -> 1 | J12: =I12/3*100 -> 33.333333 | K12: =(D12+F12+H12+J12)/4 -> 32.083333 | L12: =ROUND(K12,0) -> 32 | M12: =$F$134 -> 0 | N12: =$F$158 -> 1 | O12: =(IF($C$24=0,0,M12/$C$24)+IF($C$25=0,0,N12/$C$25))/2*100 -> 25 | P12: =$K$182 -> 2 | Q12: =IF($C$26=0,0,P12/$C$26*100) -> 40 | R12: =(O12+Q12)/2 -> 32.5 | S12: =ROUND(R12,0) -> 33 | T12: =ROUND((L12+S12)/2,0) -> 33 | U12: 32 | V12: 33 | W12: 32 | X12: =IF(W12="s/d","s/d",IF(ABS(T12-W12)<=1,"✓","✗")) -> ✓
A13: HN | B13: =COUNTIF('1 · BBDD 2025 (insumo)'!$A$2:$A$29,$A13) -> 1 | C13: =$G$39 -> 1 | D13: =C13/5*100 -> 20 | E13: =$F$63 -> 1 | F13: =E13/4*100 -> 25 | G13: =$D$87 -> 1 | H13: =G13/2*100 -> 50 | I13: =$E$111 -> 1 | J13: =I13/3*100 -> 33.333333 | K13: =(D13+F13+H13+J13)/4 -> 32.083333 | L13: =ROUND(K13,0) -> 32 | M13: =$F$135 -> 2 | N13: =$F$159 -> 2 | O13: =(IF($C$24=0,0,M13/$C$24)+IF($C$25=0,0,N13/$C$25))/2*100 -> 83.333333 | P13: =$K$183 -> 1 | Q13: =IF($C$26=0,0,P13/$C$26*100) -> 20 | R13: =(O13+Q13)/2 -> 51.666667 | S13: =ROUND(R13,0) -> 52 | T13: =ROUND((L13+S13)/2,0) -> 42 | U13: 32 | V13: 52 | W13: 42 | X13: =IF(W13="s/d","s/d",IF(ABS(T13-W13)<=1,"✓","✗")) -> ✓
A14: JM | B14: =COUNTIF('1 · BBDD 2025 (insumo)'!$A$2:$A$29,$A14) -> 0 | C14: =$G$40 -> 0 | D14: =C14/5*100 -> 0 | E14: =$F$64 -> 0 | F14: =E14/4*100 -> 0 | G14: =$D$88 -> 0 | H14: =G14/2*100 -> 0 | I14: =$E$112 -> 0 | J14: =I14/3*100 -> 0 | K14: =(D14+F14+H14+J14)/4 -> 0 | L14: =ROUND(K14,0) -> 0 | M14: =$F$136 -> 0 | N14: =$F$160 -> 0 | O14: =(IF($C$24=0,0,M14/$C$24)+IF($C$25=0,0,N14/$C$25))/2*100 -> 0 | P14: =$K$184 -> 0 | Q14: =IF($C$26=0,0,P14/$C$26*100) -> 0 | R14: =(O14+Q14)/2 -> 0 | S14: =ROUND(R14,0) -> 0 | T14: =ROUND((L14+S14)/2,0) -> 0 | U14: 0 | V14: 0 | W14: 0 | X14: =IF(W14="s/d","s/d",IF(ABS(T14-W14)<=1,"✓","✗")) -> ✓
A15: MX | B15: =COUNTIF('1 · BBDD 2025 (insumo)'!$A$2:$A$29,$A15) -> 2 | C15: =$G$41 -> 2 | D15: =C15/5*100 -> 40 | E15: =$F$65 -> 1 | F15: =E15/4*100 -> 25 | G15: =$D$89 -> 2 | H15: =G15/2*100 -> 100 | I15: =$E$113 -> 2 | J15: =I15/3*100 -> 66.666667 | K15: =(D15+F15+H15+J15)/4 -> 57.916667 | L15: =ROUND(K15,0) -> 58 | M15: =$F$137 -> 2 | N15: =$F$161 -> 0 | O15: =(IF($C$24=0,0,M15/$C$24)+IF($C$25=0,0,N15/$C$25))/2*100 -> 33.333333 | P15: =$K$185 -> 2 | Q15: =IF($C$26=0,0,P15/$C$26*100) -> 40 | R15: =(O15+Q15)/2 -> 36.666667 | S15: =ROUND(R15,0) -> 37 | T15: =ROUND((L15+S15)/2,0) -> 48 | U15: 58 | V15: 37 | W15: 47 | X15: =IF(W15="s/d","s/d",IF(ABS(T15-W15)<=1,"✓","✗")) -> ✓
A16: PA | B16: =COUNTIF('1 · BBDD 2025 (insumo)'!$A$2:$A$29,$A16) -> 0 | C16: =$G$42 -> 0 | D16: =C16/5*100 -> 0 | E16: =$F$66 -> 0 | F16: =E16/4*100 -> 0 | G16: =$D$90 -> 0 | H16: =G16/2*100 -> 0 | I16: =$E$114 -> 0 | J16: =I16/3*100 -> 0 | K16: =(D16+F16+H16+J16)/4 -> 0 | L16: =ROUND(K16,0) -> 0 | M16: =$F$138 -> 0 | N16: =$F$162 -> 0 | O16: =(IF($C$24=0,0,M16/$C$24)+IF($C$25=0,0,N16/$C$25))/2*100 -> 0 | P16: =$K$186 -> 0 | Q16: =IF($C$26=0,0,P16/$C$26*100) -> 0 | R16: =(O16+Q16)/2 -> 0 | S16: =ROUND(R16,0) -> 0 | T16: =ROUND((L16+S16)/2,0) -> 0 | U16: 0 | V16: 0 | W16: 0 | X16: =IF(W16="s/d","s/d",IF(ABS(T16-W16)<=1,"✓","✗")) -> ✓
A17: PE | B17: =COUNTIF('1 · BBDD 2025 (insumo)'!$A$2:$A$29,$A17) -> 2 | C17: =$G$43 -> 2 | D17: =C17/5*100 -> 40 | E17: =$F$67 -> 2 | F17: =E17/4*100 -> 50 | G17: =$D$91 -> 2 | H17: =G17/2*100 -> 100 | I17: =$E$115 -> 1 | J17: =I17/3*100 -> 33.333333 | K17: =(D17+F17+H17+J17)/4 -> 55.833333 | L17: =ROUND(K17,0) -> 56 | M17: =$F$139 -> 1 | N17: =$F$163 -> 1 | O17: =(IF($C$24=0,0,M17/$C$24)+IF($C$25=0,0,N17/$C$25))/2*100 -> 41.666667 | P17: =$K$187 -> 3 | Q17: =IF($C$26=0,0,P17/$C$26*100) -> 60 | R17: =(O17+Q17)/2 -> 50.833333 | S17: =ROUND(R17,0) -> 51 | T17: =ROUND((L17+S17)/2,0) -> 54 | U17: 56 | V17: 51 | W17: 53 | X17: =IF(W17="s/d","s/d",IF(ABS(T17-W17)<=1,"✓","✗")) -> ✓
A18: PY | B18: =COUNTIF('1 · BBDD 2025 (insumo)'!$A$2:$A$29,$A18) -> 0 | C18: =$G$44 -> 0 | D18: =C18/5*100 -> 0 | E18: =$F$68 -> 0 | F18: =E18/4*100 -> 0 | G18: =$D$92 -> 0 | H18: =G18/2*100 -> 0 | I18: =$E$116 -> 0 | J18: =I18/3*100 -> 0 | K18: =(D18+F18+H18+J18)/4 -> 0 | L18: =ROUND(K18,0) -> 0 | M18: =$F$140 -> 0 | N18: =$F$164 -> 0 | O18: =(IF($C$24=0,0,M18/$C$24)+IF($C$25=0,0,N18/$C$25))/2*100 -> 0 | P18: =$K$188 -> 0 | Q18: =IF($C$26=0,0,P18/$C$26*100) -> 0 | R18: =(O18+Q18)/2 -> 0 | S18: =ROUND(R18,0) -> 0 | T18: =ROUND((L18+S18)/2,0) -> 0 | U18: 0 | V18: 0 | W18: 0 | X18: =IF(W18="s/d","s/d",IF(ABS(T18-W18)<=1,"✓","✗")) -> ✓
A19: SV | B19: =COUNTIF('1 · BBDD 2025 (insumo)'!$A$2:$A$29,$A19) -> 0 | C19: =$G$45 -> 0 | D19: =C19/5*100 -> 0 | E19: =$F$69 -> 0 | F19: =E19/4*100 -> 0 | G19: =$D$93 -> 0 | H19: =G19/2*100 -> 0 | I19: =$E$117 -> 0 | J19: =I19/3*100 -> 0 | K19: =(D19+F19+H19+J19)/4 -> 0 | L19: =ROUND(K19,0) -> 0 | M19: =$F$141 -> 0 | N19: =$F$165 -> 0 | O19: =(IF($C$24=0,0,M19/$C$24)+IF($C$25=0,0,N19/$C$25))/2*100 -> 0 | P19: =$K$189 -> 0 | Q19: =IF($C$26=0,0,P19/$C$26*100) -> 0 | R19: =(O19+Q19)/2 -> 0 | S19: =ROUND(R19,0) -> 0 | T19: =ROUND((L19+S19)/2,0) -> 0 | U19: 0 | V19: 0 | W19: 0 | X19: =IF(W19="s/d","s/d",IF(ABS(T19-W19)<=1,"✓","✗")) -> ✓
A20: TT | B20: =COUNTIF('1 · BBDD 2025 (insumo)'!$A$2:$A$29,$A20) -> 0 | C20: =$G$46 -> 0 | D20: =C20/5*100 -> 0 | E20: =$F$70 -> 0 | F20: =E20/4*100 -> 0 | G20: =$D$94 -> 0 | H20: =G20/2*100 -> 0 | I20: =$E$118 -> 0 | J20: =I20/3*100 -> 0 | K20: =(D20+F20+H20+J20)/4 -> 0 | L20: =ROUND(K20,0) -> 0 | M20: =$F$142 -> 0 | N20: =$F$166 -> 0 | O20: =(IF($C$24=0,0,M20/$C$24)+IF($C$25=0,0,N20/$C$25))/2*100 -> 0 | P20: =$K$190 -> 0 | Q20: =IF($C$26=0,0,P20/$C$26*100) -> 0 | R20: =(O20+Q20)/2 -> 0 | S20: =ROUND(R20,0) -> 0 | T20: =ROUND((L20+S20)/2,0) -> 0 | U20: s/d | V20: s/d | W20: s/d | X20: =IF(W20="s/d","s/d",IF(ABS(T20-W20)<=1,"✓","✗")) -> s/d
A21: UY | B21: =COUNTIF('1 · BBDD 2025 (insumo)'!$A$2:$A$29,$A21) -> 0 | C21: =$G$47 -> 0 | D21: =C21/5*100 -> 0 | E21: =$F$71 -> 0 | F21: =E21/4*100 -> 0 | G21: =$D$95 -> 0 | H21: =G21/2*100 -> 0 | I21: =$E$119 -> 0 | J21: =I21/3*100 -> 0 | K21: =(D21+F21+H21+J21)/4 -> 0 | L21: =ROUND(K21,0) -> 0 | M21: =$F$143 -> 0 | N21: =$F$167 -> 0 | O21: =(IF($C$24=0,0,M21/$C$24)+IF($C$25=0,0,N21/$C$25))/2*100 -> 0 | P21: =$K$191 -> 0 | Q21: =IF($C$26=0,0,P21/$C$26*100) -> 0 | R21: =(O21+Q21)/2 -> 0 | S21: =ROUND(R21,0) -> 0 | T21: =ROUND((L21+S21)/2,0) -> 0 | U21: 0 | V21: 0 | W21: 0 | X21: =IF(W21="s/d","s/d",IF(ABS(T21-W21)<=1,"✓","✗")) -> ✓
A22: VE | B22: =COUNTIF('1 · BBDD 2025 (insumo)'!$A$2:$A$29,$A22) -> 0 | C22: =$G$48 -> 0 | D22: =C22/5*100 -> 0 | E22: =$F$72 -> 0 | F22: =E22/4*100 -> 0 | G22: =$D$96 -> 0 | H22: =G22/2*100 -> 0 | I22: =$E$120 -> 0 | J22: =I22/3*100 -> 0 | K22: =(D22+F22+H22+J22)/4 -> 0 | L22: =ROUND(K22,0) -> 0 | M22: =$F$144 -> 0 | N22: =$F$168 -> 0 | O22: =(IF($C$24=0,0,M22/$C$24)+IF($C$25=0,0,N22/$C$25))/2*100 -> 0 | P22: =$K$192 -> 0 | Q22: =IF($C$26=0,0,P22/$C$26*100) -> 0 | R22: =(O22+Q22)/2 -> 0 | S22: =ROUND(R22,0) -> 0 | T22: =ROUND((L22+S22)/2,0) -> 0 | U22: 0 | V22: 0 | W22: 0 | X22: =IF(W22="s/d","s/d",IF(ABS(T22-W22)<=1,"✓","✗")) -> ✓
A23: MÁXIMOS RELATIVOS DEL CICLO 2025 (fórmulas MAX sobre la tabla)
A24: Máx. desarrolladores nacionales | C24: =MAX(M3:M22) -> 3
A25: Máx. desarrolladores internacionales | C25: =MAX(N3:N22) -> 2
A26: Máx. sistemas de IA | C26: =MAX(P3:P22) -> 5 | E26: Fuente del oficial 2025: hoja «Gráfico - Índice» de data/baseline/BBDD_IA_Participacion_2025.xlsx (dato pegado). TT = s/d (no estaba en el universo 2025). Diferencias de ±1 provienen del redondeo del motor original (banker's) vs ROUND de Excel (half-up).
A27: GRILLA — Tipos de proceso presentes por país (20×5)
A28: País | B28: TP: Participación Digital | C28: TP: Gobernanza Colaborativa | D28: TP: Mini públicos | E28: TP: Referendos e Inic. Populares | F28: TP: Presupuestos Participativos | G28: SUMA
A29: AR | B29: =IF(COUNTIFS('1 · BBDD 2025 (insumo)'!$A$2:$A$29,$A29,'1 · BBDD 2025 (insumo)'!$V$2:$V$29,1)>0,1,0) -> 0 | C29: =IF(COUNTIFS('1 · BBDD 2025 (insumo)'!$A$2:$A$29,$A29,'1 · BBDD 2025 (insumo)'!$W$2:$W$29,1)>0,1,0) -> 0 | D29: =IF(COUNTIFS('1 · BBDD 2025 (insumo)'!$A$2:$A$29,$A29,'1 · BBDD 2025 (insumo)'!$X$2:$X$29,1)>0,1,0) -> 0 | E29: =IF(COUNTIFS('1 · BBDD 2025 (insumo)'!$A$2:$A$29,$A29,'1 · BBDD 2025 (insumo)'!$Y$2:$Y$29,1)>0,1,0) -> 0 | F29: =IF(COUNTIFS('1 · BBDD 2025 (insumo)'!$A$2:$A$29,$A29,'1 · BBDD 2025 (insumo)'!$Z$2:$Z$29,1)>0,1,0) -> 0 | G29: =SUM(B29:F29) -> 0
A30: BO | B30: =IF(COUNTIFS('1 · BBDD 2025 (insumo)'!$A$2:$A$29,$A30,'1 · BBDD 2025 (insumo)'!$V$2:$V$29,1)>0,1,0) -> 0 | C30: =IF(COUNTIFS('1 · BBDD 2025 (insumo)'!$A$2:$A$29,$A30,'1 · BBDD 2025 (insumo)'!$W$2:$W$29,1)>0,1,0) -> 1 | D30: =IF(COUNTIFS('1 · BBDD 2025 (insumo)'!$A$2:$A$29,$A30,'1 · BBDD 2025 (insumo)'!$X$2:$X$29,1)>0,1,0) -> 0 | E30: =IF(COUNTIFS('1 · BBDD 2025 (insumo)'!$A$2:$A$29,$A30,'1 · BBDD 2025 (insumo)'!$Y$2:$Y$29,1)>0,1,0) -> 0 | F30: =IF(COUNTIFS('1 · BBDD 2025 (insumo)'!$A$2:$A$29,$A30,'1 · BBDD 2025 (insumo)'!$Z$2:$Z$29,1)>0,1,0) -> 0 | G30: =SUM(B30:F30) -> 1
A31: BR | B31: =IF(COUNTIFS('1 · BBDD 2025 (insumo)'!$A$2:$A$29,$A31,'1 · BBDD 2025 (insumo)'!$V$2:$V$29,1)>0,1,0) -> 0 | C31: =IF(COUNTIFS('1 · BBDD 2025 (insumo)'!$A$2:$A$29,$A31,'1 · BBDD 2025 (insumo)'!$W$2:$W$29,1)>0,1,0) -> 1 | D31: =IF(COUNTIFS('1 · BBDD 2025 (insumo)'!$A$2:$A$29,$A31,'1 · BBDD 2025 (insumo)'!$X$2:$X$29,1)>0,1,0) -> 0 | E31: =IF(COUNTIFS('1 · BBDD 2025 (insumo)'!$A$2:$A$29,$A31,'1 · BBDD 2025 (insumo)'!$Y$2:$Y$29,1)>0,1,0) -> 0 | F31: =IF(COUNTIFS('1 · BBDD 2025 (insumo)'!$A$2:$A$29,$A31,'1 · BBDD 2025 (insumo)'!$Z$2:$Z$29,1)>0,1,0) -> 0 | G31: =SUM(B31:F31) -> 1
A32: CL | B32: =IF(COUNTIFS('1 · BBDD 2025 (insumo)'!$A$2:$A$29,$A32,'1 · BBDD 2025 (insumo)'!$V$2:$V$29,1)>0,1,0) -> 0 | C32: =IF(COUNTIFS('1 · BBDD 2025 (insumo)'!$A$2:$A$29,$A32,'1 · BBDD 2025 (insumo)'!$W$2:$W$29,1)>0,1,0) -> 1 | D32: =IF(COUNTIFS('1 · BBDD 2025 (insumo)'!$A$2:$A$29,$A32,'1 · BBDD 2025 (insumo)'!$X$2:$X$29,1)>0,1,0) -> 0 | E32: =IF(COUNTIFS('1 · BBDD 2025 (insumo)'!$A$2:$A$29,$A32,'1 · BBDD 2025 (insumo)'!$Y$2:$Y$29,1)>0,1,0) -> 0 | F32: =IF(COUNTIFS('1 · BBDD 2025 (insumo)'!$A$2:$A$29,$A32,'1 · BBDD 2025 (insumo)'!$Z$2:$Z$29,1)>0,1,0) -> 0 | G32: =SUM(B32:F32) -> 1
A33: CO | B33: =IF(COUNTIFS('1 · BBDD 2025 (insumo)'!$A$2:$A$29,$A33,'1 · BBDD 2025 (insumo)'!$V$2:$V$29,1)>0,1,0) -> 0 | C33: =IF(COUNTIFS('1 · BBDD 2025 (insumo)'!$A$2:$A$29,$A33,'1 · BBDD 2025 (insumo)'!$W$2:$W$29,1)>0,1,0) -> 1 | D33: =IF(COUNTIFS('1 · BBDD 2025 (insumo)'!$A$2:$A$29,$A33,'1 · BBDD 2025 (insumo)'!$X$2:$X$29,1)>0,1,0) -> 0 | E33: =IF(COUNTIFS('1 · BBDD 2025 (insumo)'!$A$2:$A$29,$A33,'1 · BBDD 2025 (insumo)'!$Y$2:$Y$29,1)>0,1,0) -> 1 | F33: =IF(COUNTIFS('1 · BBDD 2025 (insumo)'!$A$2:$A$29,$A33,'1 · BBDD 2025 (insumo)'!$Z$2:$Z$29,1)>0,1,0) -> 1 | G33: =SUM(B33:F33) -> 3
A34: CR | B34: =IF(COUNTIFS('1 · BBDD 2025 (insumo)'!$A$2:$A$29,$A34,'1 · BBDD 2025 (insumo)'!$V$2:$V$29,1)>0,1,0) -> 1 | C34: =IF(COUNTIFS('1 · BBDD 2025 (insumo)'!$A$2:$A$29,$A34,'1 · BBDD 2025 (insumo)'!$W$2:$W$29,1)>0,1,0) -> 0 | D34: =IF(COUNTIFS('1 · BBDD 2025 (insumo)'!$A$2:$A$29,$A34,'1 · BBDD 2025 (insumo)'!$X$2:$X$29,1)>0,1,0) -> 0 | E34: =IF(COUNTIFS('1 · BBDD 2025 (insumo)'!$A$2:$A$29,$A34,'1 · BBDD 2025 (insumo)'!$Y$2:$Y$29,1)>0,1,0) -> 0 | F34: =IF(COUNTIFS('1 · BBDD 2025 (insumo)'!$A$2:$A$29,$A34,'1 · BBDD 2025 (insumo)'!$Z$2:$Z$29,1)>0,1,0) -> 0 | G34: =SUM(B34:F34) -> 1
A35: CU | B35: =IF(COUNTIFS('1 · BBDD 2025 (insumo)'!$A$2:$A$29,$A35,'1 · BBDD 2025 (insumo)'!$V$2:$V$29,1)>0,1,0) -> 0 | C35: =IF(COUNTIFS('1 · BBDD 2025 (insumo)'!$A$2:$A$29,$A35,'1 · BBDD 2025 (insumo)'!$W$2:$W$29,1)>0,1,0) -> 0 | D35: =IF(COUNTIFS('1 · BBDD 2025 (insumo)'!$A$2:$A$29,$A35,'1 · BBDD 2025 (insumo)'!$X$2:$X$29,1)>0,1,0) -> 0 | E35: =IF(COUNTIFS('1 · BBDD 2025 (insumo)'!$A$2:$A$29,$A35,'1 · BBDD 2025 (insumo)'!$Y$2:$Y$29,1)>0,1,0) -> 0 | F35: =IF(COUNTIFS('1 · BBDD 2025 (insumo)'!$A$2:$A$29,$A35,'1 · BBDD 2025 (insumo)'!$Z$2:$Z$29,1)>0,1,0) -> 0 | G35: =SUM(B35:F35) -> 0
A36: DO | B36: =IF(COUNTIFS('1 · BBDD 2025 (insumo)'!$A$2:$A$29,$A36,'1 · BBDD 2025 (insumo)'!$V$2:$V$29,1)>0,1,0) -> 0 | C36: =IF(COUNTIFS('1 · BBDD 2025 (insumo)'!$A$2:$A$29,$A36,'1 · BBDD 2025 (insumo)'!$W$2:$W$29,1)>0,1,0) -> 1 | D36: =IF(COUNTIFS('1 · BBDD 2025 (insumo)'!$A$2:$A$29,$A36,'1 · BBDD 2025 (insumo)'!$X$2:$X$29,1)>0,1,0) -> 0 | E36: =IF(COUNTIFS('1 · BBDD 2025 (insumo)'!$A$2:$A$29,$A36,'1 · BBDD 2025 (insumo)'!$Y$2:$Y$29,1)>0,1,0) -> 0 | F36: =IF(COUNTIFS('1 · BBDD 2025 (insumo)'!$A$2:$A$29,$A36,'1 · BBDD 2025 (insumo)'!$Z$2:$Z$29,1)>0,1,0) -> 0 | G36: =SUM(B36:F36) -> 1
A37: EC | B37: =IF(COUNTIFS('1 · BBDD 2025 (insumo)'!$A$2:$A$29,$A37,'1 · BBDD 2025 (insumo)'!$V$2:$V$29,1)>0,1,0) -> 0 | C37: =IF(COUNTIFS('1 · BBDD 2025 (insumo)'!$A$2:$A$29,$A37,'1 · BBDD 2025 (insumo)'!$W$2:$W$29,1)>0,1,0) -> 0 | D37: =IF(COUNTIFS('1 · BBDD 2025 (insumo)'!$A$2:$A$29,$A37,'1 · BBDD 2025 (insumo)'!$X$2:$X$29,1)>0,1,0) -> 0 | E37: =IF(COUNTIFS('1 · BBDD 2025 (insumo)'!$A$2:$A$29,$A37,'1 · BBDD 2025 (insumo)'!$Y$2:$Y$29,1)>0,1,0) -> 1 | F37: =IF(COUNTIFS('1 · BBDD 2025 (insumo)'!$A$2:$A$29,$A37,'1 · BBDD 2025 (insumo)'!$Z$2:$Z$29,1)>0,1,0) -> 0 | G37: =SUM(B37:F37) -> 1
A38: GT | B38: =IF(COUNTIFS('1 · BBDD 2025 (insumo)'!$A$2:$A$29,$A38,'1 · BBDD 2025 (insumo)'!$V$2:$V$29,1)>0,1,0) -> 0 | C38: =IF(COUNTIFS('1 · BBDD 2025 (insumo)'!$A$2:$A$29,$A38,'1 · BBDD 2025 (insumo)'!$W$2:$W$29,1)>0,1,0) -> 1 | D38: =IF(COUNTIFS('1 · BBDD 2025 (insumo)'!$A$2:$A$29,$A38,'1 · BBDD 2025 (insumo)'!$X$2:$X$29,1)>0,1,0) -> 0 | E38: =IF(COUNTIFS('1 · BBDD 2025 (insumo)'!$A$2:$A$29,$A38,'1 · BBDD 2025 (insumo)'!$Y$2:$Y$29,1)>0,1,0) -> 0 | F38: =IF(COUNTIFS('1 · BBDD 2025 (insumo)'!$A$2:$A$29,$A38,'1 · BBDD 2025 (insumo)'!$Z$2:$Z$29,1)>0,1,0) -> 0 | G38: =SUM(B38:F38) -> 1
A39: HN | B39: =IF(COUNTIFS('1 · BBDD 2025 (insumo)'!$A$2:$A$29,$A39,'1 · BBDD 2025 (insumo)'!$V$2:$V$29,1)>0,1,0) -> 0 | C39: =IF(COUNTIFS('1 · BBDD 2025 (insumo)'!$A$2:$A$29,$A39,'1 · BBDD 2025 (insumo)'!$W$2:$W$29,1)>0,1,0) -> 0 | D39: =IF(COUNTIFS('1 · BBDD 2025 (insumo)'!$A$2:$A$29,$A39,'1 · BBDD 2025 (insumo)'!$X$2:$X$29,1)>0,1,0) -> 0 | E39: =IF(COUNTIFS('1 · BBDD 2025 (insumo)'!$A$2:$A$29,$A39,'1 · BBDD 2025 (insumo)'!$Y$2:$Y$29,1)>0,1,0) -> 1 | F39: =IF(COUNTIFS('1 · BBDD 2025 (insumo)'!$A$2:$A$29,$A39,'1 · BBDD 2025 (insumo)'!$Z$2:$Z$29,1)>0,1,0) -> 0 | G39: =SUM(B39:F39) -> 1
A40: JM | B40: =IF(COUNTIFS('1 · BBDD 2025 (insumo)'!$A$2:$A$29,$A40,'1 · BBDD 2025 (insumo)'!$V$2:$V$29,1)>0,1,0) -> 0 | C40: =IF(COUNTIFS('1 · BBDD 2025 (insumo)'!$A$2:$A$29,$A40,'1 · BBDD 2025 (insumo)'!$W$2:$W$29,1)>0,1,0) -> 0 | D40: =IF(COUNTIFS('1 · BBDD 2025 (insumo)'!$A$2:$A$29,$A40,'1 · BBDD 2025 (insumo)'!$X$2:$X$29,1)>0,1,0) -> 0 | E40: =IF(COUNTIFS('1 · BBDD 2025 (insumo)'!$A$2:$A$29,$A40,'1 · BBDD 2025 (insumo)'!$Y$2:$Y$29,1)>0,1,0) -> 0 | F40: =IF(COUNTIFS('1 · BBDD 2025 (insumo)'!$A$2:$A$29,$A40,'1 · BBDD 2025 (insumo)'!$Z$2:$Z$29,1)>0,1,0) -> 0 | G40: =SUM(B40:F40) -> 0
... A48: VE | B48: =IF(COUNTIFS('1 · BBDD 2025 (insumo)'!$A$2:$A$29,$A48,'1 · BBDD 2025 (insumo)'!$V$2:$V$29,1)>0,1,0) -> 0 | C48: =IF(COUNTIFS('1 · BBDD 2025 (insumo)'!$A$2:$A$29,$A48,'1 · BBDD 2025 (insumo)'!$W$2:$W$29,1)>0,1,0) -> 0 | D48: =IF(COUNTIFS('1 · BBDD 2025 (insumo)'!$A$2:$A$29,$A48,'1 · BBDD 2025 (insumo)'!$X$2:$X$29,1)>0,1,0) -> 0 | E48: =IF(COUNTIFS('1 · BBDD 2025 (insumo)'!$A$2:$A$29,$A48,'1 · BBDD 2025 (insumo)'!$Y$2:$Y$29,1)>0,1,0) -> 0 | F48: =IF(COUNTIFS('1 · BBDD 2025 (insumo)'!$A$2:$A$29,$A48,'1 · BBDD 2025 (insumo)'!$Z$2:$Z$29,1)>0,1,0) -> 0 | G48: =SUM(B48:F48) -> 0
A51: GRILLA — Etapas presentes por país (20×4)
A52: País | B52: ET: Planificación | C52: ET: Implementación | D52: ET: Análisis | E52: ET: Traducción Política | F52: SUMA
A53: AR | B53: =IF(COUNTIFS('1 · BBDD 2025 (insumo)'!$A$2:$A$29,$A53,'1 · BBDD 2025 (insumo)'!$AA$2:$AA$29,1)>0,1,0) -> 0 | C53: =IF(COUNTIFS('1 · BBDD 2025 (insumo)'!$A$2:$A$29,$A53,'1 · BBDD 2025 (insumo)'!$AB$2:$AB$29,1)>0,1,0) -> 0 | D53: =IF(COUNTIFS('1 · BBDD 2025 (insumo)'!$A$2:$A$29,$A53,'1 · BBDD 2025 (insumo)'!$AC$2:$AC$29,1)>0,1,0) -> 0 | E53: =IF(COUNTIFS('1 · BBDD 2025 (insumo)'!$A$2:$A$29,$A53,'1 · BBDD 2025 (insumo)'!$AD$2:$AD$29,1)>0,1,0) -> 0 | F53: =SUM(B53:E53) -> 0
A54: BO | B54: =IF(COUNTIFS('1 · BBDD 2025 (insumo)'!$A$2:$A$29,$A54,'1 · BBDD 2025 (insumo)'!$AA$2:$AA$29,1)>0,1,0) -> 0 | C54: =IF(COUNTIFS('1 · BBDD 2025 (insumo)'!$A$2:$A$29,$A54,'1 · BBDD 2025 (insumo)'!$AB$2:$AB$29,1)>0,1,0) -> 1 | D54: =IF(COUNTIFS('1 · BBDD 2025 (insumo)'!$A$2:$A$29,$A54,'1 · BBDD 2025 (insumo)'!$AC$2:$AC$29,1)>0,1,0) -> 1 | E54: =IF(COUNTIFS('1 · BBDD 2025 (insumo)'!$A$2:$A$29,$A54,'1 · BBDD 2025 (insumo)'!$AD$2:$AD$29,1)>0,1,0) -> 0 | F54: =SUM(B54:E54) -> 2
A55: BR | B55: =IF(COUNTIFS('1 · BBDD 2025 (insumo)'!$A$2:$A$29,$A55,'1 · BBDD 2025 (insumo)'!$AA$2:$AA$29,1)>0,1,0) -> 0 | C55: =IF(COUNTIFS('1 · BBDD 2025 (insumo)'!$A$2:$A$29,$A55,'1 · BBDD 2025 (insumo)'!$AB$2:$AB$29,1)>0,1,0) -> 1 | D55: =IF(COUNTIFS('1 · BBDD 2025 (insumo)'!$A$2:$A$29,$A55,'1 · BBDD 2025 (insumo)'!$AC$2:$AC$29,1)>0,1,0) -> 1 | E55: =IF(COUNTIFS('1 · BBDD 2025 (insumo)'!$A$2:$A$29,$A55,'1 · BBDD 2025 (insumo)'!$AD$2:$AD$29,1)>0,1,0) -> 1 | F55: =SUM(B55:E55) -> 3
A56: CL | B56: =IF(COUNTIFS('1 · BBDD 2025 (insumo)'!$A$2:$A$29,$A56,'1 · BBDD 2025 (insumo)'!$AA$2:$AA$29,1)>0,1,0) -> 0 | C56: =IF(COUNTIFS('1 · BBDD 2025 (insumo)'!$A$2:$A$29,$A56,'1 · BBDD 2025 (insumo)'!$AB$2:$AB$29,1)>0,1,0) -> 1 | D56: =IF(COUNTIFS('1 · BBDD 2025 (insumo)'!$A$2:$A$29,$A56,'1 · BBDD 2025 (insumo)'!$AC$2:$AC$29,1)>0,1,0) -> 1 | E56: =IF(COUNTIFS('1 · BBDD 2025 (insumo)'!$A$2:$A$29,$A56,'1 · BBDD 2025 (insumo)'!$AD$2:$AD$29,1)>0,1,0) -> 0 | F56: =SUM(B56:E56) -> 2
A57: CO | B57: =IF(COUNTIFS('1 · BBDD 2025 (insumo)'!$A$2:$A$29,$A57,'1 · BBDD 2025 (insumo)'!$AA$2:$AA$29,1)>0,1,0) -> 0 | C57: =IF(COUNTIFS('1 · BBDD 2025 (insumo)'!$A$2:$A$29,$A57,'1 · BBDD 2025 (insumo)'!$AB$2:$AB$29,1)>0,1,0) -> 1 | D57: =IF(COUNTIFS('1 · BBDD 2025 (insumo)'!$A$2:$A$29,$A57,'1 · BBDD 2025 (insumo)'!$AC$2:$AC$29,1)>0,1,0) -> 1 | E57: =IF(COUNTIFS('1 · BBDD 2025 (insumo)'!$A$2:$A$29,$A57,'1 · BBDD 2025 (insumo)'!$AD$2:$AD$29,1)>0,1,0) -> 0 | F57: =SUM(B57:E57) -> 2
A58: CR | B58: =IF(COUNTIFS('1 · BBDD 2025 (insumo)'!$A$2:$A$29,$A58,'1 · BBDD 2025 (insumo)'!$AA$2:$AA$29,1)>0,1,0) -> 0 | C58: =IF(COUNTIFS('1 · BBDD 2025 (insumo)'!$A$2:$A$29,$A58,'1 · BBDD 2025 (insumo)'!$AB$2:$AB$29,1)>0,1,0) -> 0 | D58: =IF(COUNTIFS('1 · BBDD 2025 (insumo)'!$A$2:$A$29,$A58,'1 · BBDD 2025 (insumo)'!$AC$2:$AC$29,1)>0,1,0) -> 1 | E58: =IF(COUNTIFS('1 · BBDD 2025 (insumo)'!$A$2:$A$29,$A58,'1 · BBDD 2025 (insumo)'!$AD$2:$AD$29,1)>0,1,0) -> 1 | F58: =SUM(B58:E58) -> 2
A59: CU | B59: =IF(COUNTIFS('1 · BBDD 2025 (insumo)'!$A$2:$A$29,$A59,'1 · BBDD 2025 (insumo)'!$AA$2:$AA$29,1)>0,1,0) -> 0 | C59: =IF(COUNTIFS('1 · BBDD 2025 (insumo)'!$A$2:$A$29,$A59,'1 · BBDD 2025 (insumo)'!$AB$2:$AB$29,1)>0,1,0) -> 0 | D59: =IF(COUNTIFS('1 · BBDD 2025 (insumo)'!$A$2:$A$29,$A59,'1 · BBDD 2025 (insumo)'!$AC$2:$AC$29,1)>0,1,0) -> 0 | E59: =IF(COUNTIFS('1 · BBDD 2025 (insumo)'!$A$2:$A$29,$A59,'1 · BBDD 2025 (insumo)'!$AD$2:$AD$29,1)>0,1,0) -> 0 | F59: =SUM(B59:E59) -> 0
A60: DO | B60: =IF(COUNTIFS('1 · BBDD 2025 (insumo)'!$A$2:$A$29,$A60,'1 · BBDD 2025 (insumo)'!$AA$2:$AA$29,1)>0,1,0) -> 0 | C60: =IF(COUNTIFS('1 · BBDD 2025 (insumo)'!$A$2:$A$29,$A60,'1 · BBDD 2025 (insumo)'!$AB$2:$AB$29,1)>0,1,0) -> 1 | D60: =IF(COUNTIFS('1 · BBDD 2025 (insumo)'!$A$2:$A$29,$A60,'1 · BBDD 2025 (insumo)'!$AC$2:$AC$29,1)>0,1,0) -> 0 | E60: =IF(COUNTIFS('1 · BBDD 2025 (insumo)'!$A$2:$A$29,$A60,'1 · BBDD 2025 (insumo)'!$AD$2:$AD$29,1)>0,1,0) -> 0 | F60: =SUM(B60:E60) -> 1
A61: EC | B61: =IF(COUNTIFS('1 · BBDD 2025 (insumo)'!$A$2:$A$29,$A61,'1 · BBDD 2025 (insumo)'!$AA$2:$AA$29,1)>0,1,0) -> 0 | C61: =IF(COUNTIFS('1 · BBDD 2025 (insumo)'!$A$2:$A$29,$A61,'1 · BBDD 2025 (insumo)'!$AB$2:$AB$29,1)>0,1,0) -> 1 | D61: =IF(COUNTIFS('1 · BBDD 2025 (insumo)'!$A$2:$A$29,$A61,'1 · BBDD 2025 (insumo)'!$AC$2:$AC$29,1)>0,1,0) -> 0 | E61: =IF(COUNTIFS('1 · BBDD 2025 (insumo)'!$A$2:$A$29,$A61,'1 · BBDD 2025 (insumo)'!$AD$2:$AD$29,1)>0,1,0) -> 0 | F61: =SUM(B61:E61) -> 1
A62: GT | B62: =IF(COUNTIFS('1 · BBDD 2025 (insumo)'!$A$2:$A$29,$A62,'1 · BBDD 2025 (insumo)'!$AA$2:$AA$29,1)>0,1,0) -> 0 | C62: =IF(COUNTIFS('1 · BBDD 2025 (insumo)'!$A$2:$A$29,$A62,'1 · BBDD 2025 (insumo)'!$AB$2:$AB$29,1)>0,1,0) -> 1 | D62: =IF(COUNTIFS('1 · BBDD 2025 (insumo)'!$A$2:$A$29,$A62,'1 · BBDD 2025 (insumo)'!$AC$2:$AC$29,1)>0,1,0) -> 0 | E62: =IF(COUNTIFS('1 · BBDD 2025 (insumo)'!$A$2:$A$29,$A62,'1 · BBDD 2025 (insumo)'!$AD$2:$AD$29,1)>0,1,0) -> 0 | F62: =SUM(B62:E62) -> 1
A63: HN | B63: =IF(COUNTIFS('1 · BBDD 2025 (insumo)'!$A$2:$A$29,$A63,'1 · BBDD 2025 (insumo)'!$AA$2:$AA$29,1)>0,1,0) -> 0 | C63: =IF(COUNTIFS('1 · BBDD 2025 (insumo)'!$A$2:$A$29,$A63,'1 · BBDD 2025 (insumo)'!$AB$2:$AB$29,1)>0,1,0) -> 0 | D63: =IF(COUNTIFS('1 · BBDD 2025 (insumo)'!$A$2:$A$29,$A63,'1 · BBDD 2025 (insumo)'!$AC$2:$AC$29,1)>0,1,0) -> 1 | E63: =IF(COUNTIFS('1 · BBDD 2025 (insumo)'!$A$2:$A$29,$A63,'1 · BBDD 2025 (insumo)'!$AD$2:$AD$29,1)>0,1,0) -> 0 | F63: =SUM(B63:E63) -> 1
A64: JM | B64: =IF(COUNTIFS('1 · BBDD 2025 (insumo)'!$A$2:$A$29,$A64,'1 · BBDD 2025 (insumo)'!$AA$2:$AA$29,1)>0,1,0) -> 0 | C64: =IF(COUNTIFS('1 · BBDD 2025 (insumo)'!$A$2:$A$29,$A64,'1 · BBDD 2025 (insumo)'!$AB$2:$AB$29,1)>0,1,0) -> 0 | D64: =IF(COUNTIFS('1 · BBDD 2025 (insumo)'!$A$2:$A$29,$A64,'1 · BBDD 2025 (insumo)'!$AC$2:$AC$29,1)>0,1,0) -> 0 | E64: =IF(COUNTIFS('1 · BBDD 2025 (insumo)'!$A$2:$A$29,$A64,'1 · BBDD 2025 (insumo)'!$AD$2:$AD$29,1)>0,1,0) -> 0 | F64: =SUM(B64:E64) -> 0
... A72: VE | B72: =IF(COUNTIFS('1 · BBDD 2025 (insumo)'!$A$2:$A$29,$A72,'1 · BBDD 2025 (insumo)'!$AA$2:$AA$29,1)>0,1,0) -> 0 | C72: =IF(COUNTIFS('1 · BBDD 2025 (insumo)'!$A$2:$A$29,$A72,'1 · BBDD 2025 (insumo)'!$AB$2:$AB$29,1)>0,1,0) -> 0 | D72: =IF(COUNTIFS('1 · BBDD 2025 (insumo)'!$A$2:$A$29,$A72,'1 · BBDD 2025 (insumo)'!$AC$2:$AC$29,1)>0,1,0) -> 0 | E72: =IF(COUNTIFS('1 · BBDD 2025 (insumo)'!$A$2:$A$29,$A72,'1 · BBDD 2025 (insumo)'!$AD$2:$AD$29,1)>0,1,0) -> 0 | F72: =SUM(B72:E72) -> 0
A75: GRILLA — Modalidades de continuidad 2025 (Uso único / Plataforma) (20×2)
A76: País | B76: CONT: Uso único | C76: CONT: Plataforma | D76: SUMA
A77: AR | B77: =IF(COUNTIFS('1 · BBDD 2025 (insumo)'!$A$2:$A$29,$A77,'1 · BBDD 2025 (insumo)'!$AH$2:$AH$29,1)>0,1,0) -> 0 | C77: =IF(COUNTIFS('1 · BBDD 2025 (insumo)'!$A$2:$A$29,$A77,'1 · BBDD 2025 (insumo)'!$AI$2:$AI$29,1)>0,1,0) -> 0 | D77: =SUM(B77:C77) -> 0
A78: BO | B78: =IF(COUNTIFS('1 · BBDD 2025 (insumo)'!$A$2:$A$29,$A78,'1 · BBDD 2025 (insumo)'!$AH$2:$AH$29,1)>0,1,0) -> 1 | C78: =IF(COUNTIFS('1 · BBDD 2025 (insumo)'!$A$2:$A$29,$A78,'1 · BBDD 2025 (insumo)'!$AI$2:$AI$29,1)>0,1,0) -> 0 | D78: =SUM(B78:C78) -> 1
A79: BR | B79: =IF(COUNTIFS('1 · BBDD 2025 (insumo)'!$A$2:$A$29,$A79,'1 · BBDD 2025 (insumo)'!$AH$2:$AH$29,1)>0,1,0) -> 0 | C79: =IF(COUNTIFS('1 · BBDD 2025 (insumo)'!$A$2:$A$29,$A79,'1 · BBDD 2025 (insumo)'!$AI$2:$AI$29,1)>0,1,0) -> 1 | D79: =SUM(B79:C79) -> 1
A80: CL | B80: =IF(COUNTIFS('1 · BBDD 2025 (insumo)'!$A$2:$A$29,$A80,'1 · BBDD 2025 (insumo)'!$AH$2:$AH$29,1)>0,1,0) -> 1 | C80: =IF(COUNTIFS('1 · BBDD 2025 (insumo)'!$A$2:$A$29,$A80,'1 · BBDD 2025 (insumo)'!$AI$2:$AI$29,1)>0,1,0) -> 0 | D80: =SUM(B80:C80) -> 1
A81: CO | B81: =IF(COUNTIFS('1 · BBDD 2025 (insumo)'!$A$2:$A$29,$A81,'1 · BBDD 2025 (insumo)'!$AH$2:$AH$29,1)>0,1,0) -> 1 | C81: =IF(COUNTIFS('1 · BBDD 2025 (insumo)'!$A$2:$A$29,$A81,'1 · BBDD 2025 (insumo)'!$AI$2:$AI$29,1)>0,1,0) -> 1 | D81: =SUM(B81:C81) -> 2
A82: CR | B82: =IF(COUNTIFS('1 · BBDD 2025 (insumo)'!$A$2:$A$29,$A82,'1 · BBDD 2025 (insumo)'!$AH$2:$AH$29,1)>0,1,0) -> 0 | C82: =IF(COUNTIFS('1 · BBDD 2025 (insumo)'!$A$2:$A$29,$A82,'1 · BBDD 2025 (insumo)'!$AI$2:$AI$29,1)>0,1,0) -> 1 | D82: =SUM(B82:C82) -> 1
A83: CU | B83: =IF(COUNTIFS('1 · BBDD 2025 (insumo)'!$A$2:$A$29,$A83,'1 · BBDD 2025 (insumo)'!$AH$2:$AH$29,1)>0,1,0) -> 0 | C83: =IF(COUNTIFS('1 · BBDD 2025 (insumo)'!$A$2:$A$29,$A83,'1 · BBDD 2025 (insumo)'!$AI$2:$AI$29,1)>0,1,0) -> 0 | D83: =SUM(B83:C83) -> 0
A84: DO | B84: =IF(COUNTIFS('1 · BBDD 2025 (insumo)'!$A$2:$A$29,$A84,'1 · BBDD 2025 (insumo)'!$AH$2:$AH$29,1)>0,1,0) -> 0 | C84: =IF(COUNTIFS('1 · BBDD 2025 (insumo)'!$A$2:$A$29,$A84,'1 · BBDD 2025 (insumo)'!$AI$2:$AI$29,1)>0,1,0) -> 1 | D84: =SUM(B84:C84) -> 1
A85: EC | B85: =IF(COUNTIFS('1 · BBDD 2025 (insumo)'!$A$2:$A$29,$A85,'1 · BBDD 2025 (insumo)'!$AH$2:$AH$29,1)>0,1,0) -> 0 | C85: =IF(COUNTIFS('1 · BBDD 2025 (insumo)'!$A$2:$A$29,$A85,'1 · BBDD 2025 (insumo)'!$AI$2:$AI$29,1)>0,1,0) -> 1 | D85: =SUM(B85:C85) -> 1
A86: GT | B86: =IF(COUNTIFS('1 · BBDD 2025 (insumo)'!$A$2:$A$29,$A86,'1 · BBDD 2025 (insumo)'!$AH$2:$AH$29,1)>0,1,0) -> 1 | C86: =IF(COUNTIFS('1 · BBDD 2025 (insumo)'!$A$2:$A$29,$A86,'1 · BBDD 2025 (insumo)'!$AI$2:$AI$29,1)>0,1,0) -> 0 | D86: =SUM(B86:C86) -> 1
A87: HN | B87: =IF(COUNTIFS('1 · BBDD 2025 (insumo)'!$A$2:$A$29,$A87,'1 · BBDD 2025 (insumo)'!$AH$2:$AH$29,1)>0,1,0) -> 1 | C87: =IF(COUNTIFS('1 · BBDD 2025 (insumo)'!$A$2:$A$29,$A87,'1 · BBDD 2025 (insumo)'!$AI$2:$AI$29,1)>0,1,0) -> 0 | D87: =SUM(B87:C87) -> 1
A88: JM | B88: =IF(COUNTIFS('1 · BBDD 2025 (insumo)'!$A$2:$A$29,$A88,'1 · BBDD 2025 (insumo)'!$AH$2:$AH$29,1)>0,1,0) -> 0 | C88: =IF(COUNTIFS('1 · BBDD 2025 (insumo)'!$A$2:$A$29,$A88,'1 · BBDD 2025 (insumo)'!$AI$2:$AI$29,1)>0,1,0) -> 0 | D88: =SUM(B88:C88) -> 0
... A96: VE | B96: =IF(COUNTIFS('1 · BBDD 2025 (insumo)'!$A$2:$A$29,$A96,'1 · BBDD 2025 (insumo)'!$AH$2:$AH$29,1)>0,1,0) -> 0 | C96: =IF(COUNTIFS('1 · BBDD 2025 (insumo)'!$A$2:$A$29,$A96,'1 · BBDD 2025 (insumo)'!$AI$2:$AI$29,1)>0,1,0) -> 0 | D96: =SUM(B96:C96) -> 0
A99: GRILLA — Tipos de organización 2025 (Público/Privado/Mixto) (20×3)
A100: País | B100: ORG: Público | C100: ORG: Privado | D100: ORG: Mixto | E100: SUMA
A101: AR | B101: =IF(COUNTIFS('1 · BBDD 2025 (insumo)'!$A$2:$A$29,$A101,'1 · BBDD 2025 (insumo)'!$AE$2:$AE$29,1)>0,1,0) -> 0 | C101: =IF(COUNTIFS('1 · BBDD 2025 (insumo)'!$A$2:$A$29,$A101,'1 · BBDD 2025 (insumo)'!$AF$2:$AF$29,1)>0,1,0) -> 0 | D101: =IF(COUNTIFS('1 · BBDD 2025 (insumo)'!$A$2:$A$29,$A101,'1 · BBDD 2025 (insumo)'!$AG$2:$AG$29,1)>0,1,0) -> 0 | E101: =SUM(B101:D101) -> 0
A102: BO | B102: =IF(COUNTIFS('1 · BBDD 2025 (insumo)'!$A$2:$A$29,$A102,'1 · BBDD 2025 (insumo)'!$AE$2:$AE$29,1)>0,1,0) -> 1 | C102: =IF(COUNTIFS('1 · BBDD 2025 (insumo)'!$A$2:$A$29,$A102,'1 · BBDD 2025 (insumo)'!$AF$2:$AF$29,1)>0,1,0) -> 0 | D102: =IF(COUNTIFS('1 · BBDD 2025 (insumo)'!$A$2:$A$29,$A102,'1 · BBDD 2025 (insumo)'!$AG$2:$AG$29,1)>0,1,0) -> 0 | E102: =SUM(B102:D102) -> 1
A103: BR | B103: =IF(COUNTIFS('1 · BBDD 2025 (insumo)'!$A$2:$A$29,$A103,'1 · BBDD 2025 (insumo)'!$AE$2:$AE$29,1)>0,1,0) -> 1 | C103: =IF(COUNTIFS('1 · BBDD 2025 (insumo)'!$A$2:$A$29,$A103,'1 · BBDD 2025 (insumo)'!$AF$2:$AF$29,1)>0,1,0) -> 1 | D103: =IF(COUNTIFS('1 · BBDD 2025 (insumo)'!$A$2:$A$29,$A103,'1 · BBDD 2025 (insumo)'!$AG$2:$AG$29,1)>0,1,0) -> 0 | E103: =SUM(B103:D103) -> 2
A104: CL | B104: =IF(COUNTIFS('1 · BBDD 2025 (insumo)'!$A$2:$A$29,$A104,'1 · BBDD 2025 (insumo)'!$AE$2:$AE$29,1)>0,1,0) -> 1 | C104: =IF(COUNTIFS('1 · BBDD 2025 (insumo)'!$A$2:$A$29,$A104,'1 · BBDD 2025 (insumo)'!$AF$2:$AF$29,1)>0,1,0) -> 1 | D104: =IF(COUNTIFS('1 · BBDD 2025 (insumo)'!$A$2:$A$29,$A104,'1 · BBDD 2025 (insumo)'!$AG$2:$AG$29,1)>0,1,0) -> 1 | E104: =SUM(B104:D104) -> 3
A105: CO | B105: =IF(COUNTIFS('1 · BBDD 2025 (insumo)'!$A$2:$A$29,$A105,'1 · BBDD 2025 (insumo)'!$AE$2:$AE$29,1)>0,1,0) -> 1 | C105: =IF(COUNTIFS('1 · BBDD 2025 (insumo)'!$A$2:$A$29,$A105,'1 · BBDD 2025 (insumo)'!$AF$2:$AF$29,1)>0,1,0) -> 0 | D105: =IF(COUNTIFS('1 · BBDD 2025 (insumo)'!$A$2:$A$29,$A105,'1 · BBDD 2025 (insumo)'!$AG$2:$AG$29,1)>0,1,0) -> 1 | E105: =SUM(B105:D105) -> 2
A106: CR | B106: =IF(COUNTIFS('1 · BBDD 2025 (insumo)'!$A$2:$A$29,$A106,'1 · BBDD 2025 (insumo)'!$AE$2:$AE$29,1)>0,1,0) -> 1 | C106: =IF(COUNTIFS('1 · BBDD 2025 (insumo)'!$A$2:$A$29,$A106,'1 · BBDD 2025 (insumo)'!$AF$2:$AF$29,1)>0,1,0) -> 0 | D106: =IF(COUNTIFS('1 · BBDD 2025 (insumo)'!$A$2:$A$29,$A106,'1 · BBDD 2025 (insumo)'!$AG$2:$AG$29,1)>0,1,0) -> 0 | E106: =SUM(B106:D106) -> 1
A107: CU | B107: =IF(COUNTIFS('1 · BBDD 2025 (insumo)'!$A$2:$A$29,$A107,'1 · BBDD 2025 (insumo)'!$AE$2:$AE$29,1)>0,1,0) -> 0 | C107: =IF(COUNTIFS('1 · BBDD 2025 (insumo)'!$A$2:$A$29,$A107,'1 · BBDD 2025 (insumo)'!$AF$2:$AF$29,1)>0,1,0) -> 0 | D107: =IF(COUNTIFS('1 · BBDD 2025 (insumo)'!$A$2:$A$29,$A107,'1 · BBDD 2025 (insumo)'!$AG$2:$AG$29,1)>0,1,0) -> 0 | E107: =SUM(B107:D107) -> 0
A108: DO | B108: =IF(COUNTIFS('1 · BBDD 2025 (insumo)'!$A$2:$A$29,$A108,'1 · BBDD 2025 (insumo)'!$AE$2:$AE$29,1)>0,1,0) -> 0 | C108: =IF(COUNTIFS('1 · BBDD 2025 (insumo)'!$A$2:$A$29,$A108,'1 · BBDD 2025 (insumo)'!$AF$2:$AF$29,1)>0,1,0) -> 0 | D108: =IF(COUNTIFS('1 · BBDD 2025 (insumo)'!$A$2:$A$29,$A108,'1 · BBDD 2025 (insumo)'!$AG$2:$AG$29,1)>0,1,0) -> 1 | E108: =SUM(B108:D108) -> 1
A109: EC | B109: =IF(COUNTIFS('1 · BBDD 2025 (insumo)'!$A$2:$A$29,$A109,'1 · BBDD 2025 (insumo)'!$AE$2:$AE$29,1)>0,1,0) -> 0 | C109: =IF(COUNTIFS('1 · BBDD 2025 (insumo)'!$A$2:$A$29,$A109,'1 · BBDD 2025 (insumo)'!$AF$2:$AF$29,1)>0,1,0) -> 0 | D109: =IF(COUNTIFS('1 · BBDD 2025 (insumo)'!$A$2:$A$29,$A109,'1 · BBDD 2025 (insumo)'!$AG$2:$AG$29,1)>0,1,0) -> 1 | E109: =SUM(B109:D109) -> 1
A110: GT | B110: =IF(COUNTIFS('1 · BBDD 2025 (insumo)'!$A$2:$A$29,$A110,'1 · BBDD 2025 (insumo)'!$AE$2:$AE$29,1)>0,1,0) -> 0 | C110: =IF(COUNTIFS('1 · BBDD 2025 (insumo)'!$A$2:$A$29,$A110,'1 · BBDD 2025 (insumo)'!$AF$2:$AF$29,1)>0,1,0) -> 0 | D110: =IF(COUNTIFS('1 · BBDD 2025 (insumo)'!$A$2:$A$29,$A110,'1 · BBDD 2025 (insumo)'!$AG$2:$AG$29,1)>0,1,0) -> 1 | E110: =SUM(B110:D110) -> 1
A111: HN | B111: =IF(COUNTIFS('1 · BBDD 2025 (insumo)'!$A$2:$A$29,$A111,'1 · BBDD 2025 (insumo)'!$AE$2:$AE$29,1)>0,1,0) -> 1 | C111: =IF(COUNTIFS('1 · BBDD 2025 (insumo)'!$A$2:$A$29,$A111,'1 · BBDD 2025 (insumo)'!$AF$2:$AF$29,1)>0,1,0) -> 0 | D111: =IF(COUNTIFS('1 · BBDD 2025 (insumo)'!$A$2:$A$29,$A111,'1 · BBDD 2025 (insumo)'!$AG$2:$AG$29,1)>0,1,0) -> 0 | E111: =SUM(B111:D111) -> 1
A112: JM | B112: =IF(COUNTIFS('1 · BBDD 2025 (insumo)'!$A$2:$A$29,$A112,'1 · BBDD 2025 (insumo)'!$AE$2:$AE$29,1)>0,1,0) -> 0 | C112: =IF(COUNTIFS('1 · BBDD 2025 (insumo)'!$A$2:$A$29,$A112,'1 · BBDD 2025 (insumo)'!$AF$2:$AF$29,1)>0,1,0) -> 0 | D112: =IF(COUNTIFS('1 · BBDD 2025 (insumo)'!$A$2:$A$29,$A112,'1 · BBDD 2025 (insumo)'!$AG$2:$AG$29,1)>0,1,0) -> 0 | E112: =SUM(B112:D112) -> 0
... A120: VE | B120: =IF(COUNTIFS('1 · BBDD 2025 (insumo)'!$A$2:$A$29,$A120,'1 · BBDD 2025 (insumo)'!$AE$2:$AE$29,1)>0,1,0) -> 0 | C120: =IF(COUNTIFS('1 · BBDD 2025 (insumo)'!$A$2:$A$29,$A120,'1 · BBDD 2025 (insumo)'!$AF$2:$AF$29,1)>0,1,0) -> 0 | D120: =IF(COUNTIFS('1 · BBDD 2025 (insumo)'!$A$2:$A$29,$A120,'1 · BBDD 2025 (insumo)'!$AG$2:$AG$29,1)>0,1,0) -> 0 | E120: =SUM(B120:D120) -> 0
A123: GRILLA — Tipos de desarrollador con origen NACIONAL (20×4)
A124: País | B124: DEV: Industria | C124: DEV: Academia | D124: DEV: Gobierno | E124: DEV: Sociedad Civil | F124: SUMA
A125: AR | B125: =IF(COUNTIFS('1 · BBDD 2025 (insumo)'!$A$2:$A$29,$A125,'1 · BBDD 2025 (insumo)'!$AJ$2:$AJ$29,1,'1 · BBDD 2025 (insumo)'!$AN$2:$AN$29,1)>0,1,0) -> 0 | C125: =IF(COUNTIFS('1 · BBDD 2025 (insumo)'!$A$2:$A$29,$A125,'1 · BBDD 2025 (insumo)'!$AK$2:$AK$29,1,'1 · BBDD 2025 (insumo)'!$AN$2:$AN$29,1)>0,1,0) -> 0 | D125: =IF(COUNTIFS('1 · BBDD 2025 (insumo)'!$A$2:$A$29,$A125,'1 · BBDD 2025 (insumo)'!$AL$2:$AL$29,1,'1 · BBDD 2025 (insumo)'!$AN$2:$AN$29,1)>0,1,0) -> 0 | E125: =IF(COUNTIFS('1 · BBDD 2025 (insumo)'!$A$2:$A$29,$A125,'1 · BBDD 2025 (insumo)'!$AM$2:$AM$29,1,'1 · BBDD 2025 (insumo)'!$AN$2:$AN$29,1)>0,1,0) -> 0 | F125: =SUM(B125:E125) -> 0
A126: BO | B126: =IF(COUNTIFS('1 · BBDD 2025 (insumo)'!$A$2:$A$29,$A126,'1 · BBDD 2025 (insumo)'!$AJ$2:$AJ$29,1,'1 · BBDD 2025 (insumo)'!$AN$2:$AN$29,1)>0,1,0) -> 0 | C126: =IF(COUNTIFS('1 · BBDD 2025 (insumo)'!$A$2:$A$29,$A126,'1 · BBDD 2025 (insumo)'!$AK$2:$AK$29,1,'1 · BBDD 2025 (insumo)'!$AN$2:$AN$29,1)>0,1,0) -> 0 | D126: =IF(COUNTIFS('1 · BBDD 2025 (insumo)'!$A$2:$A$29,$A126,'1 · BBDD 2025 (insumo)'!$AL$2:$AL$29,1,'1 · BBDD 2025 (insumo)'!$AN$2:$AN$29,1)>0,1,0) -> 0 | E126: =IF(COUNTIFS('1 · BBDD 2025 (insumo)'!$A$2:$A$29,$A126,'1 · BBDD 2025 (insumo)'!$AM$2:$AM$29,1,'1 · BBDD 2025 (insumo)'!$AN$2:$AN$29,1)>0,1,0) -> 0 | F126: =SUM(B126:E126) -> 0
A127: BR | B127: =IF(COUNTIFS('1 · BBDD 2025 (insumo)'!$A$2:$A$29,$A127,'1 · BBDD 2025 (insumo)'!$AJ$2:$AJ$29,1,'1 · BBDD 2025 (insumo)'!$AN$2:$AN$29,1)>0,1,0) -> 1 | C127: =IF(COUNTIFS('1 · BBDD 2025 (insumo)'!$A$2:$A$29,$A127,'1 · BBDD 2025 (insumo)'!$AK$2:$AK$29,1,'1 · BBDD 2025 (insumo)'!$AN$2:$AN$29,1)>0,1,0) -> 1 | D127: =IF(COUNTIFS('1 · BBDD 2025 (insumo)'!$A$2:$A$29,$A127,'1 · BBDD 2025 (insumo)'!$AL$2:$AL$29,1,'1 · BBDD 2025 (insumo)'!$AN$2:$AN$29,1)>0,1,0) -> 1 | E127: =IF(COUNTIFS('1 · BBDD 2025 (insumo)'!$A$2:$A$29,$A127,'1 · BBDD 2025 (insumo)'!$AM$2:$AM$29,1,'1 · BBDD 2025 (insumo)'!$AN$2:$AN$29,1)>0,1,0) -> 0 | F127: =SUM(B127:E127) -> 3
A128: CL | B128: =IF(COUNTIFS('1 · BBDD 2025 (insumo)'!$A$2:$A$29,$A128,'1 · BBDD 2025 (insumo)'!$AJ$2:$AJ$29,1,'1 · BBDD 2025 (insumo)'!$AN$2:$AN$29,1)>0,1,0) -> 1 | C128: =IF(COUNTIFS('1 · BBDD 2025 (insumo)'!$A$2:$A$29,$A128,'1 · BBDD 2025 (insumo)'!$AK$2:$AK$29,1,'1 · BBDD 2025 (insumo)'!$AN$2:$AN$29,1)>0,1,0) -> 1 | D128: =IF(COUNTIFS('1 · BBDD 2025 (insumo)'!$A$2:$A$29,$A128,'1 · BBDD 2025 (insumo)'!$AL$2:$AL$29,1,'1 · BBDD 2025 (insumo)'!$AN$2:$AN$29,1)>0,1,0) -> 0 | E128: =IF(COUNTIFS('1 · BBDD 2025 (insumo)'!$A$2:$A$29,$A128,'1 · BBDD 2025 (insumo)'!$AM$2:$AM$29,1,'1 · BBDD 2025 (insumo)'!$AN$2:$AN$29,1)>0,1,0) -> 0 | F128: =SUM(B128:E128) -> 2
A129: CO | B129: =IF(COUNTIFS('1 · BBDD 2025 (insumo)'!$A$2:$A$29,$A129,'1 · BBDD 2025 (insumo)'!$AJ$2:$AJ$29,1,'1 · BBDD 2025 (insumo)'!$AN$2:$AN$29,1)>0,1,0) -> 1 | C129: =IF(COUNTIFS('1 · BBDD 2025 (insumo)'!$A$2:$A$29,$A129,'1 · BBDD 2025 (insumo)'!$AK$2:$AK$29,1,'1 · BBDD 2025 (insumo)'!$AN$2:$AN$29,1)>0,1,0) -> 0 | D129: =IF(COUNTIFS('1 · BBDD 2025 (insumo)'!$A$2:$A$29,$A129,'1 · BBDD 2025 (insumo)'!$AL$2:$AL$29,1,'1 · BBDD 2025 (insumo)'!$AN$2:$AN$29,1)>0,1,0) -> 1 | E129: =IF(COUNTIFS('1 · BBDD 2025 (insumo)'!$A$2:$A$29,$A129,'1 · BBDD 2025 (insumo)'!$AM$2:$AM$29,1,'1 · BBDD 2025 (insumo)'!$AN$2:$AN$29,1)>0,1,0) -> 1 | F129: =SUM(B129:E129) -> 3
A130: CR | B130: =IF(COUNTIFS('1 · BBDD 2025 (insumo)'!$A$2:$A$29,$A130,'1 · BBDD 2025 (insumo)'!$AJ$2:$AJ$29,1,'1 · BBDD 2025 (insumo)'!$AN$2:$AN$29,1)>0,1,0) -> 0 | C130: =IF(COUNTIFS('1 · BBDD 2025 (insumo)'!$A$2:$A$29,$A130,'1 · BBDD 2025 (insumo)'!$AK$2:$AK$29,1,'1 · BBDD 2025 (insumo)'!$AN$2:$AN$29,1)>0,1,0) -> 1 | D130: =IF(COUNTIFS('1 · BBDD 2025 (insumo)'!$A$2:$A$29,$A130,'1 · BBDD 2025 (insumo)'!$AL$2:$AL$29,1,'1 · BBDD 2025 (insumo)'!$AN$2:$AN$29,1)>0,1,0) -> 0 | E130: =IF(COUNTIFS('1 · BBDD 2025 (insumo)'!$A$2:$A$29,$A130,'1 · BBDD 2025 (insumo)'!$AM$2:$AM$29,1,'1 · BBDD 2025 (insumo)'!$AN$2:$AN$29,1)>0,1,0) -> 0 | F130: =SUM(B130:E130) -> 1
A131: CU | B131: =IF(COUNTIFS('1 · BBDD 2025 (insumo)'!$A$2:$A$29,$A131,'1 · BBDD 2025 (insumo)'!$AJ$2:$AJ$29,1,'1 · BBDD 2025 (insumo)'!$AN$2:$AN$29,1)>0,1,0) -> 0 | C131: =IF(COUNTIFS('1 · BBDD 2025 (insumo)'!$A$2:$A$29,$A131,'1 · BBDD 2025 (insumo)'!$AK$2:$AK$29,1,'1 · BBDD 2025 (insumo)'!$AN$2:$AN$29,1)>0,1,0) -> 0 | D131: =IF(COUNTIFS('1 · BBDD 2025 (insumo)'!$A$2:$A$29,$A131,'1 · BBDD 2025 (insumo)'!$AL$2:$AL$29,1,'1 · BBDD 2025 (insumo)'!$AN$2:$AN$29,1)>0,1,0) -> 0 | E131: =IF(COUNTIFS('1 · BBDD 2025 (insumo)'!$A$2:$A$29,$A131,'1 · BBDD 2025 (insumo)'!$AM$2:$AM$29,1,'1 · BBDD 2025 (insumo)'!$AN$2:$AN$29,1)>0,1,0) -> 0 | F131: =SUM(B131:E131) -> 0
A132: DO | B132: =IF(COUNTIFS('1 · BBDD 2025 (insumo)'!$A$2:$A$29,$A132,'1 · BBDD 2025 (insumo)'!$AJ$2:$AJ$29,1,'1 · BBDD 2025 (insumo)'!$AN$2:$AN$29,1)>0,1,0) -> 1 | C132: =IF(COUNTIFS('1 · BBDD 2025 (insumo)'!$A$2:$A$29,$A132,'1 · BBDD 2025 (insumo)'!$AK$2:$AK$29,1,'1 · BBDD 2025 (insumo)'!$AN$2:$AN$29,1)>0,1,0) -> 0 | D132: =IF(COUNTIFS('1 · BBDD 2025 (insumo)'!$A$2:$A$29,$A132,'1 · BBDD 2025 (insumo)'!$AL$2:$AL$29,1,'1 · BBDD 2025 (insumo)'!$AN$2:$AN$29,1)>0,1,0) -> 0 | E132: =IF(COUNTIFS('1 · BBDD 2025 (insumo)'!$A$2:$A$29,$A132,'1 · BBDD 2025 (insumo)'!$AM$2:$AM$29,1,'1 · BBDD 2025 (insumo)'!$AN$2:$AN$29,1)>0,1,0) -> 0 | F132: =SUM(B132:E132) -> 1
A133: EC | B133: =IF(COUNTIFS('1 · BBDD 2025 (insumo)'!$A$2:$A$29,$A133,'1 · BBDD 2025 (insumo)'!$AJ$2:$AJ$29,1,'1 · BBDD 2025 (insumo)'!$AN$2:$AN$29,1)>0,1,0) -> 0 | C133: =IF(COUNTIFS('1 · BBDD 2025 (insumo)'!$A$2:$A$29,$A133,'1 · BBDD 2025 (insumo)'!$AK$2:$AK$29,1,'1 · BBDD 2025 (insumo)'!$AN$2:$AN$29,1)>0,1,0) -> 0 | D133: =IF(COUNTIFS('1 · BBDD 2025 (insumo)'!$A$2:$A$29,$A133,'1 · BBDD 2025 (insumo)'!$AL$2:$AL$29,1,'1 · BBDD 2025 (insumo)'!$AN$2:$AN$29,1)>0,1,0) -> 0 | E133: =IF(COUNTIFS('1 · BBDD 2025 (insumo)'!$A$2:$A$29,$A133,'1 · BBDD 2025 (insumo)'!$AM$2:$AM$29,1,'1 · BBDD 2025 (insumo)'!$AN$2:$AN$29,1)>0,1,0) -> 1 | F133: =SUM(B133:E133) -> 1
A134: GT | B134: =IF(COUNTIFS('1 · BBDD 2025 (insumo)'!$A$2:$A$29,$A134,'1 · BBDD 2025 (insumo)'!$AJ$2:$AJ$29,1,'1 · BBDD 2025 (insumo)'!$AN$2:$AN$29,1)>0,1,0) -> 0 | C134: =IF(COUNTIFS('1 · BBDD 2025 (insumo)'!$A$2:$A$29,$A134,'1 · BBDD 2025 (insumo)'!$AK$2:$AK$29,1,'1 · BBDD 2025 (insumo)'!$AN$2:$AN$29,1)>0,1,0) -> 0 | D134: =IF(COUNTIFS('1 · BBDD 2025 (insumo)'!$A$2:$A$29,$A134,'1 · BBDD 2025 (insumo)'!$AL$2:$AL$29,1,'1 · BBDD 2025 (insumo)'!$AN$2:$AN$29,1)>0,1,0) -> 0 | E134: =IF(COUNTIFS('1 · BBDD 2025 (insumo)'!$A$2:$A$29,$A134,'1 · BBDD 2025 (insumo)'!$AM$2:$AM$29,1,'1 · BBDD 2025 (insumo)'!$AN$2:$AN$29,1)>0,1,0) -> 0 | F134: =SUM(B134:E134) -> 0
A135: HN | B135: =IF(COUNTIFS('1 · BBDD 2025 (insumo)'!$A$2:$A$29,$A135,'1 · BBDD 2025 (insumo)'!$AJ$2:$AJ$29,1,'1 · BBDD 2025 (insumo)'!$AN$2:$AN$29,1)>0,1,0) -> 0 | C135: =IF(COUNTIFS('1 · BBDD 2025 (insumo)'!$A$2:$A$29,$A135,'1 · BBDD 2025 (insumo)'!$AK$2:$AK$29,1,'1 · BBDD 2025 (insumo)'!$AN$2:$AN$29,1)>0,1,0) -> 1 | D135: =IF(COUNTIFS('1 · BBDD 2025 (insumo)'!$A$2:$A$29,$A135,'1 · BBDD 2025 (insumo)'!$AL$2:$AL$29,1,'1 · BBDD 2025 (insumo)'!$AN$2:$AN$29,1)>0,1,0) -> 1 | E135: =IF(COUNTIFS('1 · BBDD 2025 (insumo)'!$A$2:$A$29,$A135,'1 · BBDD 2025 (insumo)'!$AM$2:$AM$29,1,'1 · BBDD 2025 (insumo)'!$AN$2:$AN$29,1)>0,1,0) -> 0 | F135: =SUM(B135:E135) -> 2
A136: JM | B136: =IF(COUNTIFS('1 · BBDD 2025 (insumo)'!$A$2:$A$29,$A136,'1 · BBDD 2025 (insumo)'!$AJ$2:$AJ$29,1,'1 · BBDD 2025 (insumo)'!$AN$2:$AN$29,1)>0,1,0) -> 0 | C136: =IF(COUNTIFS('1 · BBDD 2025 (insumo)'!$A$2:$A$29,$A136,'1 · BBDD 2025 (insumo)'!$AK$2:$AK$29,1,'1 · BBDD 2025 (insumo)'!$AN$2:$AN$29,1)>0,1,0) -> 0 | D136: =IF(COUNTIFS('1 · BBDD 2025 (insumo)'!$A$2:$A$29,$A136,'1 · BBDD 2025 (insumo)'!$AL$2:$AL$29,1,'1 · BBDD 2025 (insumo)'!$AN$2:$AN$29,1)>0,1,0) -> 0 | E136: =IF(COUNTIFS('1 · BBDD 2025 (insumo)'!$A$2:$A$29,$A136,'1 · BBDD 2025 (insumo)'!$AM$2:$AM$29,1,'1 · BBDD 2025 (insumo)'!$AN$2:$AN$29,1)>0,1,0) -> 0 | F136: =SUM(B136:E136) -> 0
...

Sheet 3 · Cálculo 2025 · f. nueva
A1: CÁLCULO 2025 CON LA FÓRMULA NUEVA (CENIA v2 · 5 variables · misma base 2025 recodificada)
A2: País | B2: N iniciativas | C2: nº tipos | D2: V1 Tipos de proceso | E2: nº etapas | F2: V2 Etapas de uso | G2: nivel máx (efectivo) | H2: V3 Continuidad | I2: nº tipos gub | J2: nº tipos no-gub | K2: nº combinaciones | L2: V4 Convocante | M2: V5 Cantidad | N2: Sub1 Uso | O2: Sub1 red. | P2: V Desarrollador (=f. antigua) | Q2: V Tipos de IA (=f. antigua) | R2: Sub2 Desarrollo (=f. antigua) | S2: Sub2 red. | T2: INDICADOR 2025 · fórmula nueva
A3: AR | B3: =COUNTIF('1 · BBDD 2025 (insumo)'!$A$2:$A$29,$A3) -> 0 | C3: ='2 · Cálculo 2025 · f. antigua'!C3 -> 0 | D3: =C3/5*100 -> 0 | E3: ='2 · Cálculo 2025 · f. antigua'!E3 -> 0 | F3: =E3/4*100 -> 0 | G3: =_xlfn.MAXIFS('1 · BBDD 2025 (insumo)'!$AW$2:$AW$29,'1 · BBDD 2025 (insumo)'!$A$2:$A$29,$A3) -> 0 | H3: =G3/3*100 -> 0 | I3: =$E$47 -> 0 | J3: =$F$71 -> 0 | K3: =SUMIFS('1 · BBDD 2025 (insumo)'!$AY$2:$AY$29,'1 · BBDD 2025 (insumo)'!$A$2:$A$29,$A3) -> 0 | L3: =(I3/3+J3/4+IF($C$27=0,0,K3/$C$27))/3*100 -> 0 | M3: =IF(B3=0,$F$29,IF(B3<=3,$F$30,IF(B3<=6,$F$31,IF(B3<=9,$F$32,$F$33)))) -> 0 | N3: =(D3+F3+H3+L3+M3)/5 -> 0 | O3: =ROUND(N3,0) -> 0 | P3: ='2 · Cálculo 2025 · f. antigua'!O3 -> 0 | Q3: ='2 · Cálculo 2025 · f. antigua'!Q3 -> 0 | R3: ='2 · Cálculo 2025 · f. antigua'!R3 -> 0 | S3: =ROUND(R3,0) -> 0 | T3: =ROUND((O3+S3)/2,0) -> 0
A4: BO | B4: =COUNTIF('1 · BBDD 2025 (insumo)'!$A$2:$A$29,$A4) -> 1 | C4: ='2 · Cálculo 2025 · f. antigua'!C4 -> 1 | D4: =C4/5*100 -> 20 | E4: ='2 · Cálculo 2025 · f. antigua'!E4 -> 2 | F4: =E4/4*100 -> 50 | G4: =_xlfn.MAXIFS('1 · BBDD 2025 (insumo)'!$AW$2:$AW$29,'1 · BBDD 2025 (insumo)'!$A$2:$A$29,$A4) -> 2 | H4: =G4/3*100 -> 66.666667 | I4: =$E$48 -> 1 | J4: =$F$72 -> 1 | K4: =SUMIFS('1 · BBDD 2025 (insumo)'!$AY$2:$AY$29,'1 · BBDD 2025 (insumo)'!$A$2:$A$29,$A4) -> 1 | L4: =(I4/3+J4/4+IF($C$27=0,0,K4/$C$27))/3*100 -> 36.111111 | M4: =IF(B4=0,$F$29,IF(B4<=3,$F$30,IF(B4<=6,$F$31,IF(B4<=9,$F$32,$F$33)))) -> 25 | N4: =(D4+F4+H4+L4+M4)/5 -> 39.555556 | O4: =ROUND(N4,0) -> 40 | P4: ='2 · Cálculo 2025 · f. antigua'!O4 -> 25 | Q4: ='2 · Cálculo 2025 · f. antigua'!Q4 -> 20 | R4: ='2 · Cálculo 2025 · f. antigua'!R4 -> 22.5 | S4: =ROUND(R4,0) -> 23 | T4: =ROUND((O4+S4)/2,0) -> 32
A5: BR | B5: =COUNTIF('1 · BBDD 2025 (insumo)'!$A$2:$A$29,$A5) -> 4 | C5: ='2 · Cálculo 2025 · f. antigua'!C5 -> 1 | D5: =C5/5*100 -> 20 | E5: ='2 · Cálculo 2025 · f. antigua'!E5 -> 3 | F5: =E5/4*100 -> 75 | G5: =_xlfn.MAXIFS('1 · BBDD 2025 (insumo)'!$AW$2:$AW$29,'1 · BBDD 2025 (insumo)'!$A$2:$A$29,$A5) -> 2 | H5: =G5/3*100 -> 66.666667 | I5: =$E$49 -> 2 | J5: =$F$73 -> 2 | K5: =SUMIFS('1 · BBDD 2025 (insumo)'!$AY$2:$AY$29,'1 · BBDD 2025 (insumo)'!$A$2:$A$29,$A5) -> 0 | L5: =(I5/3+J5/4+IF($C$27=0,0,K5/$C$27))/3*100 -> 38.888889 | M5: =IF(B5=0,$F$29,IF(B5<=3,$F$30,IF(B5<=6,$F$31,IF(B5<=9,$F$32,$F$33)))) -> 50 | N5: =(D5+F5+H5+L5+M5)/5 -> 50.111111 | O5: =ROUND(N5,0) -> 50 | P5: ='2 · Cálculo 2025 · f. antigua'!O5 -> 100 | Q5: ='2 · Cálculo 2025 · f. antigua'!Q5 -> 100 | R5: ='2 · Cálculo 2025 · f. antigua'!R5 -> 100 | S5: =ROUND(R5,0) -> 100 | T5: =ROUND((O5+S5)/2,0) -> 75
A6: CL | B6: =COUNTIF('1 · BBDD 2025 (insumo)'!$A$2:$A$29,$A6) -> 9 | C6: ='2 · Cálculo 2025 · f. antigua'!C6 -> 1 | D6: =C6/5*100 -> 20 | E6: ='2 · Cálculo 2025 · f. antigua'!E6 -> 2 | F6: =E6/4*100 -> 50 | G6: =_xlfn.MAXIFS('1 · BBDD 2025 (insumo)'!$AW$2:$AW$29,'1 · BBDD 2025 (insumo)'!$A$2:$A$29,$A6) -> 2 | H6: =G6/3*100 -> 66.666667 | I6: =$E$50 -> 2 | J6: =$F$74 -> 3 | K6: =SUMIFS('1 · BBDD 2025 (insumo)'!$AY$2:$AY$29,'1 · BBDD 2025 (insumo)'!$A$2:$A$29,$A6) -> 1 | L6: =(I6/3+J6/4+IF($C$27=0,0,K6/$C$27))/3*100 -> 63.888889 | M6: =IF(B6=0,$F$29,IF(B6<=3,$F$30,IF(B6<=6,$F$31,IF(B6<=9,$F$32,$F$33)))) -> 75 | N6: =(D6+F6+H6+L6+M6)/5 -> 55.111111 | O6: =ROUND(N6,0) -> 55 | P6: ='2 · Cálculo 2025 · f. antigua'!O6 -> 58.333333 | Q6: ='2 · Cálculo 2025 · f. antigua'!Q6 -> 60 | R6: ='2 · Cálculo 2025 · f. antigua'!R6 -> 59.166667 | S6: =ROUND(R6,0) -> 59 | T6: =ROUND((O6+S6)/2,0) -> 57
A7: CO | B7: =COUNTIF('1 · BBDD 2025 (insumo)'!$A$2:$A$29,$A7) -> 4 | C7: ='2 · Cálculo 2025 · f. antigua'!C7 -> 3 | D7: =C7/5*100 -> 60 | E7: ='2 · Cálculo 2025 · f. antigua'!E7 -> 2 | F7: =E7/4*100 -> 50 | G7: =_xlfn.MAXIFS('1 · BBDD 2025 (insumo)'!$AW$2:$AW$29,'1 · BBDD 2025 (insumo)'!$A$2:$A$29,$A7) -> 2 | H7: =G7/3*100 -> 66.666667 | I7: =$E$51 -> 2 | J7: =$F$75 -> 4 | K7: =SUMIFS('1 · BBDD 2025 (insumo)'!$AY$2:$AY$29,'1 · BBDD 2025 (insumo)'!$A$2:$A$29,$A7) -> 2 | L7: =(I7/3+J7/4+IF($C$27=0,0,K7/$C$27))/3*100 -> 88.888889 | M7: =IF(B7=0,$F$29,IF(B7<=3,$F$30,IF(B7<=6,$F$31,IF(B7<=9,$F$32,$F$33)))) -> 50 | N7: =(D7+F7+H7+L7+M7)/5 -> 63.111111 | O7: =ROUND(N7,0) -> 63 | P7: ='2 · Cálculo 2025 · f. antigua'!O7 -> 100 | Q7: ='2 · Cálculo 2025 · f. antigua'!Q7 -> 100 | R7: ='2 · Cálculo 2025 · f. antigua'!R7 -> 100 | S7: =ROUND(R7,0) -> 100 | T7: =ROUND((O7+S7)/2,0) -> 82
A8: CR | B8: =COUNTIF('1 · BBDD 2025 (insumo)'!$A$2:$A$29,$A8) -> 2 | C8: ='2 · Cálculo 2025 · f. antigua'!C8 -> 1 | D8: =C8/5*100 -> 20 | E8: ='2 · Cálculo 2025 · f. antigua'!E8 -> 2 | F8: =E8/4*100 -> 50 | G8: =_xlfn.MAXIFS('1 · BBDD 2025 (insumo)'!$AW$2:$AW$29,'1 · BBDD 2025 (insumo)'!$A$2:$A$29,$A8) -> 2 | H8: =G8/3*100 -> 66.666667 | I8: =$E$52 -> 1 | J8: =$F$76 -> 1 | K8: =SUMIFS('1 · BBDD 2025 (insumo)'!$AY$2:$AY$29,'1 · BBDD 2025 (insumo)'!$A$2:$A$29,$A8) -> 0 | L8: =(I8/3+J8/4+IF($C$27=0,0,K8/$C$27))/3*100 -> 19.444444 | M8: =IF(B8=0,$F$29,IF(B8<=3,$F$30,IF(B8<=6,$F$31,IF(B8<=9,$F$32,$F$33)))) -> 25 | N8: =(D8+F8+H8+L8+M8)/5 -> 36.222222 | O8: =ROUND(N8,0) -> 36 | P8: ='2 · Cálculo 2025 · f. antigua'!O8 -> 66.666667 | Q8: ='2 · Cálculo 2025 · f. antigua'!Q8 -> 40 | R8: ='2 · Cálculo 2025 · f. antigua'!R8 -> 53.333333 | S8: =ROUND(R8,0) -> 53 | T8: =ROUND((O8+S8)/2,0) -> 45
A9: CU | B9: =COUNTIF('1 · BBDD 2025 (insumo)'!$A$2:$A$29,$A9) -> 0 | C9: ='2 · Cálculo 2025 · f. antigua'!C9 -> 0 | D9: =C9/5*100 -> 0 | E9: ='2 · Cálculo 2025 · f. antigua'!E9 -> 0 | F9: =E9/4*100 -> 0 | G9: =_xlfn.MAXIFS('1 · BBDD 2025 (insumo)'!$AW$2:$AW$29,'1 · BBDD 2025 (insumo)'!$A$2:$A$29,$A9) -> 0 | H9: =G9/3*100 -> 0 | I9: =$E$53 -> 0 | J9: =$F$77 -> 0 | K9: =SUMIFS('1 · BBDD 2025 (insumo)'!$AY$2:$AY$29,'1 · BBDD 2025 (insumo)'!$A$2:$A$29,$A9) -> 0 | L9: =(I9/3+J9/4+IF($C$27=0,0,K9/$C$27))/3*100 -> 0 | M9: =IF(B9=0,$F$29,IF(B9<=3,$F$30,IF(B9<=6,$F$31,IF(B9<=9,$F$32,$F$33)))) -> 0 | N9: =(D9+F9+H9+L9+M9)/5 -> 0 | O9: =ROUND(N9,0) -> 0 | P9: ='2 · Cálculo 2025 · f. antigua'!O9 -> 0 | Q9: ='2 · Cálculo 2025 · f. antigua'!Q9 -> 0 | R9: ='2 · Cálculo 2025 · f. antigua'!R9 -> 0 | S9: =ROUND(R9,0) -> 0 | T9: =ROUND((O9+S9)/2,0) -> 0
A10: DO | B10: =COUNTIF('1 · BBDD 2025 (insumo)'!$A$2:$A$29,$A10) -> 1 | C10: ='2 · Cálculo 2025 · f. antigua'!C10 -> 1 | D10: =C10/5*100 -> 20 | E10: ='2 · Cálculo 2025 · f. antigua'!E10 -> 1 | F10: =E10/4*100 -> 25 | G10: =_xlfn.MAXIFS('1 · BBDD 2025 (insumo)'!$AW$2:$AW$29,'1 · BBDD 2025 (insumo)'!$A$2:$A$29,$A10) -> 2 | H10: =G10/3*100 -> 66.666667 | I10: =$E$54 -> 1 | J10: =$F$78 -> 2 | K10: =SUMIFS('1 · BBDD 2025 (insumo)'!$AY$2:$AY$29,'1 · BBDD 2025 (insumo)'!$A$2:$A$29,$A10) -> 1 | L10: =(I10/3+J10/4+IF($C$27=0,0,K10/$C$27))/3*100 -> 44.444444 | M10: =IF(B10=0,$F$29,IF(B10<=3,$F$30,IF(B10<=6,$F$31,IF(B10<=9,$F$32,$F$33)))) -> 25 | N10: =(D10+F10+H10+L10+M10)/5 -> 36.222222 | O10: =ROUND(N10,0) -> 36 | P10: ='2 · Cálculo 2025 · f. antigua'!O10 -> 16.666667 | Q10: ='2 · Cálculo 2025 · f. antigua'!Q10 -> 40 | R10: ='2 · Cálculo 2025 · f. antigua'!R10 -> 28.333333 | S10: =ROUND(R10,0) -> 28 | T10: =ROUND((O10+S10)/2,0) -> 32
A11: EC | B11: =COUNTIF('1 · BBDD 2025 (insumo)'!$A$2:$A$29,$A11) -> 1 | C11: ='2 · Cálculo 2025 · f. antigua'!C11 -> 1 | D11: =C11/5*100 -> 20 | E11: ='2 · Cálculo 2025 · f. antigua'!E11 -> 1 | F11: =E11/4*100 -> 25 | G11: =_xlfn.MAXIFS('1 · BBDD 2025 (insumo)'!$AW$2:$AW$29,'1 · BBDD 2025 (insumo)'!$A$2:$A$29,$A11) -> 2 | H11: =G11/3*100 -> 66.666667 | I11: =$E$55 -> 1 | J11: =$F$79 -> 1 | K11: =SUMIFS('1 · BBDD 2025 (insumo)'!$AY$2:$AY$29,'1 · BBDD 2025 (insumo)'!$A$2:$A$29,$A11) -> 1 | L11: =(I11/3+J11/4+IF($C$27=0,0,K11/$C$27))/3*100 -> 36.111111 | M11: =IF(B11=0,$F$29,IF(B11<=3,$F$30,IF(B11<=6,$F$31,IF(B11<=9,$F$32,$F$33)))) -> 25 | N11: =(D11+F11+H11+L11+M11)/5 -> 34.555556 | O11: =ROUND(N11,0) -> 35 | P11: ='2 · Cálculo 2025 · f. antigua'!O11 -> 16.666667 | Q11: ='2 · Cálculo 2025 · f. antigua'!Q11 -> 20 | R11: ='2 · Cálculo 2025 · f. antigua'!R11 -> 18.333333 | S11: =ROUND(R11,0) -> 18 | T11: =ROUND((O11+S11)/2,0) -> 27
A12: GT | B12: =COUNTIF('1 · BBDD 2025 (insumo)'!$A$2:$A$29,$A12) -> 1 | C12: ='2 · Cálculo 2025 · f. antigua'!C12 -> 1 | D12: =C12/5*100 -> 20 | E12: ='2 · Cálculo 2025 · f. antigua'!E12 -> 1 | F12: =E12/4*100 -> 25 | G12: =_xlfn.MAXIFS('1 · BBDD 2025 (insumo)'!$AW$2:$AW$29,'1 · BBDD 2025 (insumo)'!$A$2:$A$29,$A12) -> 2 | H12: =G12/3*100 -> 66.666667 | I12: =$E$56 -> 0 | J12: =$F$80 -> 2 | K12: =SUMIFS('1 · BBDD 2025 (insumo)'!$AY$2:$AY$29,'1 · BBDD 2025 (insumo)'!$A$2:$A$29,$A12) -> 1 | L12: =(I12/3+J12/4+IF($C$27=0,0,K12/$C$27))/3*100 -> 33.333333 | M12: =IF(B12=0,$F$29,IF(B12<=3,$F$30,IF(B12<=6,$F$31,IF(B12<=9,$F$32,$F$33)))) -> 25 | N12: =(D12+F12+H12+L12+M12)/5 -> 34 | O12: =ROUND(N12,0) -> 34 | P12: ='2 · Cálculo 2025 · f. antigua'!O12 -> 25 | Q12: ='2 · Cálculo 2025 · f. antigua'!Q12 -> 40 | R12: ='2 · Cálculo 2025 · f. antigua'!R12 -> 32.5 | S12: =ROUND(R12,0) -> 33 | T12: =ROUND((O12+S12)/2,0) -> 34
A13: HN | B13: =COUNTIF('1 · BBDD 2025 (insumo)'!$A$2:$A$29,$A13) -> 1 | C13: ='2 · Cálculo 2025 · f. antigua'!C13 -> 1 | D13: =C13/5*100 -> 20 | E13: ='2 · Cálculo 2025 · f. antigua'!E13 -> 1 | F13: =E13/4*100 -> 25 | G13: =_xlfn.MAXIFS('1 · BBDD 2025 (insumo)'!$AW$2:$AW$29,'1 · BBDD 2025 (insumo)'!$A$2:$A$29,$A13) -> 2 | H13: =G13/3*100 -> 66.666667 | I13: =$E$57 -> 0 | J13: =$F$81 -> 2 | K13: =SUMIFS('1 · BBDD 2025 (insumo)'!$AY$2:$AY$29,'1 · BBDD 2025 (insumo)'!$A$2:$A$29,$A13) -> 1 | L13: =(I13/3+J13/4+IF($C$27=0,0,K13/$C$27))/3*100 -> 33.333333 | M13: =IF(B13=0,$F$29,IF(B13<=3,$F$30,IF(B13<=6,$F$31,IF(B13<=9,$F$32,$F$33)))) -> 25 | N13: =(D13+F13+H13+L13+M13)/5 -> 34 | O13: =ROUND(N13,0) -> 34 | P13: ='2 · Cálculo 2025 · f. antigua'!O13 -> 83.333333 | Q13: ='2 · Cálculo 2025 · f. antigua'!Q13 -> 20 | R13: ='2 · Cálculo 2025 · f. antigua'!R13 -> 51.666667 | S13: =ROUND(R13,0) -> 52 | T13: =ROUND((O13+S13)/2,0) -> 43
A14: JM | B14: =COUNTIF('1 · BBDD 2025 (insumo)'!$A$2:$A$29,$A14) -> 0 | C14: ='2 · Cálculo 2025 · f. antigua'!C14 -> 0 | D14: =C14/5*100 -> 0 | E14: ='2 · Cálculo 2025 · f. antigua'!E14 -> 0 | F14: =E14/4*100 -> 0 | G14: =_xlfn.MAXIFS('1 · BBDD 2025 (insumo)'!$AW$2:$AW$29,'1 · BBDD 2025 (insumo)'!$A$2:$A$29,$A14) -> 0 | H14: =G14/3*100 -> 0 | I14: =$E$58 -> 0 | J14: =$F$82 -> 0 | K14: =SUMIFS('1 · BBDD 2025 (insumo)'!$AY$2:$AY$29,'1 · BBDD 2025 (insumo)'!$A$2:$A$29,$A14) -> 0 | L14: =(I14/3+J14/4+IF($C$27=0,0,K14/$C$27))/3*100 -> 0 | M14: =IF(B14=0,$F$29,IF(B14<=3,$F$30,IF(B14<=6,$F$31,IF(B14<=9,$F$32,$F$33)))) -> 0 | N14: =(D14+F14+H14+L14+M14)/5 -> 0 | O14: =ROUND(N14,0) -> 0 | P14: ='2 · Cálculo 2025 · f. antigua'!O14 -> 0 | Q14: ='2 · Cálculo 2025 · f. antigua'!Q14 -> 0 | R14: ='2 · Cálculo 2025 · f. antigua'!R14 -> 0 | S14: =ROUND(R14,0) -> 0 | T14: =ROUND((O14+S14)/2,0) -> 0
A15: MX | B15: =COUNTIF('1 · BBDD 2025 (insumo)'!$A$2:$A$29,$A15) -> 2 | C15: ='2 · Cálculo 2025 · f. antigua'!C15 -> 2 | D15: =C15/5*100 -> 40 | E15: ='2 · Cálculo 2025 · f. antigua'!E15 -> 1 | F15: =E15/4*100 -> 25 | G15: =_xlfn.MAXIFS('1 · BBDD 2025 (insumo)'!$AW$2:$AW$29,'1 · BBDD 2025 (insumo)'!$A$2:$A$29,$A15) -> 2 | H15: =G15/3*100 -> 66.666667 | I15: =$E$59 -> 1 | J15: =$F$83 -> 1 | K15: =SUMIFS('1 · BBDD 2025 (insumo)'!$AY$2:$AY$29,'1 · BBDD 2025 (insumo)'!$A$2:$A$29,$A15) -> 0 | L15: =(I15/3+J15/4+IF($C$27=0,0,K15/$C$27))/3*100 -> 19.444444 | M15: =IF(B15=0,$F$29,IF(B15<=3,$F$30,IF(B15<=6,$F$31,IF(B15<=9,$F$32,$F$33)))) -> 25 | N15: =(D15+F15+H15+L15+M15)/5 -> 35.222222 | O15: =ROUND(N15,0) -> 35 | P15: ='2 · Cálculo 2025 · f. antigua'!O15 -> 33.333333 | Q15: ='2 · Cálculo 2025 · f. antigua'!Q15 -> 40 | R15: ='2 · Cálculo 2025 · f. antigua'!R15 -> 36.666667 | S15: =ROUND(R15,0) -> 37 | T15: =ROUND((O15+S15)/2,0) -> 36
A16: PA | B16: =COUNTIF('1 · BBDD 2025 (insumo)'!$A$2:$A$29,$A16) -> 0 | C16: ='2 · Cálculo 2025 · f. antigua'!C16 -> 0 | D16: =C16/5*100 -> 0 | E16: ='2 · Cálculo 2025 · f. antigua'!E16 -> 0 | F16: =E16/4*100 -> 0 | G16: =_xlfn.MAXIFS('1 · BBDD 2025 (insumo)'!$AW$2:$AW$29,'1 · BBDD 2025 (insumo)'!$A$2:$A$29,$A16) -> 0 | H16: =G16/3*100 -> 0 | I16: =$E$60 -> 0 | J16: =$F$84 -> 0 | K16: =SUMIFS('1 · BBDD 2025 (insumo)'!$AY$2:$AY$29,'1 · BBDD 2025 (insumo)'!$A$2:$A$29,$A16) -> 0 | L16: =(I16/3+J16/4+IF($C$27=0,0,K16/$C$27))/3*100 -> 0 | M16: =IF(B16=0,$F$29,IF(B16<=3,$F$30,IF(B16<=6,$F$31,IF(B16<=9,$F$32,$F$33)))) -> 0 | N16: =(D16+F16+H16+L16+M16)/5 -> 0 | O16: =ROUND(N16,0) -> 0 | P16: ='2 · Cálculo 2025 · f. antigua'!O16 -> 0 | Q16: ='2 · Cálculo 2025 · f. antigua'!Q16 -> 0 | R16: ='2 · Cálculo 2025 · f. antigua'!R16 -> 0 | S16: =ROUND(R16,0) -> 0 | T16: =ROUND((O16+S16)/2,0) -> 0
A17: PE | B17: =COUNTIF('1 · BBDD 2025 (insumo)'!$A$2:$A$29,$A17) -> 2 | C17: ='2 · Cálculo 2025 · f. antigua'!C17 -> 2 | D17: =C17/5*100 -> 40 | E17: ='2 · Cálculo 2025 · f. antigua'!E17 -> 2 | F17: =E17/4*100 -> 50 | G17: =_xlfn.MAXIFS('1 · BBDD 2025 (insumo)'!$AW$2:$AW$29,'1 · BBDD 2025 (insumo)'!$A$2:$A$29,$A17) -> 2 | H17: =G17/3*100 -> 66.666667 | I17: =$E$61 -> 2 | J17: =$F$85 -> 0 | K17: =SUMIFS('1 · BBDD 2025 (insumo)'!$AY$2:$AY$29,'1 · BBDD 2025 (insumo)'!$A$2:$A$29,$A17) -> 0 | L17: =(I17/3+J17/4+IF($C$27=0,0,K17/$C$27))/3*100 -> 22.222222 | M17: =IF(B17=0,$F$29,IF(B17<=3,$F$30,IF(B17<=6,$F$31,IF(B17<=9,$F$32,$F$33)))) -> 25 | N17: =(D17+F17+H17+L17+M17)/5 -> 40.777778 | O17: =ROUND(N17,0) -> 41 | P17: ='2 · Cálculo 2025 · f. antigua'!O17 -> 41.666667 | Q17: ='2 · Cálculo 2025 · f. antigua'!Q17 -> 60 | R17: ='2 · Cálculo 2025 · f. antigua'!R17 -> 50.833333 | S17: =ROUND(R17,0) -> 51 | T17: =ROUND((O17+S17)/2,0) -> 46
A18: PY | B18: =COUNTIF('1 · BBDD 2025 (insumo)'!$A$2:$A$29,$A18) -> 0 | C18: ='2 · Cálculo 2025 · f. antigua'!C18 -> 0 | D18: =C18/5*100 -> 0 | E18: ='2 · Cálculo 2025 · f. antigua'!E18 -> 0 | F18: =E18/4*100 -> 0 | G18: =_xlfn.MAXIFS('1 · BBDD 2025 (insumo)'!$AW$2:$AW$29,'1 · BBDD 2025 (insumo)'!$A$2:$A$29,$A18) -> 0 | H18: =G18/3*100 -> 0 | I18: =$E$62 -> 0 | J18: =$F$86 -> 0 | K18: =SUMIFS('1 · BBDD 2025 (insumo)'!$AY$2:$AY$29,'1 · BBDD 2025 (insumo)'!$A$2:$A$29,$A18) -> 0 | L18: =(I18/3+J18/4+IF($C$27=0,0,K18/$C$27))/3*100 -> 0 | M18: =IF(B18=0,$F$29,IF(B18<=3,$F$30,IF(B18<=6,$F$31,IF(B18<=9,$F$32,$F$33)))) -> 0 | N18: =(D18+F18+H18+L18+M18)/5 -> 0 | O18: =ROUND(N18,0) -> 0 | P18: ='2 · Cálculo 2025 · f. antigua'!O18 -> 0 | Q18: ='2 · Cálculo 2025 · f. antigua'!Q18 -> 0 | R18: ='2 · Cálculo 2025 · f. antigua'!R18 -> 0 | S18: =ROUND(R18,0) -> 0 | T18: =ROUND((O18+S18)/2,0) -> 0
A19: SV | B19: =COUNTIF('1 · BBDD 2025 (insumo)'!$A$2:$A$29,$A19) -> 0 | C19: ='2 · Cálculo 2025 · f. antigua'!C19 -> 0 | D19: =C19/5*100 -> 0 | E19: ='2 · Cálculo 2025 · f. antigua'!E19 -> 0 | F19: =E19/4*100 -> 0 | G19: =_xlfn.MAXIFS('1 · BBDD 2025 (insumo)'!$AW$2:$AW$29,'1 · BBDD 2025 (insumo)'!$A$2:$A$29,$A19) -> 0 | H19: =G19/3*100 -> 0 | I19: =$E$63 -> 0 | J19: =$F$87 -> 0 | K19: =SUMIFS('1 · BBDD 2025 (insumo)'!$AY$2:$AY$29,'1 · BBDD 2025 (insumo)'!$A$2:$A$29,$A19) -> 0 | L19: =(I19/3+J19/4+IF($C$27=0,0,K19/$C$27))/3*100 -> 0 | M19: =IF(B19=0,$F$29,IF(B19<=3,$F$30,IF(B19<=6,$F$31,IF(B19<=9,$F$32,$F$33)))) -> 0 | N19: =(D19+F19+H19+L19+M19)/5 -> 0 | O19: =ROUND(N19,0) -> 0 | P19: ='2 · Cálculo 2025 · f. antigua'!O19 -> 0 | Q19: ='2 · Cálculo 2025 · f. antigua'!Q19 -> 0 | R19: ='2 · Cálculo 2025 · f. antigua'!R19 -> 0 | S19: =ROUND(R19,0) -> 0 | T19: =ROUND((O19+S19)/2,0) -> 0
A20: TT | B20: =COUNTIF('1 · BBDD 2025 (insumo)'!$A$2:$A$29,$A20) -> 0 | C20: ='2 · Cálculo 2025 · f. antigua'!C20 -> 0 | D20: =C20/5*100 -> 0 | E20: ='2 · Cálculo 2025 · f. antigua'!E20 -> 0 | F20: =E20/4*100 -> 0 | G20: =_xlfn.MAXIFS('1 · BBDD 2025 (insumo)'!$AW$2:$AW$29,'1 · BBDD 2025 (insumo)'!$A$2:$A$29,$A20) -> 0 | H20: =G20/3*100 -> 0 | I20: =$E$64 -> 0 | J20: =$F$88 -> 0 | K20: =SUMIFS('1 · BBDD 2025 (insumo)'!$AY$2:$AY$29,'1 · BBDD 2025 (insumo)'!$A$2:$A$29,$A20) -> 0 | L20: =(I20/3+J20/4+IF($C$27=0,0,K20/$C$27))/3*100 -> 0 | M20: =IF(B20=0,$F$29,IF(B20<=3,$F$30,IF(B20<=6,$F$31,IF(B20<=9,$F$32,$F$33)))) -> 0 | N20: =(D20+F20+H20+L20+M20)/5 -> 0 | O20: =ROUND(N20,0) -> 0 | P20: ='2 · Cálculo 2025 · f. antigua'!O20 -> 0 | Q20: ='2 · Cálculo 2025 · f. antigua'!Q20 -> 0 | R20: ='2 · Cálculo 2025 · f. antigua'!R20 -> 0 | S20: =ROUND(R20,0) -> 0 | T20: =ROUND((O20+S20)/2,0) -> 0
A21: UY | B21: =COUNTIF('1 · BBDD 2025 (insumo)'!$A$2:$A$29,$A21) -> 0 | C21: ='2 · Cálculo 2025 · f. antigua'!C21 -> 0 | D21: =C21/5*100 -> 0 | E21: ='2 · Cálculo 2025 · f. antigua'!E21 -> 0 | F21: =E21/4*100 -> 0 | G21: =_xlfn.MAXIFS('1 · BBDD 2025 (insumo)'!$AW$2:$AW$29,'1 · BBDD 2025 (insumo)'!$A$2:$A$29,$A21) -> 0 | H21: =G21/3*100 -> 0 | I21: =$E$65 -> 0 | J21: =$F$89 -> 0 | K21: =SUMIFS('1 · BBDD 2025 (insumo)'!$AY$2:$AY$29,'1 · BBDD 2025 (insumo)'!$A$2:$A$29,$A21) -> 0 | L21: =(I21/3+J21/4+IF($C$27=0,0,K21/$C$27))/3*100 -> 0 | M21: =IF(B21=0,$F$29,IF(B21<=3,$F$30,IF(B21<=6,$F$31,IF(B21<=9,$F$32,$F$33)))) -> 0 | N21: =(D21+F21+H21+L21+M21)/5 -> 0 | O21: =ROUND(N21,0) -> 0 | P21: ='2 · Cálculo 2025 · f. antigua'!O21 -> 0 | Q21: ='2 · Cálculo 2025 · f. antigua'!Q21 -> 0 | R21: ='2 · Cálculo 2025 · f. antigua'!R21 -> 0 | S21: =ROUND(R21,0) -> 0 | T21: =ROUND((O21+S21)/2,0) -> 0
A22: VE | B22: =COUNTIF('1 · BBDD 2025 (insumo)'!$A$2:$A$29,$A22) -> 0 | C22: ='2 · Cálculo 2025 · f. antigua'!C22 -> 0 | D22: =C22/5*100 -> 0 | E22: ='2 · Cálculo 2025 · f. antigua'!E22 -> 0 | F22: =E22/4*100 -> 0 | G22: =_xlfn.MAXIFS('1 · BBDD 2025 (insumo)'!$AW$2:$AW$29,'1 · BBDD 2025 (insumo)'!$A$2:$A$29,$A22) -> 0 | H22: =G22/3*100 -> 0 | I22: =$E$66 -> 0 | J22: =$F$90 -> 0 | K22: =SUMIFS('1 · BBDD 2025 (insumo)'!$AY$2:$AY$29,'1 · BBDD 2025 (insumo)'!$A$2:$A$29,$A22) -> 0 | L22: =(I22/3+J22/4+IF($C$27=0,0,K22/$C$27))/3*100 -> 0 | M22: =IF(B22=0,$F$29,IF(B22<=3,$F$30,IF(B22<=6,$F$31,IF(B22<=9,$F$32,$F$33)))) -> 0 | N22: =(D22+F22+H22+L22+M22)/5 -> 0 | O22: =ROUND(N22,0) -> 0 | P22: ='2 · Cálculo 2025 · f. antigua'!O22 -> 0 | Q22: ='2 · Cálculo 2025 · f. antigua'!Q22 -> 0 | R22: ='2 · Cálculo 2025 · f. antigua'!R22 -> 0 | S22: =ROUND(R22,0) -> 0 | T22: =ROUND((O22+S22)/2,0) -> 0
A24: PARÁMETROS (azul sobre amarillo = entrada; el máximo es fórmula)
A25: Año de referencia del ciclo | C25: 2026
A26: Caducidad de anuncio (años) | C26: 2
A27: Máx. combinaciones del ciclo 2025 | C27: =MAX(K3:K22) -> 2
A28: Umbrales de Cantidad (nº iniciativas → puntaje)
E29: 0 | F29: 0
E30: 1-3 | F30: 25
E31: 4-6 | F31: 50
E32: 7-9 | F32: 75
E33: 10 o más | F33: 100
A35: Sub2 es idéntico en ambas fórmulas (la metodología 2026 no lo modificó): las columnas P/Q/R referencian la pestaña 2.
A36: V1/V2 (tipos y etapas) usan las MISMAS grillas de la pestaña 2: la definición de esas dos variables no cambió; lo nuevo es Continuidad por nivel máximo, Convocante (3 subcomponentes con co-convocatoria) y Cantidad.
A45: GRILLA — Convocante gubernamental (recodificación 2026) (20×3)
A46: País | B46: CONV: gobierno local | C46: CONV: gobierno nacional | D46: CONV: otra institución pública | E46: SUMA
A47: AR | B47: =IF(COUNTIFS('1 · BBDD 2025 (insumo)'!$A$2:$A$29,$A47,'1 · BBDD 2025 (insumo)'!$AP$2:$AP$29,1)>0,1,0) -> 0 | C47: =IF(COUNTIFS('1 · BBDD 2025 (insumo)'!$A$2:$A$29,$A47,'1 · BBDD 2025 (insumo)'!$AQ$2:$AQ$29,1)>0,1,0) -> 0 | D47: =IF(COUNTIFS('1 · BBDD 2025 (insumo)'!$A$2:$A$29,$A47,'1 · BBDD 2025 (insumo)'!$AR$2:$AR$29,1)>0,1,0) -> 0 | E47: =SUM(B47:D47) -> 0
A48: BO | B48: =IF(COUNTIFS('1 · BBDD 2025 (insumo)'!$A$2:$A$29,$A48,'1 · BBDD 2025 (insumo)'!$AP$2:$AP$29,1)>0,1,0) -> 0 | C48: =IF(COUNTIFS('1 · BBDD 2025 (insumo)'!$A$2:$A$29,$A48,'1 · BBDD 2025 (insumo)'!$AQ$2:$AQ$29,1)>0,1,0) -> 1 | D48: =IF(COUNTIFS('1 · BBDD 2025 (insumo)'!$A$2:$A$29,$A48,'1 · BBDD 2025 (insumo)'!$AR$2:$AR$29,1)>0,1,0) -> 0 | E48: =SUM(B48:D48) -> 1
A49: BR | B49: =IF(COUNTIFS('1 · BBDD 2025 (insumo)'!$A$2:$A$29,$A49,'1 · BBDD 2025 (insumo)'!$AP$2:$AP$29,1)>0,1,0) -> 1 | C49: =IF(COUNTIFS('1 · BBDD 2025 (insumo)'!$A$2:$A$29,$A49,'1 · BBDD 2025 (insumo)'!$AQ$2:$AQ$29,1)>0,1,0) -> 1 | D49: =IF(COUNTIFS('1 · BBDD 2025 (insumo)'!$A$2:$A$29,$A49,'1 · BBDD 2025 (insumo)'!$AR$2:$AR$29,1)>0,1,0) -> 0 | E49: =SUM(B49:D49) -> 2
A50: CL | B50: =IF(COUNTIFS('1 · BBDD 2025 (insumo)'!$A$2:$A$29,$A50,'1 · BBDD 2025 (insumo)'!$AP$2:$AP$29,1)>0,1,0) -> 0 | C50: =IF(COUNTIFS('1 · BBDD 2025 (insumo)'!$A$2:$A$29,$A50,'1 · BBDD 2025 (insumo)'!$AQ$2:$AQ$29,1)>0,1,0) -> 1 | D50: =IF(COUNTIFS('1 · BBDD 2025 (insumo)'!$A$2:$A$29,$A50,'1 · BBDD 2025 (insumo)'!$AR$2:$AR$29,1)>0,1,0) -> 1 | E50: =SUM(B50:D50) -> 2
A51: CO | B51: =IF(COUNTIFS('1 · BBDD 2025 (insumo)'!$A$2:$A$29,$A51,'1 · BBDD 2025 (insumo)'!$AP$2:$AP$29,1)>0,1,0) -> 1 | C51: =IF(COUNTIFS('1 · BBDD 2025 (insumo)'!$A$2:$A$29,$A51,'1 · BBDD 2025 (insumo)'!$AQ$2:$AQ$29,1)>0,1,0) -> 1 | D51: =IF(COUNTIFS('1 · BBDD 2025 (insumo)'!$A$2:$A$29,$A51,'1 · BBDD 2025 (insumo)'!$AR$2:$AR$29,1)>0,1,0) -> 0 | E51: =SUM(B51:D51) -> 2
A52: CR | B52: =IF(COUNTIFS('1 · BBDD 2025 (insumo)'!$A$2:$A$29,$A52,'1 · BBDD 2025 (insumo)'!$AP$2:$AP$29,1)>0,1,0) -> 0 | C52: =IF(COUNTIFS('1 · BBDD 2025 (insumo)'!$A$2:$A$29,$A52,'1 · BBDD 2025 (insumo)'!$AQ$2:$AQ$29,1)>0,1,0) -> 0 | D52: =IF(COUNTIFS('1 · BBDD 2025 (insumo)'!$A$2:$A$29,$A52,'1 · BBDD 2025 (insumo)'!$AR$2:$AR$29,1)>0,1,0) -> 1 | E52: =SUM(B52:D52) -> 1
A53: CU | B53: =IF(COUNTIFS('1 · BBDD 2025 (insumo)'!$A$2:$A$29,$A53,'1 · BBDD 2025 (insumo)'!$AP$2:$AP$29,1)>0,1,0) -> 0 | C53: =IF(COUNTIFS('1 · BBDD 2025 (insumo)'!$A$2:$A$29,$A53,'1 · BBDD 2025 (insumo)'!$AQ$2:$AQ$29,1)>0,1,0) -> 0 | D53: =IF(COUNTIFS('1 · BBDD 2025 (insumo)'!$A$2:$A$29,$A53,'1 · BBDD 2025 (insumo)'!$AR$2:$AR$29,1)>0,1,0) -> 0 | E53: =SUM(B53:D53) -> 0
A54: DO | B54: =IF(COUNTIFS('1 · BBDD 2025 (insumo)'!$A$2:$A$29,$A54,'1 · BBDD 2025 (insumo)'!$AP$2:$AP$29,1)>0,1,0) -> 0 | C54: =IF(COUNTIFS('1 · BBDD 2025 (insumo)'!$A$2:$A$29,$A54,'1 · BBDD 2025 (insumo)'!$AQ$2:$AQ$29,1)>0,1,0) -> 1 | D54: =IF(COUNTIFS('1 · BBDD 2025 (insumo)'!$A$2:$A$29,$A54,'1 · BBDD 2025 (insumo)'!$AR$2:$AR$29,1)>0,1,0) -> 0 | E54: =SUM(B54:D54) -> 1
A55: EC | B55: =IF(COUNTIFS('1 · BBDD 2025 (insumo)'!$A$2:$A$29,$A55,'1 · BBDD 2025 (insumo)'!$AP$2:$AP$29,1)>0,1,0) -> 0 | C55: =IF(COUNTIFS('1 · BBDD 2025 (insumo)'!$A$2:$A$29,$A55,'1 · BBDD 2025 (insumo)'!$AQ$2:$AQ$29,1)>0,1,0) -> 1 | D55: =IF(COUNTIFS('1 · BBDD 2025 (insumo)'!$A$2:$A$29,$A55,'1 · BBDD 2025 (insumo)'!$AR$2:$AR$29,1)>0,1,0) -> 0 | E55: =SUM(B55:D55) -> 1
A56: GT | B56: =IF(COUNTIFS('1 · BBDD 2025 (insumo)'!$A$2:$A$29,$A56,'1 · BBDD 2025 (insumo)'!$AP$2:$AP$29,1)>0,1,0) -> 0 | C56: =IF(COUNTIFS('1 · BBDD 2025 (insumo)'!$A$2:$A$29,$A56,'1 · BBDD 2025 (insumo)'!$AQ$2:$AQ$29,1)>0,1,0) -> 0 | D56: =IF(COUNTIFS('1 · BBDD 2025 (insumo)'!$A$2:$A$29,$A56,'1 · BBDD 2025 (insumo)'!$AR$2:$AR$29,1)>0,1,0) -> 0 | E56: =SUM(B56:D56) -> 0
A57: HN | B57: =IF(COUNTIFS('1 · BBDD 2025 (insumo)'!$A$2:$A$29,$A57,'1 · BBDD 2025 (insumo)'!$AP$2:$AP$29,1)>0,1,0) -> 0 | C57: =IF(COUNTIFS('1 · BBDD 2025 (insumo)'!$A$2:$A$29,$A57,'1 · BBDD 2025 (insumo)'!$AQ$2:$AQ$29,1)>0,1,0) -> 0 | D57: =IF(COUNTIFS('1 · BBDD 2025 (insumo)'!$A$2:$A$29,$A57,'1 · BBDD 2025 (insumo)'!$AR$2:$AR$29,1)>0,1,0) -> 0 | E57: =SUM(B57:D57) -> 0
A58: JM | B58: =IF(COUNTIFS('1 · BBDD 2025 (insumo)'!$A$2:$A$29,$A58,'1 · BBDD 2025 (insumo)'!$AP$2:$AP$29,1)>0,1,0) -> 0 | C58: =IF(COUNTIFS('1 · BBDD 2025 (insumo)'!$A$2:$A$29,$A58,'1 · BBDD 2025 (insumo)'!$AQ$2:$AQ$29,1)>0,1,0) -> 0 | D58: =IF(COUNTIFS('1 · BBDD 2025 (insumo)'!$A$2:$A$29,$A58,'1 · BBDD 2025 (insumo)'!$AR$2:$AR$29,1)>0,1,0) -> 0 | E58: =SUM(B58:D58) -> 0
... A66: VE | B66: =IF(COUNTIFS('1 · BBDD 2025 (insumo)'!$A$2:$A$29,$A66,'1 · BBDD 2025 (insumo)'!$AP$2:$AP$29,1)>0,1,0) -> 0 | C66: =IF(COUNTIFS('1 · BBDD 2025 (insumo)'!$A$2:$A$29,$A66,'1 · BBDD 2025 (insumo)'!$AQ$2:$AQ$29,1)>0,1,0) -> 0 | D66: =IF(COUNTIFS('1 · BBDD 2025 (insumo)'!$A$2:$A$29,$A66,'1 · BBDD 2025 (insumo)'!$AR$2:$AR$29,1)>0,1,0) -> 0 | E66: =SUM(B66:D66) -> 0
A69: GRILLA — Convocante no gubernamental (recodificación 2026) (20×4)
A70: País | B70: CONV: empresa | C70: CONV: universidad | D70: CONV: sociedad civil | E70: CONV: organización internacional | F70: SUMA
A71: AR | B71: =IF(COUNTIFS('1 · BBDD 2025 (insumo)'!$A$2:$A$29,$A71,'1 · BBDD 2025 (insumo)'!$AS$2:$AS$29,1)>0,1,0) -> 0 | C71: =IF(COUNTIFS('1 · BBDD 2025 (insumo)'!$A$2:$A$29,$A71,'1 · BBDD 2025 (insumo)'!$AT$2:$AT$29,1)>0,1,0) -> 0 | D71: =IF(COUNTIFS('1 · BBDD 2025 (insumo)'!$A$2:$A$29,$A71,'1 · BBDD 2025 (insumo)'!$AU$2:$AU$29,1)>0,1,0) -> 0 | E71: =IF(COUNTIFS('1 · BBDD 2025 (insumo)'!$A$2:$A$29,$A71,'1 · BBDD 2025 (insumo)'!$AV$2:$AV$29,1)>0,1,0) -> 0 | F71: =SUM(B71:E71) -> 0
A72: BO | B72: =IF(COUNTIFS('1 · BBDD 2025 (insumo)'!$A$2:$A$29,$A72,'1 · BBDD 2025 (insumo)'!$AS$2:$AS$29,1)>0,1,0) -> 0 | C72: =IF(COUNTIFS('1 · BBDD 2025 (insumo)'!$A$2:$A$29,$A72,'1 · BBDD 2025 (insumo)'!$AT$2:$AT$29,1)>0,1,0) -> 0 | D72: =IF(COUNTIFS('1 · BBDD 2025 (insumo)'!$A$2:$A$29,$A72,'1 · BBDD 2025 (insumo)'!$AU$2:$AU$29,1)>0,1,0) -> 0 | E72: =IF(COUNTIFS('1 · BBDD 2025 (insumo)'!$A$2:$A$29,$A72,'1 · BBDD 2025 (insumo)'!$AV$2:$AV$29,1)>0,1,0) -> 1 | F72: =SUM(B72:E72) -> 1
A73: BR | B73: =IF(COUNTIFS('1 · BBDD 2025 (insumo)'!$A$2:$A$29,$A73,'1 · BBDD 2025 (insumo)'!$AS$2:$AS$29,1)>0,1,0) -> 1 | C73: =IF(COUNTIFS('1 · BBDD 2025 (insumo)'!$A$2:$A$29,$A73,'1 · BBDD 2025 (insumo)'!$AT$2:$AT$29,1)>0,1,0) -> 1 | D73: =IF(COUNTIFS('1 · BBDD 2025 (insumo)'!$A$2:$A$29,$A73,'1 · BBDD 2025 (insumo)'!$AU$2:$AU$29,1)>0,1,0) -> 0 | E73: =IF(COUNTIFS('1 · BBDD 2025 (insumo)'!$A$2:$A$29,$A73,'1 · BBDD 2025 (insumo)'!$AV$2:$AV$29,1)>0,1,0) -> 0 | F73: =SUM(B73:E73) -> 2
A74: CL | B74: =IF(COUNTIFS('1 · BBDD 2025 (insumo)'!$A$2:$A$29,$A74,'1 · BBDD 2025 (insumo)'!$AS$2:$AS$29,1)>0,1,0) -> 1 | C74: =IF(COUNTIFS('1 · BBDD 2025 (insumo)'!$A$2:$A$29,$A74,'1 · BBDD 2025 (insumo)'!$AT$2:$AT$29,1)>0,1,0) -> 1 | D74: =IF(COUNTIFS('1 · BBDD 2025 (insumo)'!$A$2:$A$29,$A74,'1 · BBDD 2025 (insumo)'!$AU$2:$AU$29,1)>0,1,0) -> 1 | E74: =IF(COUNTIFS('1 · BBDD 2025 (insumo)'!$A$2:$A$29,$A74,'1 · BBDD 2025 (insumo)'!$AV$2:$AV$29,1)>0,1,0) -> 0 | F74: =SUM(B74:E74) -> 3
A75: CO | B75: =IF(COUNTIFS('1 · BBDD 2025 (insumo)'!$A$2:$A$29,$A75,'1 · BBDD 2025 (insumo)'!$AS$2:$AS$29,1)>0,1,0) -> 1 | C75: =IF(COUNTIFS('1 · BBDD 2025 (insumo)'!$A$2:$A$29,$A75,'1 · BBDD 2025 (insumo)'!$AT$2:$AT$29,1)>0,1,0) -> 1 | D75: =IF(COUNTIFS('1 · BBDD 2025 (insumo)'!$A$2:$A$29,$A75,'1 · BBDD 2025 (insumo)'!$AU$2:$AU$29,1)>0,1,0) -> 1 | E75: =IF(COUNTIFS('1 · BBDD 2025 (insumo)'!$A$2:$A$29,$A75,'1 · BBDD 2025 (insumo)'!$AV$2:$AV$29,1)>0,1,0) -> 1 | F75: =SUM(B75:E75) -> 4
A76: CR | B76: =IF(COUNTIFS('1 · BBDD 2025 (insumo)'!$A$2:$A$29,$A76,'1 · BBDD 2025 (insumo)'!$AS$2:$AS$29,1)>0,1,0) -> 0 | C76: =IF(COUNTIFS('1 · BBDD 2025 (insumo)'!$A$2:$A$29,$A76,'1 · BBDD 2025 (insumo)'!$AT$2:$AT$29,1)>0,1,0) -> 0 | D76: =IF(COUNTIFS('1 · BBDD 2025 (insumo)'!$A$2:$A$29,$A76,'1 · BBDD 2025 (insumo)'!$AU$2:$AU$29,1)>0,1,0) -> 0 | E76: =IF(COUNTIFS('1 · BBDD 2025 (insumo)'!$A$2:$A$29,$A76,'1 · BBDD 2025 (insumo)'!$AV$2:$AV$29,1)>0,1,0) -> 1 | F76: =SUM(B76:E76) -> 1
A77: CU | B77: =IF(COUNTIFS('1 · BBDD 2025 (insumo)'!$A$2:$A$29,$A77,'1 · BBDD 2025 (insumo)'!$AS$2:$AS$29,1)>0,1,0) -> 0 | C77: =IF(COUNTIFS('1 · BBDD 2025 (insumo)'!$A$2:$A$29,$A77,'1 · BBDD 2025 (insumo)'!$AT$2:$AT$29,1)>0,1,0) -> 0 | D77: =IF(COUNTIFS('1 · BBDD 2025 (insumo)'!$A$2:$A$29,$A77,'1 · BBDD 2025 (insumo)'!$AU$2:$AU$29,1)>0,1,0) -> 0 | E77: =IF(COUNTIFS('1 · BBDD 2025 (insumo)'!$A$2:$A$29,$A77,'1 · BBDD 2025 (insumo)'!$AV$2:$AV$29,1)>0,1,0) -> 0 | F77: =SUM(B77:E77) -> 0
A78: DO | B78: =IF(COUNTIFS('1 · BBDD 2025 (insumo)'!$A$2:$A$29,$A78,'1 · BBDD 2025 (insumo)'!$AS$2:$AS$29,1)>0,1,0) -> 1 | C78: =IF(COUNTIFS('1 · BBDD 2025 (insumo)'!$A$2:$A$29,$A78,'1 · BBDD 2025 (insumo)'!$AT$2:$AT$29,1)>0,1,0) -> 1 | D78: =IF(COUNTIFS('1 · BBDD 2025 (insumo)'!$A$2:$A$29,$A78,'1 · BBDD 2025 (insumo)'!$AU$2:$AU$29,1)>0,1,0) -> 0 | E78: =IF(COUNTIFS('1 · BBDD 2025 (insumo)'!$A$2:$A$29,$A78,'1 · BBDD 2025 (insumo)'!$AV$2:$AV$29,1)>0,1,0) -> 0 | F78: =SUM(B78:E78) -> 2
A79: EC | B79: =IF(COUNTIFS('1 · BBDD 2025 (insumo)'!$A$2:$A$29,$A79,'1 · BBDD 2025 (insumo)'!$AS$2:$AS$29,1)>0,1,0) -> 0 | C79: =IF(COUNTIFS('1 · BBDD 2025 (insumo)'!$A$2:$A$29,$A79,'1 · BBDD 2025 (insumo)'!$AT$2:$AT$29,1)>0,1,0) -> 0 | D79: =IF(COUNTIFS('1 · BBDD 2025 (insumo)'!$A$2:$A$29,$A79,'1 · BBDD 2025 (insumo)'!$AU$2:$AU$29,1)>0,1,0) -> 1 | E79: =IF(COUNTIFS('1 · BBDD 2025 (insumo)'!$A$2:$A$29,$A79,'1 · BBDD 2025 (insumo)'!$AV$2:$AV$29,1)>0,1,0) -> 0 | F79: =SUM(B79:E79) -> 1
A80: GT | B80: =IF(COUNTIFS('1 · BBDD 2025 (insumo)'!$A$2:$A$29,$A80,'1 · BBDD 2025 (insumo)'!$AS$2:$AS$29,1)>0,1,0) -> 0 | C80: =IF(COUNTIFS('1 · BBDD 2025 (insumo)'!$A$2:$A$29,$A80,'1 · BBDD 2025 (insumo)'!$AT$2:$AT$29,1)>0,1,0) -> 0 | D80: =IF(COUNTIFS('1 · BBDD 2025 (insumo)'!$A$2:$A$29,$A80,'1 · BBDD 2025 (insumo)'!$AU$2:$AU$29,1)>0,1,0) -> 1 | E80: =IF(COUNTIFS('1 · BBDD 2025 (insumo)'!$A$2:$A$29,$A80,'1 · BBDD 2025 (insumo)'!$AV$2:$AV$29,1)>0,1,0) -> 1 | F80: =SUM(B80:E80) -> 2
A81: HN | B81: =IF(COUNTIFS('1 · BBDD 2025 (insumo)'!$A$2:$A$29,$A81,'1 · BBDD 2025 (insumo)'!$AS$2:$AS$29,1)>0,1,0) -> 0 | C81: =IF(COUNTIFS('1 · BBDD 2025 (insumo)'!$A$2:$A$29,$A81,'1 · BBDD 2025 (insumo)'!$AT$2:$AT$29,1)>0,1,0) -> 1 | D81: =IF(COUNTIFS('1 · BBDD 2025 (insumo)'!$A$2:$A$29,$A81,'1 · BBDD 2025 (insumo)'!$AU$2:$AU$29,1)>0,1,0) -> 0 | E81: =IF(COUNTIFS('1 · BBDD 2025 (insumo)'!$A$2:$A$29,$A81,'1 · BBDD 2025 (insumo)'!$AV$2:$AV$29,1)>0,1,0) -> 1 | F81: =SUM(B81:E81) -> 2
A82: JM | B82: =IF(COUNTIFS('1 · BBDD 2025 (insumo)'!$A$2:$A$29,$A82,'1 · BBDD 2025 (insumo)'!$AS$2:$AS$29,1)>0,1,0) -> 0 | C82: =IF(COUNTIFS('1 · BBDD 2025 (insumo)'!$A$2:$A$29,$A82,'1 · BBDD 2025 (insumo)'!$AT$2:$AT$29,1)>0,1,0) -> 0 | D82: =IF(COUNTIFS('1 · BBDD 2025 (insumo)'!$A$2:$A$29,$A82,'1 · BBDD 2025 (insumo)'!$AU$2:$AU$29,1)>0,1,0) -> 0 | E82: =IF(COUNTIFS('1 · BBDD 2025 (insumo)'!$A$2:$A$29,$A82,'1 · BBDD 2025 (insumo)'!$AV$2:$AV$29,1)>0,1,0) -> 0 | F82: =SUM(B82:E82) -> 0
... A90: VE | B90: =IF(COUNTIFS('1 · BBDD 2025 (insumo)'!$A$2:$A$29,$A90,'1 · BBDD 2025 (insumo)'!$AS$2:$AS$29,1)>0,1,0) -> 0 | C90: =IF(COUNTIFS('1 · BBDD 2025 (insumo)'!$A$2:$A$29,$A90,'1 · BBDD 2025 (insumo)'!$AT$2:$AT$29,1)>0,1,0) -> 0 | D90: =IF(COUNTIFS('1 · BBDD 2025 (insumo)'!$A$2:$A$29,$A90,'1 · BBDD 2025 (insumo)'!$AU$2:$AU$29,1)>0,1,0) -> 0 | E90: =IF(COUNTIFS('1 · BBDD 2025 (insumo)'!$A$2:$A$29,$A90,'1 · BBDD 2025 (insumo)'!$AV$2:$AV$29,1)>0,1,0) -> 0 | F90: =SUM(B90:E90) -> 0

Sheet 4 · Comparación
A1: COMPARACIÓN — Indicador de IA en Participación Ciudadana
A2: 2025 con fórmula antigua y con fórmula nueva = fórmulas que referencian las pestañas 2 y 3 (auditables aquí). 2026 = valores del entregable BBDD_casos_incluidos_ILIA2026.xlsx · pestaña «2 · Índice por país» (pegados como dato el 2026-07-19; las fórmulas auditables están en ese archivo).
A3: Δ efecto fórmula = misma base 2025, fórmula nueva − antigua · Δ real = 2026 − 2025 (ambos con fórmula nueva) · Δ total = 2026 (f. nueva) − 2025 (f. antigua publicada)
A5: País | B5: Indicador 2025 · fórmula antigua | C5: Indicador 2025 · fórmula nueva | D5: Indicador 2026 | E5: Δ efecto fórmula (2025n−2025a) | F5: Δ real (2026−2025n) | G5: Δ total (2026−2025a) | H5: Sub1 2025 · f. antigua | I5: Sub1 2025 · f. nueva | J5: Sub1 2026 | K5: Sub2 2025 (ambas fórmulas) | L5: Sub2 2026 | M5: V1 Tipos 2025n | N5: V1 Tipos 2026 | O5: V2 Etapas 2025n | P5: V2 Etapas 2026 | Q5: V3 Continuidad 2025n | R5: V3 Continuidad 2026 | S5: V4 Convocante 2025n | T5: V4 Convocante 2026 | U5: V5 Cantidad 2025n | V5: V5 Cantidad 2026
A6: AR | B6: ='2 · Cálculo 2025 · f. antigua'!T3 -> 0 | C6: ='3 · Cálculo 2025 · f. nueva'!T3 -> 0 | D6: 0 | E6: =C6-B6 -> 0 | F6: =D6-C6 -> 0 | G6: =D6-B6 -> 0 | H6: ='2 · Cálculo 2025 · f. antigua'!L3 -> 0 | I6: ='3 · Cálculo 2025 · f. nueva'!O3 -> 0 | J6: 0 | K6: ='2 · Cálculo 2025 · f. antigua'!S3 -> 0 | L6: 0 | M6: ='3 · Cálculo 2025 · f. nueva'!D3 -> 0 | N6: 0 | O6: ='3 · Cálculo 2025 · f. nueva'!F3 -> 0 | P6: 0 | Q6: ='3 · Cálculo 2025 · f. nueva'!H3 -> 0 | R6: 0 | S6: ='3 · Cálculo 2025 · f. nueva'!L3 -> 0 | T6: 0 | U6: ='3 · Cálculo 2025 · f. nueva'!M3 -> 0 | V6: 0
A7: BO | B7: ='2 · Cálculo 2025 · f. antigua'!T4 -> 31 | C7: ='3 · Cálculo 2025 · f. nueva'!T4 -> 32 | D7: 27 | E7: =C7-B7 -> 1 | F7: =D7-C7 -> -5 | G7: =D7-B7 -> -4 | H7: ='2 · Cálculo 2025 · f. antigua'!L4 -> 38 | I7: ='3 · Cálculo 2025 · f. nueva'!O4 -> 40 | J7: 40 | K7: ='2 · Cálculo 2025 · f. antigua'!S4 -> 23 | L7: 13 | M7: ='3 · Cálculo 2025 · f. nueva'!D4 -> 20 | N7: 20 | O7: ='3 · Cálculo 2025 · f. nueva'!F4 -> 50 | P7: 50 | Q7: ='3 · Cálculo 2025 · f. nueva'!H4 -> 66.666667 | R7: 66.7 | S7: ='3 · Cálculo 2025 · f. nueva'!L4 -> 36.111111 | T7: 36.1 | U7: ='3 · Cálculo 2025 · f. nueva'!M4 -> 25 | V7: 25
A8: BR | B8: ='2 · Cálculo 2025 · f. antigua'!T5 -> 77 | C8: ='3 · Cálculo 2025 · f. nueva'!T5 -> 75 | D8: 91 | E8: =C8-B8 -> -2 | F8: =D8-C8 -> 16 | G8: =D8-B8 -> 14 | H8: ='2 · Cálculo 2025 · f. antigua'!L5 -> 53 | I8: ='3 · Cálculo 2025 · f. nueva'!O5 -> 50 | J8: 81 | K8: ='2 · Cálculo 2025 · f. antigua'!S5 -> 100 | L8: 100 | M8: ='3 · Cálculo 2025 · f. nueva'!D5 -> 20 | N8: 100 | O8: ='3 · Cálculo 2025 · f. nueva'!F5 -> 75 | P8: 75 | Q8: ='3 · Cálculo 2025 · f. nueva'!H5 -> 66.666667 | R8: 100 | S8: ='3 · Cálculo 2025 · f. nueva'!L5 -> 38.888889 | T8: 55.6 | U8: ='3 · Cálculo 2025 · f. nueva'!M5 -> 50 | V8: 75
A9: CL | B9: ='2 · Cálculo 2025 · f. antigua'!T6 -> 57 | C9: ='3 · Cálculo 2025 · f. nueva'!T6 -> 57 | D9: 73 | E9: =C9-B9 -> 0 | F9: =D9-C9 -> 16 | G9: =D9-B9 -> 16 | H9: ='2 · Cálculo 2025 · f. antigua'!L6 -> 55 | I9: ='3 · Cálculo 2025 · f. nueva'!O6 -> 55 | J9: 69 | K9: ='2 · Cálculo 2025 · f. antigua'!S6 -> 59 | L9: 77 | M9: ='3 · Cálculo 2025 · f. nueva'!D6 -> 20 | N9: 60 | O9: ='3 · Cálculo 2025 · f. nueva'!F6 -> 50 | P9: 75 | Q9: ='3 · Cálculo 2025 · f. nueva'!H6 -> 66.666667 | R9: 66.7 | S9: ='3 · Cálculo 2025 · f. nueva'!L6 -> 63.888889 | T9: 69.4 | U9: ='3 · Cálculo 2025 · f. nueva'!M6 -> 75 | V9: 75
A10: CO | B10: ='2 · Cálculo 2025 · f. antigua'!T7 -> 85 | C10: ='3 · Cálculo 2025 · f. nueva'!T7 -> 82 | D10: 53 | E10: =C10-B10 -> -3 | F10: =D10-C10 -> -29 | G10: =D10-B10 -> -32 | H10: ='2 · Cálculo 2025 · f. antigua'!L7 -> 69 | I10: ='3 · Cálculo 2025 · f. nueva'!O7 -> 63 | J10: 56 | K10: ='2 · Cálculo 2025 · f. antigua'!S7 -> 100 | L10: 50 | M10: ='3 · Cálculo 2025 · f. nueva'!D7 -> 60 | N10: 60 | O10: ='3 · Cálculo 2025 · f. nueva'!F7 -> 50 | P10: 50 | Q10: ='3 · Cálculo 2025 · f. nueva'!H7 -> 66.666667 | R10: 66.7 | S10: ='3 · Cálculo 2025 · f. nueva'!L7 -> 88.888889 | T10: 77.8 | U10: ='3 · Cálculo 2025 · f. nueva'!M7 -> 50 | V10: 25
A11: CR | B11: ='2 · Cálculo 2025 · f. antigua'!T8 -> 46 | C11: ='3 · Cálculo 2025 · f. nueva'!T8 -> 45 | D11: 0 | E11: =C11-B11 -> -1 | F11: =D11-C11 -> -45 | G11: =D11-B11 -> -46 | H11: ='2 · Cálculo 2025 · f. antigua'!L8 -> 38 | I11: ='3 · Cálculo 2025 · f. nueva'!O8 -> 36 | J11: 0 | K11: ='2 · Cálculo 2025 · f. antigua'!S8 -> 53 | L11: 0 | M11: ='3 · Cálculo 2025 · f. nueva'!D8 -> 20 | N11: 0 | O11: ='3 · Cálculo 2025 · f. nueva'!F8 -> 50 | P11: 0 | Q11: ='3 · Cálculo 2025 · f. nueva'!H8 -> 66.666667 | R11: 0 | S11: ='3 · Cálculo 2025 · f. nueva'!L8 -> 19.444444 | T11: 0 | U11: ='3 · Cálculo 2025 · f. nueva'!M8 -> 25 | V11: 0
A12: CU | B12: ='2 · Cálculo 2025 · f. antigua'!T9 -> 0 | C12: ='3 · Cálculo 2025 · f. nueva'!T9 -> 0 | D12: 33 | E12: =C12-B12 -> 0 | F12: =D12-C12 -> 33 | G12: =D12-B12 -> 33 | H12: ='2 · Cálculo 2025 · f. antigua'!L9 -> 0 | I12: ='3 · Cálculo 2025 · f. nueva'!O9 -> 0 | J12: 34 | K12: ='2 · Cálculo 2025 · f. antigua'!S9 -> 0 | L12: 31 | M12: ='3 · Cálculo 2025 · f. nueva'!D9 -> 0 | N12: 40 | O12: ='3 · Cálculo 2025 · f. nueva'!F9 -> 0 | P12: 25 | Q12: ='3 · Cálculo 2025 · f. nueva'!H9 -> 0 | R12: 66.7 | S12: ='3 · Cálculo 2025 · f. nueva'!L9 -> 0 | T12: 11.1 | U12: ='3 · Cálculo 2025 · f. nueva'!M9 -> 0 | V12: 25
A13: DO | B13: ='2 · Cálculo 2025 · f. antigua'!T10 -> 30 | C13: ='3 · Cálculo 2025 · f. nueva'!T10 -> 32 | D13: 0 | E13: =C13-B13 -> 2 | F13: =D13-C13 -> -32 | G13: =D13-B13 -> -30 | H13: ='2 · Cálculo 2025 · f. antigua'!L10 -> 32 | I13: ='3 · Cálculo 2025 · f. nueva'!O10 -> 36 | J13: 0 | K13: ='2 · Cálculo 2025 · f. antigua'!S10 -> 28 | L13: 0 | M13: ='3 · Cálculo 2025 · f. nueva'!D10 -> 20 | N13: 0 | O13: ='3 · Cálculo 2025 · f. nueva'!F10 -> 25 | P13: 0 | Q13: ='3 · Cálculo 2025 · f. nueva'!H10 -> 66.666667 | R13: 0 | S13: ='3 · Cálculo 2025 · f. nueva'!L10 -> 44.444444 | T13: 0 | U13: ='3 · Cálculo 2025 · f. nueva'!M10 -> 25 | V13: 0
A14: EC | B14: ='2 · Cálculo 2025 · f. antigua'!T11 -> 25 | C14: ='3 · Cálculo 2025 · f. nueva'!T11 -> 27 | D14: 23 | E14: =C14-B14 -> 2 | F14: =D14-C14 -> -4 | G14: =D14-B14 -> -2 | H14: ='2 · Cálculo 2025 · f. antigua'!L11 -> 32 | I14: ='3 · Cálculo 2025 · f. nueva'!O11 -> 35 | J14: 35 | K14: ='2 · Cálculo 2025 · f. antigua'!S11 -> 18 | L14: 11 | M14: ='3 · Cálculo 2025 · f. nueva'!D11 -> 20 | N14: 20 | O14: ='3 · Cálculo 2025 · f. nueva'!F11 -> 25 | P14: 25 | Q14: ='3 · Cálculo 2025 · f. nueva'!H11 -> 66.666667 | R14: 66.7 | S14: ='3 · Cálculo 2025 · f. nueva'!L11 -> 36.111111 | T14: 36.1 | U14: ='3 · Cálculo 2025 · f. nueva'!M11 -> 25 | V14: 25
A15: GT | B15: ='2 · Cálculo 2025 · f. antigua'!T12 -> 33 | C15: ='3 · Cálculo 2025 · f. nueva'!T12 -> 34 | D15: 28 | E15: =C15-B15 -> 1 | F15: =D15-C15 -> -6 | G15: =D15-B15 -> -5 | H15: ='2 · Cálculo 2025 · f. antigua'!L12 -> 32 | I15: ='3 · Cálculo 2025 · f. nueva'!O12 -> 34 | J15: 39 | K15: ='2 · Cálculo 2025 · f. antigua'!S12 -> 33 | L15: 17 | M15: ='3 · Cálculo 2025 · f. nueva'!D12 -> 20 | N15: 20 | O15: ='3 · Cálculo 2025 · f. nueva'!F12 -> 25 | P15: 50 | Q15: ='3 · Cálculo 2025 · f. nueva'!H12 -> 66.666667 | R15: 66.7 | S15: ='3 · Cálculo 2025 · f. nueva'!L12 -> 33.333333 | T15: 33.3 | U15: ='3 · Cálculo 2025 · f. nueva'!M12 -> 25 | V15: 25
A16: HN | B16: ='2 · Cálculo 2025 · f. antigua'!T13 -> 42 | C16: ='3 · Cálculo 2025 · f. nueva'!T13 -> 43 | D16: 0 | E16: =C16-B16 -> 1 | F16: =D16-C16 -> -43 | G16: =D16-B16 -> -42 | H16: ='2 · Cálculo 2025 · f. antigua'!L13 -> 32 | I16: ='3 · Cálculo 2025 · f. nueva'!O13 -> 34 | J16: 0 | K16: ='2 · Cálculo 2025 · f. antigua'!S13 -> 52 | L16: 0 | M16: ='3 · Cálculo 2025 · f. nueva'!D13 -> 20 | N16: 0 | O16: ='3 · Cálculo 2025 · f. nueva'!F13 -> 25 | P16: 0 | Q16: ='3 · Cálculo 2025 · f. nueva'!H13 -> 66.666667 | R16: 0 | S16: ='3 · Cálculo 2025 · f. nueva'!L13 -> 33.333333 | T16: 0 | U16: ='3 · Cálculo 2025 · f. nueva'!M13 -> 25 | V16: 0
A17: JM | B17: ='2 · Cálculo 2025 · f. antigua'!T14 -> 0 | C17: ='3 · Cálculo 2025 · f. nueva'!T14 -> 0 | D17: 0 | E17: =C17-B17 -> 0 | F17: =D17-C17 -> 0 | G17: =D17-B17 -> 0 | H17: ='2 · Cálculo 2025 · f. antigua'!L14 -> 0 | I17: ='3 · Cálculo 2025 · f. nueva'!O14 -> 0 | J17: 0 | K17: ='2 · Cálculo 2025 · f. antigua'!S14 -> 0 | L17: 0 | M17: ='3 · Cálculo 2025 · f. nueva'!D14 -> 0 | N17: 0 | O17: ='3 · Cálculo 2025 · f. nueva'!F14 -> 0 | P17: 0 | Q17: ='3 · Cálculo 2025 · f. nueva'!H14 -> 0 | R17: 0 | S17: ='3 · Cálculo 2025 · f. nueva'!L14 -> 0 | T17: 0 | U17: ='3 · Cálculo 2025 · f. nueva'!M14 -> 0 | V17: 0
... A25: VE | B25: ='2 · Cálculo 2025 · f. antigua'!T22 -> 0 | C25: ='3 · Cálculo 2025 · f. nueva'!T22 -> 0 | D25: 17 | E25: =C25-B25 -> 0 | F25: =D25-C25 -> 17 | G25: =D25-B25 -> 17 | H25: ='2 · Cálculo 2025 · f. antigua'!L22 -> 0 | I25: ='3 · Cálculo 2025 · f. nueva'!O22 -> 0 | J25: 23 | K25: ='2 · Cálculo 2025 · f. antigua'!S22 -> 0 | L25: 11 | M25: ='3 · Cálculo 2025 · f. nueva'!D22 -> 0 | N25: 20 | O25: ='3 · Cálculo 2025 · f. nueva'!F22 -> 0 | P25: 25 | Q25: ='3 · Cálculo 2025 · f. nueva'!H22 -> 0 | R25: 33.3 | S25: ='3 · Cálculo 2025 · f. nueva'!L22 -> 0 | T25: 11.1 | U25: ='3 · Cálculo 2025 · f. nueva'!M22 -> 0 | V25: 25

Sheet 5 · Gráficos
A1: GRÁFICOS — todos leen los rangos de la pestaña «4 · Comparación» (recalculan al cambiar los datos)
A2: Azul = 2025 fórmula antigua · Verde = 2025 fórmula nueva · Magenta = 2026. V1-V5 existen como variables solo en la fórmula nueva (V1/V2 comparten definición con la antigua). Paleta verificada para daltonismo (ΔE CVD ≥ 8).
